Workbook

Sheet Logistics record 
A1: Move HK route from Starlink to UHAN's fwd | AC1: Tỷ giá | AD1: 26462
A2: UHAN Payment in Month | D2: 45658 | E2: 45689 | F2: 45717 | G2: 45748 | H2: 45778 | I2: 45809 | J2: 45839 | K2: 45870 | L2: 45901 | M2: 45931 | N2: 45962 | O2: 45992 | P2: 46023 | Q2: 46054 | R2: 46082 | S2: 46113 | T2: 46143 | U2: 46174
B3: Full logistics cost (Unigen pay) | D3: =D5-D4 -> 26480.584 | E3: =E5-E4 -> 26132.98 | F3: =F5-F4 -> 33641.018 | G3: =G5-G4 -> 33015.803 | H3: =H5-H4 -> 38983.797 | I3: =I5-I4 -> 44867.902 | J3: =J5-J4 -> 42915.709 | K3: =K5-K4 -> 62058.689 | ... N3: =N5-N4 -> 92101.001 | O3: 79951.99 | P3: 56495.208 | Q3: 40169.203 | R3: 35311.391 | S3: 31992.676 | T3: 34640.775 | U3: =U5-U4 -> 35866.719 | W3: Detail of raising: (SUM) | X3: Tracking/INV | Y3: Consignee/Shipper | Z3: =SUM(Z4:Z9) -> 385.45839
C4: Pay on behalf of others | D4: 4048.6692 | E4: 3024.6214 | F4: 7479.8127 | G4: 5886.7599 | H4: 11929.093 | I4: 2570.6327 | J4: 6520.1634 | K4: 2458.2838 | L4: 12377.15 | M4: 3933.3031 | N4: 3960.316 | O4: 8568.3017 | P4: 1696.0434 | Q4: 1329.7689 | R4: 4516.8992 | S4: 675.60553 | T4: 2752.5485 | U4: =Z13 -> 9194.6792 | W4: RMA | X4: INV06879 | Y4: MATAN DIGITAL PRINTERS 2001 LTD. | Z4: 15.116015
A5: Total Logistics cost (include pay on behalf of others) | D5: =SUM(D17+D50+D51+D52) -> 30529.253 | E5: =SUM(E17+E50+E51+E52) -> 29157.602 | F5: =SUM(F17+F50+F51+F52) -> 41120.831 | G5: =G17+G50+G51+G52 -> 38902.563 | H5: 50912.89 | I5: =I17+I50+I51+I52 -> 47438.535 | J5: =J17+J50+J51+J52 -> 49435.872 | K5: =K17+K50+K51+K52 -> 64516.973 | L5: =L17+L50+L51+L52 -> 79469.818 | M5: =M17+M50+M51+M52 -> 74219.52 | N5: =N17+N50+N51+N52 -> 96061.317 | O5: 88520.292 | P5: 58191.252 | Q5: 41498.972 | R5: 39828.291 | S5: 32668.282 | T5: 37393.323 | U5: =U17+U50+U51+U52 -> 45061.398 | W5: RMA | X5: INV06857 | Y5: Lucid USA, Inc.(CasaGrande Whse) | Z5: 15.116015
A6: Import | B6: Raw materials (Supplier to UHAN) | C6: Freight | D6: 15426.511 | E6: 20289.672 | F6: 23089.23 | G6: 26743.123 | H6: 30140.19 | I6: 27086.524 | J6: 30923.757 | K6: 42036.32 | L6: 47441.34 | M6: =45665.6558113536-546.52 -> 45119.136 | N6: 62891.245 | O6: 56967.015 | P6: 43467.765 | Q6: 27352.373 | R6: 26797.207 | S6: 22861.48 | T6: 21430.89 | U6: ='Debit Summary'!A6+'Debit Summary'!B6+'Debit Summary'!C6+'Debit Summary'!D6+'Debit Summary'!E6+'Debit Summary'!G6 -> 23157.228 | W6: RMA | X6: INV06840 | Y6: HELLA GmbH & Co. KGaA. | Z6: 15.116015
C7: Shipment No# | D7: ='Import material detail'!D2+'Import material detail'!D5+'Import material detail'!D11 -> 91 | E7: ='Import material detail'!E2+'Import material detail'!E5+'Import material detail'!E11 -> 119 | F7: ='Import material detail'!F2+'Import material detail'!F5+'Import material detail'!F11 -> 146 | G7: ='Import material detail'!G2+'Import material detail'!G5+'Import material detail'!G11 -> 153 | H7: 161 | I7: ='Import material detail'!I2+'Import material detail'!I5+'Import material detail'!I11 -> 197 | J7: ='Import material detail'!J2+'Import material detail'!J5+'Import material detail'!J11 -> 146 | K7: 240 | L7: 237 | M7: 262 | N7: ='Import material detail'!N2+'Import material detail'!N5+'Import material detail'!N11 -> 269 | O7: 263 | P7: 207 | Q7: 196 | R7: 156 | S7: 149 | T7: 112 | U7: ='Debit Summary'!A7+'Debit Summary'!B7+'Debit Summary'!C7+'Debit Summary'!D7+'Debit Summary'!E7+'Debit Summary'!G7 -> 171 | W7: Handle customs for wrong weight shipment | X7: INV06819 | Y7: AIC | Z7: =9000000/AD1 -> 340.11035
C8: Weight of Freight (KG) | D8: 10154.65 | E8: 14337.72 | F8: 12048.42 | G8: 18644.4 | H8: 25191.46 | I8: 21137.97 | J8: 25034.7 | K8: 40755.74 | L8: 37897.265 | M8: 45142.48 | N8: 47706.056 | O8: 55349.783 | P8: 35083.926 | Q8: 23788.92 | R8: 10237.445 | S8: 16565.673 | T8: 18241.364 | U8: =SUM('Debit Summary'!A8:G8) -> 15681.871 | W8: MRO Machine | X8: x | Y8: x | Z8: x
C9: Customs & Trucking fees | D9: =6907.35+451.2 -> 7358.55 | E9: =6595+144 -> 6739 | F9: 7641.0108 | G9: =7844.32+370.31 -> 8214.63 | H9: 9479.21 | I9: 10714.885 | J9: 11863.437 | K9: 15520.52 | L9: 18187.94 | M9: 20964.916 | N9: 19021.774 | O9: 17365.977 | P9: 10119.204 | Q9: 8249.5262 | R9: 7376.2303 | S9: 6542.1566 | T9: 9359.5515 | U9: ='Debit Summary'!A9+'Debit Summary'!B9+'Debit Summary'!C9+'Debit Summary'!D9+'Debit Summary'!E9+'Debit Summary'!G9 -> 17704.253
C10: Import declaration No# | D10: ='Import material detail'!D14 -> 251 | E10: ='Import material detail'!E14 -> 251 | F10: ='Import material detail'!F14 -> 290 | G10: ='Import material detail'!G14 -> 333 | H10: ='Import material detail'!H14 -> 312 | I10: ='Import material detail'!I14 -> 438 | J10: ='Import material detail'!J14 -> 515 | K10: ='Import material detail'!K14 -> 578 | L10: 596 | M10: 781 | N10: 788 | O10: 635 | P10: 381 | Q10: 331 | R10: 358 | S10: 289 | T10: 336 | U10: ='Debit Summary'!A10+'Debit Summary'!B10+'Debit Summary'!C10+'Debit Summary'!D10+'Debit Summary'!E10+'Debit Summary'!G10 -> 531
C11: Subtotal of Raw materials | D11: =D9+D6 -> 22785.061 | E11: =E9+E6 -> 27028.672 | F11: =F9+F6 -> 30730.24 | G11: =G9+G6 -> 34957.753 | H11: 39619.4 | I11: =I9+I6 -> 37801.409 | J11: =J9+J6 -> 42787.194 | K11: =K9+K6 -> 57556.84 | L11: =L9+L6 -> 65629.28 | M11: =M9+M6 -> 66084.052 | N11: =N9+N6 -> 81913.019 | O11: 74332.993 | P11: 53586.969 | Q11: 35601.9 | R11: 34173.438 | S11: 29403.637 | T11: 30790.442 | U11: =U9+U6 -> 40861.481
B12: Equipments + Toolings | C12: Freight | D12: 2740.032 | E12: 0 | F12: 2795.6731 | G12: 0 | H12: $ - | I12: 2112.75 | J12: 872.82 | K12: 1749.41 | L12: 6713.3374 | M12: 1061.9926 | N12: 5487.0877 | O12: 1293.5894 | P12: 86.048164 | Q12: 0 | R12: 13.906384 | S12: 544.54526 | T12: 1675.7718 | U12: ='Debit Summary'!A12+'Debit Summary'!B12+'Debit Summary'!C12+'Debit Summary'!D12+'Debit Summary'!E12+'Debit Summary'!G12 -> 669.35217 | Z12: Cost | AA12: Quote customer
C13: Weight of Freight (KG) | D13: 4220 KG | E13: 0 KG | F13: 3318 KG | G13: 0 | H13: $ - | I13: 5185 | J13: 1020 | K13: 4260 | L13: 14564 | M13: 383 | N13: 13995 | O13: 1293.5894 | P13: 0 | Q13: 0 | R13: 0 | S13: 82 | T13: 3959 | U13: =SUM('Debit Summary'!A13:G13) -> 288 | W13: UHAN pay on behalf of Others (SUM) | X13: Tracking/INV | Y13: Consignee/Shipper | Z13: =SUM(Z14:Z133) -> 9194.6792 | AA13: =SUM(AA14:AA133) -> 12000
C14: Customs & Trucking fees | D14: =240+1279.16 -> 1519.16 | E14: 132 | F14: 2523.0517 | G14: =244.835501147666+527.81+15.3 -> 787.9455 | H14: 752.28 | I14: 1779.4605 | J14: 408.9116 | K14: 1428.29 | L14: 895.02967 | M14: 1264.71 | N14: 2960.5659 | O14: 1801.4838 | P14: 887.50503 | Q14: 563.72795 | R14: 587.94503 | S14: 600.85229 | T14: 1743.3324 | U14: ='Debit Summary'!A14+'Debit Summary'!B14+'Debit Summary'!C14+'Debit Summary'!D14+'Debit Summary'!E14+'Debit Summary'!G14 -> 608.41933 | W14: PURE | X14: 8XN5256 | Y14: KIOXIA CORPORATION C/O KIOXIA AMERICA INC | Z14: 75.866526 | AA14: 100 | AB14: Victoria charge $100 to customer
C15: Subtotal of Equipments & Toolings | D15: =SUM(D12:D14) -> 4259.192 | E15: =SUM(E12:E14) -> 132 | F15: =SUM(F12:F14) -> 5318.7248 | G15: =SUM(G12:G14) -> 787.9455 | H15: 752.28 | I15: =I14+I12 -> 3892.2105 | J15: =J14+J12 -> 1281.7316 | K15: =K14+K12 -> 3177.7 | L15: =L14+L12 -> 7608.3671 | M15: =M14+M12 -> 2326.7026 | N15: =N14+N12 -> 8447.6537 | O15: 3095.0732 | P15: 973.5532 | Q15: 563.72795 | R15: 601.85141 | S15: 1145.3976 | T15: 3419.1043 | U15: =U14+U12 -> 1277.7715 | W15: PURE | X15: 8XN5262 | Y15: KIOXIA CORPORATION C/O KIOXIA AMERICA INC | Z15: 75.866526 | AA15: 100 | AB15: Victoria charge $100 to customer
C16: Other freight charges | F16: 2320 | H16: 819.98 | I16: 1880 | K16: 565.04 | L16: 1175.6229 | N16: 965.57992 | U16: =22000000/AD1 -> 831.38085 | W16: PURE | X16: 8XN5254 | Y16: KIOXIA CORPORATION C/O KIOXIA AMERICA INC | Z16: 75.866526 | AA16: 100 | AB16: Victoria charge $100 to customer
B17: Subtotal | D17: =D11+D15+D16 -> 27044.253 | E17: =E11+E15+E16 -> 27160.672 | F17: =F11+F15+F16 -> 38368.965 | G17: =G11+G15+G16 -> 35745.699 | H17: =H11+H15+H16 -> 41191.66 | I17: =I11+I15+I16 -> 43573.62 | J17: =J11+J15+J16 -> 44068.925 | K17: =K11+K15+K16 -> 61299.58 | ... N17: =N11+N15+N16 -> 91326.253 | O17: 77428.066 | P17: 54560.522 | Q17: 36165.628 | R17: 34775.289 | S17: 30549.034 | T17: 34209.546 | U17: =U11+U15+U16 -> 42970.633 | W17: PURE | X17: 8XN5259 | Y17: KIOXIA CORPORATION C/O KIOXIA AMERICA INC | Z17: 75.866526 | AA17: 100 | AB17: Victoria charge $100 to customer
A18: Export | B18: Transfer to HQ1, MY | C18: Freight | D18: 1742 | E18: 400.37184 | F18: 353.8289 | G18: 157.56094 | H18: 221.76339 | I18: 402.85 | J18: =737.03+2202.92 -> 2939.95 | K18: 308.84042 | L18: 1888.9864 | M18: 2401.1 | N18: =1219.9066716305-35.12 -> 1184.7867 | O18: 4463.5949 | P18: 475.29078 | Q18: 129.64758 | R18: 330.67037 | S18: 253.60432 | T18: 1156.3564 | U18: ='Debit Summary'!A18+'Debit Summary'!B18+'Debit Summary'!C18+'Debit Summary'!D18+'Debit Summary'!E18+'Debit Summary'!G18 -> 354.56802 | W18: PURE | X18: 8XN5270 | Y18: KIOXIA CORPORATION C/O KIOXIA AMERICA INC | Z18: 75.866526 | AA18: 100 | AB18: Victoria charge $100 to customer
C19: Weight of Freight | D19: 184.2 KG | E19: 53.9 KG | F19: 39.5 KG | G19: 10.2 KG | H19: 15.3 KG | I19: 44.5 KG | J19: 330 | K19: 22.2 | L19: 281.8 KG | M19: 379.9 | N19: 103.2 | O19: 1225.9 | P19: 41.4 | Q19: 8.4 | R19: 34.3 | S19: 21.1 | T19: 121 | U19: =SUM('Debit Summary'!A19:G19) -> 27 | W19: PURE | X19: 8XN5255 | Y19: KIOXIA CORPORATION C/O KIOXIA AMERICA INC | Z19: 75.866526 | AA19: 100 | AB19: Victoria charge $100 to customer
C20: Customs & Trucking fees | D20: =4190000/25000 -> 167.6 | E20: =2180000/25000 -> 87.2 | F20: 208.71914 | G20: =2410000/26140 -> 92.195868 | H20: 234.17239 | I20: 82.83 | J20: 201.89394 | K20: 130.33 | L20: =1930000/26369 -> 73.192006 | M20: =4110000/26388 -> 155.75261 | N20: 264.68249 | O20: 181.57695 | P20: 136.18975 | Q20: 221.23389 | R20: 193.07363 | S20: 193.04434 | T20: 140.50901 | U20: ='Debit Summary'!A20+'Debit Summary'!B20+'Debit Summary'!C20+'Debit Summary'!D20+'Debit Summary'!E20+'Debit Summary'!G20 -> 239.96674 | W20: PURE | X20: 8XN5912 | Y20: KIOXIA CORPORATION C/O KIOXIA AMERICA INC | Z20: 75.866526 | AA20: 100 | AB20: Victoria charge $100 to customer
C21: Subtotal of Transfer Raw Materials | D21: =SUM(D18:D20) -> 1909.6 | E21: =SUM(E18:E20) -> 487.57184 | F21: =SUM(F18:F20) -> 562.54803 | G21: =SUM(G18:G20) -> 249.75681 | H21: =SUM(H18:H20) -> 455.93577 | I21: =I20+I18 -> 485.68 | J21: =J20+J18 -> 3141.8439 | K21: =K20+K18 -> 439.17042 | L21: =L20+L18 -> 1962.1784 | M21: =M20+M18 -> 2556.8527 | N21: =N20+N18 -> 1449.4692 | O21: 4645.1718 | P21: 611.48053 | Q21: 350.88148 | R21: 523.744 | S21: 446.64865 | T21: 1296.8654 | U21: =U20+U18 -> 594.53477 | W21: PURE | X21: 8XN5273 | Y21: KIOXIA CORPORATION C/O KIOXIA AMERICA INC | Z21: 75.866526 | AA21: 100 | AB21: Victoria charge $100 to customer
B22: LUCID | C22: Freight | D22: 101 | E22: 58.71316 | F22: 81.018519 | G22: 0 | H22: 8129.72 | I22: 0 | J22: 50.73467 | K22: 0 | L22: 0 | M22: 0 | N22: 0 | O22: 1755.0862 | P22: 28.417521 | Q22: 28.724408 | R22: 1974.1019 | S22: 22.441992 | T22: 0 | U22: ='Debit Summary'!A22+'Debit Summary'!B22+'Debit Summary'!C22+'Debit Summary'!D22+'Debit Summary'!E22+'Debit Summary'!G22 -> 0 | W22: PURE | X22: 8XN5266 | Y22: KIOXIA CORPORATION C/O KIOXIA AMERICA INC | Z22: 75.866526 | AA22: 100 | AB22: Victoria charge $100 to customer
C23: Weight of Freight | D23: 5.8 KG | E23: 3.6 KG | F23: 21.7 KG | G23: 0 | H23: 1138 KG | I23: 0 KG | J23: 0.6 | K23: 0 | L23: 0 | M23: 0 | N23: 0 | O23: 2.7 | P23: 1.1 | Q23: 0.8 | R23: 249.6 | S23: 0.3 | T23: 0 | U23: =SUM('Debit Summary'!A23:G23) -> 0 | W23: PURE | X23: 8XN5252 | Y23: KIOXIA CORPORATION C/O KIOXIA AMERICA INC | Z23: 75.866526 | AA23: 100 | AB23: Victoria charge $100 to customer
C24: Customs & Trucking fees | D24: =2000000/25000 -> 80 | E24: =7890000/25000 -> 315.6 | F24: 136.18827 | G24: =3200000/26140 -> 122.41775 | H24: 195.65217 | I24: 121.58 | J24: 203.78788 | K24: 210.95 | L24: =(19130000+700000)/26369 -> 752.01942 | M24: =18108000/26388 -> 686.22101 | N24: =1179.50202582453+339.74 -> 1519.242 | O24: 794.94428 | P24: 622.55761 | Q24: 508.60988 | R24: 529.1507 | S24: 383.43384 | T24: 285.18406 | U24: ='Debit Summary'!A24+'Debit Summary'!B24+'Debit Summary'!C24+'Debit Summary'!D24+'Debit Summary'!E24+'Debit Summary'!G24 -> 211.62422 | W24: PURE | X24: 8XN5275 | Y24: KIOXIA CORPORATION C/O KIOXIA AMERICA INC | Z24: 75.866526 | AA24: 100 | AB24: Victoria charge $100 to customer
C25: Subtotal of FG Lucid | D25: =SUM(D22:D24) -> 181 | E25: =SUM(E22:E24) -> 374.31316 | F25: =SUM(F22:F24) -> 217.20679 | G25: =SUM(G22:G24) -> 122.41775 | H25: =SUM(H22:H24) -> 8325.3722 | I25: =I24+I22 -> 121.58 | J25: =J24+J22 -> 254.52255 | K25: =K24+K22 -> 210.95 | L25: =L24+L22 -> 752.01942 | M25: =M24+M22 -> 686.22101 | N25: =N24+N22 -> 1519.242 | O25: 2550.0305 | P25: 650.97513 | Q25: 537.33428 | R25: 2503.2526 | S25: 405.87583 | T25: 285.18406 | U25: =U24+U22 -> 211.62422 | W25: PURE | X25: 8XN5253 | Y25: KIOXIA CORPORATION C/O KIOXIA AMERICA INC | Z25: 75.866526 | AA25: 100 | AB25: Victoria charge $100 to customer
B26: AGIGA | C26: Freight | D26: 82 | E26: 210.99108 | F26: 198.15988 | G26: 88 | H26: 77.493631 | I26: 0 | J26: 0 | K26: 52.3 | L26: 0 | M26: 0 | N26: 0 | O26: 0 | P26: 0 | Q26: 0 | R26: 0 | S26: 0 | T26: 0 | U26: ='Debit Summary'!A26+'Debit Summary'!B26+'Debit Summary'!C26+'Debit Summary'!D26+'Debit Summary'!E26+'Debit Summary'!G26 -> 0 | W26: PURE | X26: 8XN5264 | Y26: KIOXIA CORPORATION C/O KIOXIA AMERICA INC | Z26: 75.866526 | AA26: 100 | AB26: Victoria charge $100 to customer
C27: Weight of Freight | D27: 7.8 KG | E27: 16.4 KG | F27: 15.6 KG | G27: 4.6 KG | H27: 11.6 KG | I27: 0 KG | J27: 0 | K27: 2.4 | L27: 0 | M27: 0 | N27: 0 | U27: =SUM('Debit Summary'!A27:G27) -> 0 | W27: PURE | X27: 8XN5258 | Y27: KIOXIA CORPORATION C/O KIOXIA AMERICA INC | Z27: 75.866526 | AA27: 100 | AB27: Victoria charge $100 to customer
C28: Customs & Trucking fees | D28: =3450000/25000 -> 138 | E28: =1930000/25000 -> 77.2 | F28: 74.459877 | G28: =1930000/26140 -> 73.833206 | H28: 24.790236 | I28: 15.2 | J28: 0 | K28: 24.484876 | L28: move to OEM | M28: move to OEM | N28: move to OEM | O28: move to OEM | P28: move to OEM | Q28: move to OEM | R28: move to OEM | S28: move to OEM | T28: move to OEM | U28: move to OEM | W28: PURE | X28: 8XN5257 | Y28: KIOXIA CORPORATION C/O KIOXIA AMERICA INC | Z28: 75.866526 | AA28: 100 | AB28: Victoria charge $100 to customer
C29: Subtotal of FG AGIGA | D29: =SUM(D26:D28) -> 220 | E29: =SUM(E26:E28) -> 288.19108 | F29: =SUM(F26:F28) -> 272.61975 | G29: =SUM(G26:G28) -> 161.83321 | H29: =SUM(H26:H28) -> 102.28387 | I29: =SUM(I26:I28) -> 15.2 | J29: =SUM(J26:J28) -> 0 | K29: =SUM(K26:K28) -> 79.184876 | ... N29: =SUM(N26:N28) -> 0 | O29: 0 | P29: 0 | Q29: 0 | R29: 0 | S29: 0 | T29: 0 | U29: =SUM(U26:U28) -> 0 | W29: PURE | X29: 8XN5268 | Y29: KIOXIA CORPORATION C/O KIOXIA AMERICA INC | Z29: 75.866526 | AA29: 100 | AB29: Victoria charge $100 to customer
B30: EFI | C30: Freight | D30: 0 | E30: 0 | F30: 228.65328 | G30: 0 | H30: 0 | I30: =109.42+1540.17 -> 1649.59 | J30: =103.64+391.75 -> 495.39 | K30: 772.93 | L30: 0 | M30: 0 | O30: 0 | P30: 873.91243 | Q30: 72.426008 | R30: 0 | S30: 0 | T30: 0 | U30: ='Debit Summary'!A30+'Debit Summary'!B30+'Debit Summary'!C30+'Debit Summary'!D30+'Debit Summary'!E30+'Debit Summary'!G30 -> 0 | W30: PURE | X30: 8XN5271 | Y30: KIOXIA CORPORATION C/O KIOXIA AMERICA INC | Z30: 75.866526 | AA30: 100 | AB30: Victoria charge $100 to customer
C31: Weight of Freight | D31: 0 | E31: 0 | F31: 27.3 KG | I31: 196.9 KG | J31: 9.2 | K31: 61.5 | L31: 0 | M31: 0 | O31: 0 | P31: 93 | Q31: 4.9 | R31: 0 | S31: 0 | T31: 0 | U31: =SUM('Debit Summary'!A31:G31) -> 0 | W31: PURE | X31: 8XN5272 | Y31: KIOXIA CORPORATION C/O KIOXIA AMERICA INC | Z31: 75.866526 | AA31: 100 | AB31: Victoria charge $100 to customer
C32: Customs fees & Trucking for Inspection by Customs | D32: =2400000/25000+45.2 -> 141.2 | E32: =800000/25000 -> 32 | F32: 114.96914 | G32: =400000/26140 -> 15.302219 | H32: 201.373 | I32: 60.79 | J32: 204.92424 | K32: 87.77 | L32: =400000/26369 -> 15.169328 | M32: =800000/26388 -> 30.316811 | N32: 60.585406 | O32: 233.51024 | P32: 119.73986 | Q32: 39.913331 | R32: 0 | S32: 58.027079 | T32: 15.14922 | U32: ='Debit Summary'!A32+'Debit Summary'!B32+'Debit Summary'!C32+'Debit Summary'!D32+'Debit Summary'!E32+'Debit Summary'!G32 -> 90.696093 | W32: PURE | X32: 8XN5904 | Y32: KIOXIA CORPORATION C/O KIOXIA AMERICA INC | Z32: 75.866526 | AA32: 100 | AB32: Victoria charge $100 to customer
C33: Fees paid to EFI's fwd (term FOB) | D33: 0 | E33: 0 | F33: 0 | G33: 0 | H33: 0 | I33: 0 | J33: 0 | K33: 0 | L33: 0 | M33: 0 | W33: PURE | X33: 8XN5907 | Y33: KIOXIA CORPORATION C/O KIOXIA AMERICA INC | Z33: 75.866526 | AA33: 100 | AB33: Victoria charge $100 to customer
C34: Subtotal of EFI | D34: =D30+D32+D33 -> 141.2 | E34: =E30+E32+E33 -> 32 | F34: =F30+F32+F33 -> 343.62242 | G34: =G30+G32+G33 -> 15.302219 | H34: =H30+H32+H33 -> 201.373 | I34: =I30+I32+I33 -> 1710.38 | J34: =J30+J32+J33 -> 700.31424 | K34: =K30+K32+K33 -> 860.7 | ... N34: =N30+N32+N33 -> 60.585406 | O34: 233.51024 | P34: 993.6523 | Q34: 112.33934 | R34: 0 | S34: 58.027079 | T34: 15.14922 | U34: =U30+U32+U33 -> 90.696093 | W34: PURE | X34: 8XN5906 | Y34: KIOXIA CORPORATION C/O KIOXIA AMERICA INC | Z34: 75.866526 | AA34: 100 | AB34: Victoria charge $100 to customer
B35: PURE | C35: Freight (For RMA shipment) | F35: 165.89506 | G35: 311 | H35: 45.995767 | I35: 280.18 | J35: 272.2551 | K35: 179.99376 | L35: 198.88331 | M35: =10240094/26388 -> 388.05874 | N35: 83.395927 | O35: 43.756825 | P35: 62.842464 | Q35: 69.856198 | R35: 687.23237 | S35: 61.328213 | T35: 302.52233 | U35: ='Debit Summary'!A35+'Debit Summary'!B35+'Debit Summary'!C35+'Debit Summary'!D35+'Debit Summary'!E35+'Debit Summary'!G35 -> 79.008767 | W35: PURE | X35: 8XN5267 | Y35: KIOXIA CORPORATION C/O KIOXIA AMERICA INC | Z35: 75.866526 | AA35: 100 | AB35: Victoria charge $100 to customer
C36: Weight of Freight | F36: 20 KG | G36: 34 KG | H36: 11.2 KG | I36: 28.8 KG | J36: 22.1 | K36: 13 | L36: 14.6 KG | M36: 33.5 | N36: 6.2 | O36: 2.2 | P36: 12.4 | Q36: 2 | R36: 2.8 | S36: 3 | T36: 10.6 | U36: =SUM('Debit Summary'!A36:G36) -> 2.3 | W36: PURE | X36: 8XN5263 | Y36: KIOXIA CORPORATION C/O KIOXIA AMERICA INC | Z36: 75.866526 | AA36: 100 | AB36: Victoria charge $100 to customer
C37: Customs fees & Trucking for Inspection by Customs | D37: =2000000/25000 -> 80 | E37: =3130000/25000 -> 125.2 | F37: 717.20679 | G37: =3800000/26140 -> 145.37108 | H37: 83.142639 | I37: 272.42 | J37: =271.59+60 -> 331.59 | K37: 499.11 | L37: =18280000/26369 -> 693.23827 | M37: =9160000/26388 -> 347.12748 | N37: 343.06486 | O37: 383.62396 | P37: 257.45983 | Q37: 237.95948 | R37: 480.21849 | S37: 478.62859 | T37: 627.55643 | U37: ='Debit Summary'!A37+'Debit Summary'!B37+'Debit Summary'!C37+'Debit Summary'!D37+'Debit Summary'!E37+'Debit Summary'!G37 -> 213.51372 | W37: PURE | X37: 8XN5265 | Y37: KIOXIA CORPORATION C/O KIOXIA AMERICA INC | Z37: 75.866526 | AA37: 100 | AB37: Victoria charge $100 to customer
C38: Subtotal of FG Pure | D38: =D35+D37 -> 80 | E38: =E35+E37 -> 125.2 | F38: =F35+F37 -> 883.10185 | G38: =G35+G37 -> 456.37108 | H38: =H35+H37 -> 129.13841 | I38: =I35+I37 -> 552.6 | J38: =J35+J37 -> 603.8451 | K38: =K35+K37 -> 679.10376 | ... N38: =N35+N37 -> 426.46079 | O38: 427.38078 | P38: 320.3023 | Q38: 307.81568 | R38: 1167.4509 | S38: 539.9568 | T38: 930.07876 | U38: =U35+U37 -> 292.52249 | W38: PURE | X38: 8XN5910 | Y38: KIOXIA CORPORATION C/O KIOXIA AMERICA INC | Z38: 75.866526 | AA38: 100 | AB38: Victoria charge $100 to customer
B39: AIC | C39: Freight | E39: 63.89112 | F39: 0 | G39: 0 | H39: 0 | I39: 0 | J39: 0 | K39: 0 | L39: 0 | M39: =2105236/26388 -> 79.780052 | N39: 0 | O39: 0 | P39: 0 | Q39: 0 | R39: 0 | S39: 0 | T39: 0 | U39: ='Debit Summary'!A39+'Debit Summary'!B39+'Debit Summary'!C39+'Debit Summary'!D39+'Debit Summary'!E39+'Debit Summary'!G39 -> 0 | W39: PURE | X39: 8XN5274 | Y39: KIOXIA CORPORATION C/O KIOXIA AMERICA INC | Z39: 75.866526 | AA39: 100 | AB39: Victoria charge $100 to customer
C40: Weight of Freight | E40: 16.5 KG | F40: 0 KG | G40: 0 KG | H40: 0 KG | I40: 0 KG | J40: 0 | K40: 0 | L40: 0 | M40: 10.1 | N40: 0 | O40: 0 | P40: 0 | Q40: 0 | R40: 0 | S40: 0 | T40: 0 | U40: =SUM('Debit Summary'!A40:G40) -> 0 | W40: PURE | X40: 8XN5908 | Y40: KIOXIA CORPORATION C/O KIOXIA AMERICA INC | Z40: 75.866526 | AA40: 100 | AB40: Victoria charge $100 to customer
C41: Customs & Trucking fees | E41: =2010000/25000 -> 80.4 | F41: 15.432099 | G41: 0 | H41: 0 | I41: 0 | J41: 0 | K41: 45.2 | L41: =6640000/26369 -> 251.81084 | M41: =2600000/26388 -> 98.529635 | N41: 42.788443 | O41: 0 | P41: 141.92808 | Q41: 24.708253 | R41: 0 | S41: 58.027079 | T41: 0 | U41: =SUM('Debit Summary'!A41:G41) -> 355.22636 | W41: PURE | X41: 8XN5279 | Y41: KIOXIA CORPORATION C/O KIOXIA AMERICA INC | Z41: 75.866526 | AA41: 100 | AB41: Victoria charge $100 to customer
C42: Subtotal of AIC | D42: =SUM(D41+D39) -> 0 | E42: =SUM(E41+E39) -> 144.29112 | F42: =SUM(F41+F39) -> 15.432099 | G42: =SUM(G41+G39) -> 0 | H42: =SUM(H41+H39) -> 0 | I42: =SUM(I41+I39) -> 0 | J42: =SUM(J41+J39) -> 0 | K42: =SUM(K41+K39) -> 45.2 | ... N42: =SUM(N41+N39) -> 42.788443 | O42: 0 | P42: 141.92808 | Q42: 24.708253 | R42: 0 | S42: 58.027079 | T42: 0 | U42: =SUM(U41+U39) -> 355.22636 | W42: PURE | X42: 8XN5909 | Y42: KIOXIA CORPORATION C/O KIOXIA AMERICA INC | Z42: 75.866526 | AA42: 100 | AB42: Victoria charge $100 to customer
B43: FORD | C43: Freight | T43: 0 | U43: ='Debit Summary'!A43+'Debit Summary'!B43+'Debit Summary'!C43+'Debit Summary'!D43+'Debit Summary'!E43+'Debit Summary'!G43 -> 112.95749 | W43: PURE | X43: 8XN5277 | Y43: KIOXIA CORPORATION C/O KIOXIA AMERICA INC | Z43: 75.866526 | AA43: 100 | AB43: Victoria charge $100 to customer
C44: Weight of Freight | T44: 0 | U44: =SUM('Debit Summary'!A44:G44) -> 3.5 | W44: PURE | X44: 8XN5261 | Y44: KIOXIA CORPORATION C/O KIOXIA AMERICA INC | Z44: 75.866526 | AA44: 100 | AB44: Victoria charge $100 to customer
C45: Customs & Trucking fees | T45: 0 | U45: ='Debit Summary'!A45+'Debit Summary'!B45+'Debit Summary'!C45+'Debit Summary'!D45+'Debit Summary'!E45+'Debit Summary'!G45 -> 0 | W45: PURE | X45: 8XN5260 | Y45: KIOXIA CORPORATION C/O KIOXIA AMERICA INC | Z45: 75.866526 | AA45: 100 | AB45: Victoria charge $100 to customer
C46: Subtotal of Ford | D46: =SUM(D45+D43) -> 0 | E46: =SUM(E45+E43) -> 0 | F46: =SUM(F45+F43) -> 0 | G46: =SUM(G45+G43) -> 0 | H46: =SUM(H45+H43) -> 0 | I46: =SUM(I45+I43) -> 0 | J46: =SUM(J45+J43) -> 0 | K46: =SUM(K45+K43) -> 0 | ... S46: =SUM(S45+S43) -> 0 | T46: 0 | U46: =SUM(U45+U43) -> 112.95749 | W46: PURE | X46: 8XN5269 | Y46: KIOXIA CORPORATION C/O KIOXIA AMERICA INC | Z46: 75.866526 | AA46: 100 | AB46: Victoria charge $100 to customer
B47: Other shipment (To UTPE, return to supplier, return equipment to HQ, OEM…) | C47: Customs & Trucking fees | D47: =7710000/25000+213.6 -> 522 | E47: =(2800000+1130000)/25000 -> 157.2 | F47: 163.96605 | G47: =(5200000+1130000)/26140 -> 242.15761 | H47: 195.65217 | I47: 488.98 | J47: 88.257576 | K47: 350.32 | L47: =9130000/26369 -> 346.2399 | M47: =10250000/26388+67.46 -> 455.89414 | N47: =433.942973986141-55.275 -> 378.66797 | O47: 595.14784 | P47: 421.95868 | Q47: 3401.3237 | R47: 202.55661 | S47: 147.15364 | T47: 54.915922 | U47: ='Debit Summary'!A47+'Debit Summary'!B47+'Debit Summary'!C47+'Debit Summary'!D47+'Debit Summary'!E47+'Debit Summary'!G47 -> 47.237548 | W47: PURE | X47: 8XN5280 | Y47: KIOXIA CORPORATION C/O KIOXIA AMERICA INC | Z47: 75.866526 | AA47: 100 | AB47: Victoria charge $100 to customer
B48: Other freight charges | C48: Other freight charges | D48: 108 | E48: 132.16296 | F48: 66.517052 | G48: =77+1192.63 -> 1269.63 | H48: 17.04 | I48: 209.34 | J48: =17.67+45.91 -> 63.58 | K48: 136.14427 | L48: 130.87599 | M48: =16907992/26388 -> 640.74549 | N48: =319.584521583551-249.344 -> 70.240522 | O48: 2017.4064 | P48: 113.99823 | Q48: 218.05421 | R48: 115.84645 | S48: 220.07202 | T48: 413.35497 | U48: ='Debit Summary'!A48+'Debit Summary'!B48+'Debit Summary'!C48+'Debit Summary'!D48+'Debit Summary'!E48+'Debit Summary'!G48 -> 151.28962 | W48: PURE | X48: 8XN5282 | Y48: KIOXIA CORPORATION C/O KIOXIA AMERICA INC | Z48: 75.866526 | AA48: 100 | AB48: Victoria charge $100 to customer
C49: Subtotal of Other charges | D49: =SUM(D47:D48) -> 630 | E49: =SUM(E47:E48) -> 289.36296 | F49: =SUM(F47:F48) -> 230.4831 | G49: =SUM(G47:G48) -> 1511.7876 | H49: =SUM(H47:H48) -> 212.69217 | I49: =SUM(I47:I48) -> 698.32 | J49: =SUM(J47:J48) -> 151.83758 | K49: =SUM(K47:K48) -> 486.46427 | ... N49: =SUM(N47:N48) -> 448.9085 | O49: 2612.5543 | P49: 535.95691 | Q49: 3619.3779 | R49: 318.40306 | S49: 367.22566 | T49: 468.27089 | U49: =SUM(U47:U48) -> 198.52717 | W49: PURE | X49: 8XN5278 | Y49: KIOXIA CORPORATION C/O KIOXIA AMERICA INC | Z49: 75.866526 | AA49: 100 | AB49: Victoria charge $100 to customer
B50: Subtotal | D50: =D49+D38+D29+D25+D21+D34+D42 -> 3161.8 | E50: =E49+E38+E29+E25+E21+E34+E42 -> 1740.9302 | F50: =F49+F38+F29+F25+F21+F34+F42 -> 2525.014 | G50: =G49+G38+G29+G25+G21+G34+G42 -> 2517.4687 | H50: =H49+H38+H29+H25+H21+H34+H42 -> 9426.7954 | I50: =I49+I38+I29+I25+I21+I34+I42 -> 3583.76 | J50: =J49+J38+J29+J25+J21+J34+J42 -> 4852.3634 | K50: =K49+K38+K29+K25+K21+K34+K42 -> 2800.7733 | ... N50: =N49+N38+N29+N25+N21+N34+N42 -> 3947.4543 | O50: 10468.648 | P50: 3254.2952 | Q50: 4952.4569 | R50: 4512.8505 | S50: 1875.7611 | T50: 2995.5484 | U50: =U49+U38+U29+U25+U21+U34+U42+U46 -> 1856.0886 | W50: PURE | X50: 8XN5905 | Y50: KIOXIA CORPORATION C/O KIOXIA AMERICA INC | Z50: 75.866526 | AA50: 100 | AB50: Victoria charge $100 to customer
A51: Customs fees in Month | D51: =8080000/25000 -> 323.2 | E51: 256 | F51: 226.85185 | G51: 294.56771 | H51: 294.43173 | I51: =7400000/26320 -> 281.15502 | J51: =10940000/26400 -> 414.39394 | K51: 416.61958 | L51: 706.1322 | M51: 525.23874 | N51: =20800000/26409 -> 787.61028 | O51: 623.57847 | P51: 376.43458 | Q51: 380.88722 | R51: 198.76342 | S51: 243.48618 | T51: 188.22906 | U51: ='Debit Summary'!A51+'Debit Summary'!B51+'Debit Summary'!C51+'Debit Summary'!D51+'Debit Summary'!E51+'Debit Summary'!G51 -> 234.67614 | W51: PURE | X51: 8XN5276 | Y51: KIOXIA CORPORATION C/O KIOXIA AMERICA INC | Z51: 75.866526 | AA51: 100 | AB51: Victoria charge $100 to customer
A52: Others | G52: =9000000/26100 -> 344.82759 | J52: =2645000/26400 -> 100.18939 | R52: 341.38755 | W52: PURE | X52: 8XN5281 | Y52: KIOXIA CORPORATION C/O KIOXIA AMERICA INC | Z52: 75.866526 | AA52: 100 | AB52: Victoria charge $100 to customer
W53: PURE | X53: 8XN5911 | Y53: KIOXIA CORPORATION C/O KIOXIA AMERICA INC | Z53: 75.866526 | AA53: 100 | AB53: Victoria charge $100 to customer
W54: PURE | X54: 8XN5902 | Y54: KIOXIA CORPORATION C/O KIOXIA AMERICA INC | Z54: 98.540549 | AA54: 100 | AB54: Victoria charge $100 to customer
W55: PURE | X55: 8XN5903 | Y55: KIOXIA CORPORATION C/O KIOXIA AMERICA INC | Z55: 75.866526 | AA55: 100 | AB55: Victoria charge $100 to customer
W56: PURE | X56: 8XN5984 | Y56: KIOXIA CORPORATION C/O KIOXIA AMERICA INC | Z56: 75.866526 | AA56: 100 | AB56: Victoria charge $100 to customer
W57: PURE | X57: 8XN5981 | Y57: KIOXIA CORPORATION C/O KIOXIA AMERICA INC | Z57: 75.866526 | AA57: 100 | AB57: Victoria charge $100 to customer
W58: PURE | X58: 8XN5985 | Y58: KIOXIA CORPORATION C/O KIOXIA AMERICA INC | Z58: 75.866526 | AA58: 100 | AB58: Victoria charge $100 to customer
W59: PURE | X59: 8XN5982 | Y59: KIOXIA CORPORATION C/O KIOXIA AMERICA INC | Z59: 75.866526 | AA59: 100 | AB59: Victoria charge $100 to customer
W60: PURE | X60: 8XN5980 | Y60: KIOXIA CORPORATION C/O KIOXIA AMERICA INC | Z60: 75.866526 | AA60: 100 | AB60: Victoria charge $100 to customer
W61: PURE | X61: 8XN5986 | Y61: KIOXIA CORPORATION C/O KIOXIA AMERICA INC | Z61: 98.540549 | AA61: 100 | AB61: Victoria charge $100 to customer
W62: PURE | X62: 8XN5978 | Y62: KIOXIA CORPORATION C/O KIOXIA AMERICA INC | Z62: 75.866526 | AA62: 100 | AB62: Victoria charge $100 to customer
W63: PURE | X63: 8XN5983 | Y63: KIOXIA CORPORATION C/O KIOXIA AMERICA INC | Z63: 75.866526 | AA63: 100 | AB63: Victoria charge $100 to customer
W64: PURE | X64: 8XN5979 | Y64: KIOXIA CORPORATION C/O KIOXIA AMERICA INC | Z64: 75.866526 | AA64: 100 | AB64: Victoria charge $100 to customer
... W133: PURE | X133: 8XN6107 | Y133: KIOXIA CORPORATION C/O KIOXIA AMERICA INC | Z133: 98.540549 | AA133: 100 | AB133: Victoria charge $100 to customer

Sheet Debit Summary
A1: Của sheet Logistics Record | S1: FedEx | T1: VVMV | U1: Dolphin | V1: EI | W1: DHL
A2: FedEx | B2: VVMV | C2: Dolphin | D2: EI | E2: Gia Bảo | F2: Evergreen | G2: DHL | T2: =COUNTIFS(VVMV!F:F,"raw materials",VVMV!N:N,"Air",VVMV!L:L,">0") -> 2 | U2: =COUNTIFS(Dolphin!H:H,"Air",Dolphin!G:G,"Raw materials") -> 0 | V2: =COUNTIFS(EI!F:F,"air import",EI!AY:AY,"Raw materials") -> 5
T3: =SUMIFS(VVMV!T:T,VVMV!F:F,"Raw materials",VVMV!N:N,"Air",VVMV!L:L,">0") -> 501 | U3: =SUMIFS(Dolphin!K:K,Dolphin!H:H,"Air",Dolphin!G:G,"Raw materials") -> 0 | V3: =SUMIFS(EI!M:M,EI!F:F,"air import",EI!AY:AY,"Raw materials") -> 594
I4: Double check | T4: =SUMIFS(VVMV!L:L,VVMV!F:F,"Raw materials",VVMV!N:N,"Air",VVMV!L:L,">0") -> 927.25482 | U4: ='FWD Detail'!BV50 -> 0 | V4: =SUMIFS(EI!AV:AV,EI!F:F,"air import",EI!AY:AY,"Raw materials") -> 1435.3751 | W4: =SUMIFS(EI!AW:AW,EI!G:G,"air import",EI!AZ:AZ,"Raw materials") -> 0
J5: fedex | K5: Ei | L5: dolphin | M5: vvmv | N5: DHL | O5: Evergreen | P5: Gia Bảo | Q5: Total | S5: =COUNTIF('FedEx Import'!S:S,"raw materials") -> 138
A6: =SUMIF('FedEx Import'!S:S,"Raw materials",'FedEx Import'!R:R) -> 9743.2527 | B6: =SUMIFS(VVMV!L:L,VVMV!E:E,"Import",VVMV!F:F,"Raw materials") -> 7975.643 | C6: =(SUMIF(Dolphin!G:G,"Raw materials",Dolphin!Q:Q)+SUMIF(Dolphin!G:G,"Raw materials",Dolphin!R:R)+SUMIF(Dolphin!G:G,"Raw materials",Dolphin!S:S)+SUMIF(Dolphin!G:G,"Raw materials",Dolphin!W:W))/'Logistics record '!AD1 -> 1899.1301 | D6: =SUMIFS(EI!AV:AV,EI!AX:AX,"import",EI!AY:AY,"Raw materials") -> 1435.3751 | G6: =SUMIF(DHL!C:C,"raw materials",DHL!W:W) -> 2103.8266 | I6: Xuất | J6: =SUM('FedEx Export'!AC:AC) -> 584.86641 | M6: =SUMIF(VVMV!E:E,"Export",VVMV!O:O) -> 818.15433 | N6: =SUMIF(DHL!B:B,"Export",DHL!W:W) -> 112.95749 | O6: =9000000/'Logistics record '!AD1 -> 340.11035 | Q6: =SUM(J6:P6) -> 1856.0886 | S6: =SUMIF('FedEx Import'!S:S,"raw materials",'FedEx Import'!L:L) -> 2534.8
A7: =COUNTIF('FedEx Import'!S:S,"raw materials") -> 138 | B7: =COUNTIFS(VVMV!F:F,"Raw materials",VVMV!L:L,">0") -> 14 | C7: =COUNTIF(Dolphin!G:G,"Raw materials") -> 4 | D7: =COUNTIF(EI!AY:AY,"Raw materials") -> 5 | G7: =COUNTIF(DHL!C:C,"Raw materials") -> 10 | J7: =J6*'Logistics record '!$AD$1 -> 15476735 | M7: =M6*'Logistics record '!$AD$1 -> 21650000 | S7: =SUMIF('FedEx Import'!S:S,"raw materials",'FedEx Import'!R:R) -> 9743.2527
A8: =SUMIF('FedEx Import'!S:S,"Raw materials",'FedEx Import'!L:L) -> 2534.8 | B8: =SUMIFS(VVMV!T:T,VVMV!F:F,"Raw materials",VVMV!L:L,">0") -> 9551.971 | C8: =SUMIF(Dolphin!G:G,"Raw materials",Dolphin!K:K) -> 2829.1 | D8: =SUMIF(EI!AY:AY,"Raw materials",EI!N:N) -> 586 | G8: =SUMIF(DHL!C:C,"Raw materials",DHL!O:O) -> 180 | I8: Nhập | J8: =SUM('FedEx Import'!R:R) -> 9743.2527 | K8: =SUM(EI!AV:AV) -> 2104.7273 | L8: =SUM(Dolphin!Y18:Y21)/'Logistics record '!$AD$1 -> 2192.3808 | M8: =SUMIF(VVMV!E:E,"import",VVMV!O:O) -> 25995.065 | N8: =SUMIF(DHL!B:B,"import",DHL!W:W) -> 2103.8266 | P8: =22000000/'Logistics record '!AD1 -> 831.38085 | Q8: =SUM(J8:P8) -> 42970.633 | W8: =COUNTIF(DHL!C:C,"Raw materials") -> 10
B9: =SUMIFS(VVMV!J:J,VVMV!E:E,"import",VVMV!F:F,"Raw materials")+SUMIFS(VVMV!K:K,VVMV!E:E,"import",VVMV!F:F,"Raw materials")+SUMIFS(VVMV!M:M,VVMV!E:E,"import",VVMV!F:F,"Raw materials") -> 17411.003 | C9: =SUMIF(Dolphin!G:G,"Raw materials",Dolphin!M:M)/'Logistics record '!AD1+SUMIF(Dolphin!G:G,"Raw materials",Dolphin!N:N)/'Logistics record '!AD1+SUMIF(Dolphin!G:G,"Raw materials",Dolphin!O:O)/'Logistics record '!AD1+SUMIF(Dolphin!G:G,"Raw materials",Dolphin!P:P)/'Logistics record '!AD1 -> 293.2507 | J9: =J8*'Logistics record '!$AD$1 -> 2.5782595e+08 | K9: =EI!AT23 -> 55570168 | L9: =L8*'Logistics record '!$AD$1 -> 58014781 | M9: =M8*'Logistics record '!$AD$1 -> 6.8788141e+08 | W9: =SUMIF(DHL!C:C,"raw materials",DHL!O:O) -> 180
B10: =COUNTIFS(VVMV!F:F,"raw materials",VVMV!J:J,">0") -> 527 | C10: 4 | I10: LPHQ | L10: =Dolphin!X22/'Logistics record '!$AD$1 -> 2.2674023 | M10: =SUMIF(VVMV!B:B,"Lệ phí hải quan",VVMV!AG:AG)/'Logistics record '!$AD$1 -> 232.40874 | Q10: =SUM(J10:P10) -> 234.67614 | W10: =SUMIF(DHL!C:C,"raw materials",DHL!W:W) -> 2103.8266
L11: =L10*'Logistics record '!$AD$1 -> 60000 | M11: =M10*'Logistics record '!$AD$1 -> 6150000 | Q11: =SUM(J11:P11) -> 6210000 | T11: =COUNTIFS(VVMV!F:F,"raw materials",VVMV!N:N,"Sea",VVMV!L:L,">0") -> 12 | U11: =COUNTIFS(Dolphin!H:H,"Sea",Dolphin!G:G,"Raw materials") -> 4 | V11: =COUNTIF(EI!F:F,"sea import") -> 0 | W11: =COUNTIF(EI!G:G,"sea import") -> 0
A12: =SUMIF('FedEx Import'!S:S,"Equipments + toolings",'FedEx Import'!R:R) -> 0 | B12: =SUMIFS(VVMV!L:L,VVMV!E:E,"Import",VVMV!F:F,"Equipments + Toolings") -> 0 | C12: =SUMIFS(Dolphin!AD:AD,Dolphin!AB:AB,"import",Dolphin!G:G,"Equipments + Toolings") -> 0 | D12: =SUMIFS(EI!AV:AV,EI!AX:AX,"import",EI!AY:AY,"equipments + toolings") -> 669.35217 | I12: BCQT | L12: =Dolphin!X24/'Logistics record '!$AD$1 -> 0 | M12: =SUMIF(VVMV!B:B,"Báo cáo quyết toán",VVMV!AG:AG)/'Logistics record '!$AD$1 -> 0 | Q12: =SUM(J12:P12) -> 0
A13: =SUMIF('FedEx Import'!S:S,"equipments + toolings",'FedEx Import'!L:L) -> 0 | B13: =SUMIFS(VVMV!T:T,VVMV!F:F,"Equipments + toolings",VVMV!L:L,">0") -> 0 | C13: =SUMIF(Dolphin!G18:G23,"Equipments + Toolings",Dolphin!K18:K23) -> 0 | D13: =SUMIF(EI!AY:AY,"Equipments + Toolings",EI!N:N) -> 288 | L13: =L12*'Logistics record '!$AD$1 -> 0 | M13: =M12*'Logistics record '!$AD$1 -> 0 | Q13: =SUM(J13:P13) -> 0 | T13: =SUMIFS(VVMV!L:L,VVMV!F:F,"Raw materials",VVMV!N:N,"Sea",VVMV!L:L,">0") -> 7048.3882 | U13: =SUMIFS(Dolphin!AD:AD,Dolphin!H:H,"sea",Dolphin!G:G,"Raw Materials") -> 1477.4045 | V13: =SUMIF(EI!F:F,"sea import",EI!AV:AV) -> 0 | W13: =SUMIF(EI!G:G,"sea import",EI!AW:AW) -> 0
B14: =SUMIFS(VVMV!J:J,VVMV!E:E,"import",VVMV!F:F,"Equipments + Toolings")+SUMIFS(VVMV!K:K,VVMV!E:E,"import",VVMV!F:F,"Equipments + Toolings")+SUMIFS(VVMV!M:M,VVMV!E:E,"import",VVMV!F:F,"Equipments + Toolings") -> 608.41933 | C14: =SUMIF(Dolphin!G:G,"Equipments + Toolings",Dolphin!M:M)/'Logistics record '!AD1+SUMIF(Dolphin!G:G,"Equipments + Toolings",Dolphin!N:N)/'Logistics record '!AD1+SUMIF(Dolphin!G:G,"Equipments + Toolings",Dolphin!O:O)/'Logistics record '!AD1+SUMIF(Dolphin!G:G,"Equipments + Toolings",Dolphin!P:P)/'Logistics record '!AD1 -> 0 | I14: Total | J14: =+J8+J6+J11 -> 10328.119 | K14: =+K8+K6+K11 -> 2104.7273 | L14: =L10+L8+L6 -> 2194.6482 | M14: =M10+M8+M6+M12 -> 27045.628 | N14: =N10+N8+N6+N12 -> 2216.784 | O14: =O10+O8+O6+O12 -> 340.11035 | P14: =P10+P8+P6+P12 -> 831.38085 | Q14: =SUM(J14:P14) -> 45061.398 | T14: =COUNTIF(VVMV!F:F,"raw materials") -> 527 | U14: =COUNTIF(Dolphin!G:G,"raw materials") -> 4
I15: VND | J15: =+J14*'Logistics record '!AD1 -> 2.7330269e+08 | K15: =SUM(EI!AU13:AU82) -> 55570168 | L15: =+L14*'Logistics record '!AD1 -> 58074781 | M15: =+M14*'Logistics record '!$AD$1 -> 7.1568141e+08 | N15: =+N14*'Logistics record '!$AD$1 -> 58660539 | O15: =+O14*'Logistics record '!$AD$1 -> 9000000 | P15: =P14*'Logistics record '!AD1 -> 22000000 | Q15: =+Q14*'Logistics record '!AD1 -> 1.1924147e+09 | T15: =SUMIF(VVMV!F:F,"raw materials",VVMV!J:J) -> 7932.1291 | U15: =SUMIF(Dolphin!G:G,"raw materials",Dolphin!AF:AF) -> 81.626483
E16: =22000000/'Logistics record '!AD1 -> 831.38085 | T16: =COUNTIFS(VVMV!F:F,"raw materials",VVMV!K:K,">0") -> 17 | U16: =COUNTIF(Dolphin!G:G,"raw materials") -> 4
T17: =SUMIF(VVMV!F:F,"raw materials",VVMV!K:K) -> 967.42499 | U17: =SUMIF(Dolphin!G:G,"raw materials",Dolphin!AG:AG) -> 211.62422
A18: =SUMIF('FedEx Export'!W:W,"transfer",'FedEx Export'!AC:AC) -> 354.56802 | C18: =(SUMIFS(Dolphin!Q:Q,Dolphin!AB:AB,"Export",Dolphin!AA:AA,"Transfer")+SUMIFS(Dolphin!R:R,Dolphin!AB:AB,"Export",Dolphin!AA:AA,"Transfer")+SUMIFS(Dolphin!S:S,Dolphin!AB:AB,"Export",Dolphin!AA:AA,"Transfer")+SUMIFS(Dolphin!X:X,Dolphin!AB:AB,"Export",Dolphin!AA:AA,"Transfer"))/'Logistics record '!$AD$1 -> 0 | T18: =COUNTIFS(VVMV!F:F,"raw materials",VVMV!M:M,">0") -> 142 | U18: =COUNTIF(Dolphin!G:G,"raw materials") -> 4
A19: =SUMIF('FedEx Export'!W:W,"transfer",'FedEx Export'!L:L) -> 27 | T19: =SUMIF(VVMV!F:F,"Raw materials",VVMV!M:M) -> 8511.4486 | U19: =SUMIF(Dolphin!G:G,"raw materials",Dolphin!AI:AI) -> 421.72557
B20: =SUMIFS(VVMV!O:O,VVMV!G:G,"Transfer",VVMV!E:E,"EXPORT") -> 239.96674 | C20: =(SUMIFS(Dolphin!M:M,Dolphin!AB:AB,"Export",Dolphin!AA:AA,"Transfer")+SUMIFS(Dolphin!N:N,Dolphin!AB:AB,"Export",Dolphin!AA:AA,"Transfer")+SUMIFS(Dolphin!O:O,Dolphin!AB:AB,"Export",Dolphin!AA:AA,"Transfer")+SUMIFS(Dolphin!P:P,Dolphin!AB:AB,"Export",Dolphin!AA:AA,"Transfer"))/'Logistics record '!$AD$1 -> 0 | S20: =SUMIF('Import material detail'!$C$2:$C$19,"Amount",S2:S19) -> 9743.2527 | T20: =SUMIF('Import material detail'!$C$2:$C$19,"Amount",T2:T19) -> 25386.646 | U20: =SUMIF('Import material detail'!$C$2:$C$19,"Amount",U2:U19) -> 2192.3808 | V20: =SUMIF('Import material detail'!$C$2:$C$19,"Amount",V2:V19) -> 1435.3751 | W20: =SUMIF('Import material detail'!$C$2:$C$19,"Amount",W2:W19) -> 2103.8266
S21: Của sheet Import material detail
A22: =SUMIF('FedEx Export'!W:W,"Lucid",'FedEx Export'!AC:AC) -> 0 | C22: =(SUMIFS(Dolphin!Q:Q,Dolphin!AB:AB,"Export",Dolphin!AA:AA,"Lucid")+SUMIFS(Dolphin!R:R,Dolphin!AB:AB,"Export",Dolphin!AA:AA,"Lucid")+SUMIFS(Dolphin!S:S,Dolphin!AB:AB,"Export",Dolphin!AA:AA,"Lucid")+SUMIFS(Dolphin!X:X,Dolphin!AB:AB,"Export",Dolphin!AA:AA,"Lucid"))/'Logistics record '!$AD$1 -> 0 | D22: =SUMIFS(EI!AV:AV,EI!AW:AW,"Lucid",EI!AX:AX,"Export") -> 0
A23: =SUMIF('FedEx Export'!W:W,"Lucid",'FedEx Export'!L:L) -> 0
B24: =SUMIFS(VVMV!O:O,VVMV!G:G,"Lucid",VVMV!E:E,"EXPORT") -> 211.62422 | C24: =(SUMIFS(Dolphin!M:M,Dolphin!AB:AB,"Export",Dolphin!AA:AA,"Lucid")+SUMIFS(Dolphin!N:N,Dolphin!AB:AB,"Export",Dolphin!AA:AA,"Lucid")+SUMIFS(Dolphin!O:O,Dolphin!AB:AB,"Export",Dolphin!AA:AA,"Lucid")+SUMIFS(Dolphin!P:P,Dolphin!AB:AB,"Export",Dolphin!AA:AA,"Lucid"))/'Logistics record '!$AD$1 -> 0
C26: =(SUMIFS(Dolphin!Q:Q,Dolphin!AB:AB,"Export",Dolphin!AA:AA,"Agiga")+SUMIFS(Dolphin!R:R,Dolphin!AB:AB,"Export",Dolphin!AA:AA,"Agiga")+SUMIFS(Dolphin!S:S,Dolphin!AB:AB,"Export",Dolphin!AA:AA,"Agiga")+SUMIFS(Dolphin!X:X,Dolphin!AB:AB,"Export",Dolphin!AA:AA,"Agiga"))/'Logistics record '!$AD$1 -> 0
C28: =(SUMIFS(Dolphin!M:M,Dolphin!AB:AB,"Export",Dolphin!AA:AA,"AGIGA")+SUMIFS(Dolphin!N:N,Dolphin!AB:AB,"Export",Dolphin!AA:AA,"AGIGA")+SUMIFS(Dolphin!O:O,Dolphin!AB:AB,"Export",Dolphin!AA:AA,"AGIGA")+SUMIFS(Dolphin!P:P,Dolphin!AB:AB,"Export",Dolphin!AA:AA,"AGIGA"))/'Logistics record '!$AD$1 -> 0
A30: =SUMIF('FedEx Export'!W:W,"EFI",'FedEx Export'!AC:AC) -> 0 | C30: =(SUMIFS(Dolphin!Q:Q,Dolphin!AB:AB,"Export",Dolphin!AA:AA,"EFI")+SUMIFS(Dolphin!R:R,Dolphin!AB:AB,"Export",Dolphin!AA:AA,"EFI")+SUMIFS(Dolphin!S:S,Dolphin!AB:AB,"Export",Dolphin!AA:AA,"EFI")+SUMIFS(Dolphin!X:X,Dolphin!AB:AB,"Export",Dolphin!AA:AA,"EFI"))/'Logistics record '!$AD$1 -> 0 | D30: =SUMIFS(EI!AV:AV,EI!AW:AW,"EFI",EI!AX:AX,"Export") -> 0
A31: =SUMIF('FedEx Export'!W:W,"EFI",'FedEx Export'!L:L) -> 0
B32: =SUMIFS(VVMV!O:O,VVMV!G:G,"EFI",VVMV!E:E,"EXPORT") -> 90.696093
C33: =(SUMIFS(Dolphin!M:M,Dolphin!AB:AB,"Export",Dolphin!AA:AA,"EFI")+SUMIFS(Dolphin!N:N,Dolphin!AB:AB,"Export",Dolphin!AA:AA,"EFI")+SUMIFS(Dolphin!O:O,Dolphin!AB:AB,"Export",Dolphin!AA:AA,"EFI")+SUMIFS(Dolphin!P:P,Dolphin!AB:AB,"Export",Dolphin!AA:AA,"EFI"))/'Logistics record '!$AD$1 -> 0
A35: =SUMIF('FedEx Export'!W:W,"Pure",'FedEx Export'!AC:AC) -> 79.008767 | C35: =(SUMIFS(Dolphin!Q:Q,Dolphin!AB:AB,"Export",Dolphin!AA:AA,"PURE")+SUMIFS(Dolphin!R:R,Dolphin!AB:AB,"Export",Dolphin!AA:AA,"PURE")+SUMIFS(Dolphin!S:S,Dolphin!AB:AB,"Export",Dolphin!AA:AA,"PURE")+SUMIFS(Dolphin!X:X,Dolphin!AB:AB,"Export",Dolphin!AA:AA,"PURE"))/'Logistics record '!$AD$1 -> 0 | D35: =SUMIFS(EI!AV:AV,EI!AW:AW,"PURE",EI!AX:AX,"Export") -> 0
A36: =SUMIF('FedEx Export'!W:W,"Pure",'FedEx Export'!L:L) -> 2.3
B37: =SUMIFS(VVMV!O:O,VVMV!G:G,"Pure",VVMV!E:E,"EXPORT") -> 213.51372 | C37: =(SUMIFS(Dolphin!M:M,Dolphin!AB:AB,"Export",Dolphin!AA:AA,"PURE")+SUMIFS(Dolphin!N:N,Dolphin!AB:AB,"Export",Dolphin!AA:AA,"PURE")+SUMIFS(Dolphin!O:O,Dolphin!AB:AB,"Export",Dolphin!AA:AA,"PURE")+SUMIFS(Dolphin!P:P,Dolphin!AB:AB,"Export",Dolphin!AA:AA,"PURE"))/'Logistics record '!$AD$1 -> 0
A39: =SUMIF('FedEx Export'!W:W,"AIC",'FedEx Export'!AC:AC) -> 0 | C39: =(SUMIFS(Dolphin!Q:Q,Dolphin!AB:AB,"Export",Dolphin!AA:AA,"AIC")+SUMIFS(Dolphin!R:R,Dolphin!AB:AB,"Export",Dolphin!AA:AA,"AIC")+SUMIFS(Dolphin!S:S,Dolphin!AB:AB,"Export",Dolphin!AA:AA,"AIC")+SUMIFS(Dolphin!X:X,Dolphin!AB:AB,"Export",Dolphin!AA:AA,"AIC"))/'Logistics record '!$AD$1 -> 0 | D39: =SUMIFS(EI!AV:AV,EI!AW:AW,"AIC",EI!AX:AX,"Export") -> 0
A40: =SUMIF('FedEx Export'!W:W,"AIC",'FedEx Export'!L:L) -> 0
B41: =SUMIFS(VVMV!O:O,VVMV!G:G,"AIC",VVMV!E:E,"EXPORT") -> 15.116015 | C41: =(SUMIFS(Dolphin!M:M,Dolphin!AB:AB,"Export",Dolphin!AA:AA,"AIC")+SUMIFS(Dolphin!N:N,Dolphin!AB:AB,"Export",Dolphin!AA:AA,"AIC")+SUMIFS(Dolphin!O:O,Dolphin!AB:AB,"Export",Dolphin!AA:AA,"AIC")+SUMIFS(Dolphin!P:P,Dolphin!AB:AB,"Export",Dolphin!AA:AA,"AIC"))/'Logistics record '!$AD$1 -> 0 | F41: =9000000/'Logistics record '!AD1 -> 340.11035
A43: =SUMIF('FedEx Export'!W:W,"Ford",'FedEx Export'!AC:AC) -> 0 | C43: =(SUMIFS(Dolphin!Q:Q,Dolphin!AB:AB,"Export",Dolphin!AA:AA,"Ford")+SUMIFS(Dolphin!R:R,Dolphin!AB:AB,"Export",Dolphin!AA:AA,"Ford")+SUMIFS(Dolphin!S:S,Dolphin!AB:AB,"Export",Dolphin!AA:AA,"Ford")+SUMIFS(Dolphin!X:X,Dolphin!AB:AB,"Export",Dolphin!AA:AA,"Ford"))/'Logistics record '!$AD$1 -> 0 | D43: =SUMIFS(EI!AV:AV,EI!AW:AW,"Ford",EI!AX:AX,"Export") -> 0 | G43: =SUMIFS(DHL!W:W,DHL!B:B,"export",DHL!D:D,"ford") -> 112.95749
A44: =SUMIF('FedEx Export'!W:W,"AIC",'FedEx Export'!L:L) -> 0 | G44: =SUMIFS(DHL!O:O,DHL!B:B,"export",DHL!D:D,"ford") -> 3.5
B45: =SUMIFS(VVMV!O:O,VVMV!G:G,"Ford",VVMV!E:E,"EXPORT") -> 0 | C45: =(SUMIFS(Dolphin!M:M,Dolphin!AB:AB,"Export",Dolphin!AA:AA,"Ford")+SUMIFS(Dolphin!N:N,Dolphin!AB:AB,"Export",Dolphin!AA:AA,"Ford")+SUMIFS(Dolphin!O:O,Dolphin!AB:AB,"Export",Dolphin!AA:AA,"Ford")+SUMIFS(Dolphin!P:P,Dolphin!AB:AB,"Export",Dolphin!AA:AA,"Ford"))/'Logistics record '!$AD$1 -> 0
B47: =SUMIFS(VVMV!O:O,VVMV!G:G,"OEM",VVMV!E:E,"EXPORT")+SUMIFS(VVMV!O:O,VVMV!G:G,"Other",VVMV!E:E,"EXPORT")+SUMIFS(VVMV!O:O,VVMV!G:G,"AGIGA",VVMV!E:E,"EXPORT") -> 47.237548 | C47: =(SUMIFS(Dolphin!M:M,Dolphin!AB:AB,"Export",Dolphin!AA:AA,"OEM")+SUMIFS(Dolphin!N:N,Dolphin!AB:AB,"Export",Dolphin!AA:AA,"OEM")+SUMIFS(Dolphin!O:O,Dolphin!AB:AB,"Export",Dolphin!AA:AA,"OEM")+SUMIFS(Dolphin!P:P,Dolphin!AB:AB,"Export",Dolphin!AA:AA,"OEM"))/'Logistics record '!$AD$1+(SUMIFS(Dolphin!M:M,Dolphin!AB:AB,"Export",Dolphin!AA:AA,"OTHER")+SUMIFS(Dolphin!N:N,Dolphin!AB:AB,"Export",Dolphin!AA:AA,"OTHER")+SUMIFS(Dolphin!O:O,Dolphin!AB:AB,"Export",Dolphin!AA:AA,"OTHER")+SUMIFS(Dolphin!P:P,Dolphin!AB:AB,"Export",Dolphin!AA:AA,"OTHER"))/'Logistics record '!$AD$1 -> 0 | D47: =SUMIFS(EI!AV:AV,EI!AW:AW,"OEM",EI!AX:AX,"Export") -> 0
A48: =SUMIF('FedEx Export'!W:W,"Other",'FedEx Export'!AC:AC)+SUMIF('FedEx Export'!W:W,"OEM",'FedEx Export'!AC:AC)+SUMIF('FedEx Export'!W:W,"AGIGA",'FedEx Export'!AC:AC) -> 151.28962 | C48: =(SUMIFS(Dolphin!Q:Q,Dolphin!AB:AB,"Export",Dolphin!AA:AA,"OEM")+SUMIFS(Dolphin!R:R,Dolphin!AB:AB,"Export",Dolphin!AA:AA,"OEM")+SUMIFS(Dolphin!S:S,Dolphin!AB:AB,"Export",Dolphin!AA:AA,"OEM")+SUMIFS(Dolphin!X:X,Dolphin!AB:AB,"Export",Dolphin!AA:AA,"OEM"))/'Logistics record '!$AD$1+(SUMIFS(Dolphin!Q:Q,Dolphin!AB:AB,"Export",Dolphin!AA:AA,"OTHER")+SUMIFS(Dolphin!R:R,Dolphin!AB:AB,"Export",Dolphin!AA:AA,"OTHER")+SUMIFS(Dolphin!S:S,Dolphin!AB:AB,"Export",Dolphin!AA:AA,"OTHER")+SUMIFS(Dolphin!X:X,Dolphin!AB:AB,"Export",Dolphin!AA:AA,"OTHER"))/'Logistics record '!$AD$1 -> 0
B51: =VLOOKUP("Lệ phí hải quan",VVMV!$B:$AF,31,0)/'Logistics record '!AD1 -> 232.40874 | C51: =VLOOKUP("LỆ PHÍ HẢI QUAN",Dolphin!B:X,23,0)/'Logistics record '!AD1 -> 2.2674023
A53: =SUM(A48,A12,A39,A35,A30,A26,A22,A18,A6) -> 10328.119 | B53: =B51+B47+B41+B37+B32+B24+B20+B14+B12+B9+B6+B52 -> 27045.628 | C53: =C51+C47+C41+C37+C32+C24+C20+C14+C12+C9+C6+C52 -> 2194.6482 | D53: =D51+D47+D41+D37+D32+D24+D20+D14+D12+D9+D6+D52 -> 2104.7273 | E53: =E51+E47+E41+E37+E32+E24+E20+E14+E12+E9+E6+E52+E16 -> 831.38085 | F53: =F51+F47+F41+F37+F32+F24+F20+F14+F12+F9+F6+F52+F16 -> 340.11035 | G53: =G6+G12+G18+G22+G26+G30+G35+G39+G43+G48 -> 2216.784

Sheet FedEx Export
R1: VLOOKUP
B2: VAT INVOICE NO. | C2: DEBIT NOTE NO. | D2: DEBIT NOTE DATE | E2: AWB | F2: SHIP DATE | G2: SHIPPER | H2: CONSIGNEE | I2: ORIG | J2: DEST | K2: SERV | L2: CHRGBL WGHT (KG) | M2: NET CHARGE | N2: OTHER CHARGE | O2: FUEL SURCHARGE | P2: VAT (8%) | Q2: TOTAL AMOUNT (VND) | R2: STT | S2: Description | T2: Invoice | U2: Remark | V2: Who pays? | W2: Route | X2: STT | Y2: GW | Z2: CONSIGNEE | AA2: DEST | AB2: Final Amount | AC2: USD | AD2: VVMV | AE2: TOTAL
B3: 1K26TFA-00029775 | C3: 734101624 | D3: 46199 | E3: 872009826743 | F3: 46162 | G3: UNIGEN VIET NAM HANOI CO., LTD | H3: AGIGA TECH (CHENGDU) LLC | I3: VN | J3: CN | K3: 2P | L3: 11.8 | M3: 1746034 | N3: 0 | O3: 851192 | P3: 207778 | Q3: 2805004 | R3: 344 | S3: CUPCAKE | T3: INV06818 | U3: Ship to CTU | V3: x | W3: OEM | X3: 344 | Y3: 8 | Z3: CTU | AA3: CN | AB3: 2805004 | AC3: =AB3/'Logistics record '!$AD$1 -> 106.00121 | AD3: =SUMIF(VVMV!F:F,'FedEx Export'!T3,VVMV!O:O) -> 0 | AE3: =AD3+AC3 -> 106.00121
B4: 1K26TFA-00029775 | C4: 734101624 | D4: 46199 | E4: 872266860800 | F4: 46169 | G4: UNIGEN VIET NAM HANOI CO., LTD | H4: PURE STORAGE, INC. | I4: VN | J4: US | K4: IE | L4: 0.6 | M4: 610238 | N4: 68300 | O4: 302068 | P4: 78448 | Q4: 1059054 | R4: 372 | S4: IC | T4: Sample 754 | U4: Ship QA's sample for evaluation | V4: x | W4: PURE | X4: 372 | Y4: 0.092 | Z4: PURE US | AA4: US | AB4: 1059054 | AC4: =AB4/'Logistics record '!$AD$1 -> 40.021691 | AD4: =SUMIF(VVMV!F:F,'FedEx Export'!T4,VVMV!O:O) -> 0 | AE4: =AD4+AC4 -> 40.021691
B5: 1K26TFA-00029775 | C5: 734101624 | D5: 46199 | E5: 872329335608 | F5: 46171 | G5: UNIGEN VIET NAM HANOI CO., LTD | H5: UNIGEN CORPORATION | I5: VN | J5: US | K5: IE | L5: 1.7 | M5: 814665 | N5: 68300 | O5: 403259 | P5: 102898 | Q5: 1389122 | R5: 390 | S5: PCBA, STEEL | T5: E01087 | U5: Transfer material | V5: x | W5: Transfer | X5: 390 | Y5: 1.1 | Z5: HQ1 | AA5: US | AB5: 1389122 | AC5: =AB5/'Logistics record '!$AD$1 -> 52.494974 | AD5: =SUMIF(VVMV!F:F,'FedEx Export'!T5,VVMV!O:O) -> 47.237548 | AE5: =AD5+AC5 -> 99.732522
B6: 1K26TFA-00029775 | C6: 734101624 | D6: 46199 | E6: 872639262181 | F6: 46178 | G6: UNIGEN VIET NAM HANOI CO., LTD | H6: UNIGEN CORPORATION | I6: VN | J6: US | K6: IE | L6: 16 | M6: 2797192 | N6: 68300 | O6: 1377617 | P6: 339449 | Q6: 4582558 | R6: 397 | S6: IC, RES, TRANS, DIODE, LABEL, CAP | T6: E01089 | U6: Transfer material | V6: x | W6: Transfer | X6: 397 | Y6: 8.9 | Z6: HQ1 | AA6: US | AB6: 4582558 | AC6: =AB6/'Logistics record '!$AD$1 -> 173.17504 | AD6: =SUMIF(VVMV!F:F,'FedEx Export'!T6,VVMV!O:O) -> 47.237548 | AE6: =AD6+AC6 -> 220.41259
B7: 1K26TFA-00029775 | C7: 734101624 | D7: 46199 | E7: 872758765274 | F7: 46181 | G7: UNIGEN VIET NAM HANOI CO., LTD | H7: COMPEQ MANUFACTURING (HUIZHOU) | I7: VN | J7: CN | K7: 2P | L7: 1.7 | M7: 670355 | N7: 0 | O7: 284901 | P7: 76420 | Q7: 1031676 | R7: 402 | S7: PCB | T7: Sample 756 | U7: Ship QA's sample for evaluation | V7: x | W7: PURE | X7: 402 | Y7: 1.653 | Z7: COMPEQ | AA7: CN | AB7: 1031676 | AC7: =AB7/'Logistics record '!$AD$1 -> 38.987076 | AD7: =SUMIF(VVMV!F:F,'FedEx Export'!T7,VVMV!O:O) -> 0 | AE7: =AD7+AC7 -> 38.987076
B8: 1K26TFA-00029775 | C8: 734101624 | D8: 46199 | E8: 872885278038 | F8: 46184 | G8: UNIGEN VIET NAM HANOI CO., LTD | H8: INGRASYS TECHNOLOGY INC. | I8: VN | J8: TW | K8: IE | L8: 4.6 | M8: 778702 | N8: 0 | O8: 330948 | P8: 88772 | Q8: 1198422 | R8: 410 | S8: DDR4 | T8: INV06869 | U8: RMA | V8: x | W8: OEM | X8: 410 | Y8: 1.6 | Z8: INGRASYS | AA8: TW | AB8: 1198422 | AC8: =AB8/'Logistics record '!$AD$1 -> 45.288414 | AD8: =SUMIF(VVMV!F:F,'FedEx Export'!T8,VVMV!O:O) -> 47.237548 | AE8: =AD8+AC8 -> 92.525962
B9: 1K26TFA-00029775 | C9: 734101624 | D9: 46199 | E9: 873056855970 | F9: 46188 | G9: UNIGEN VIET NAM HANOI CO., LTD | H9: UNIGEN CORPORATION | I9: VN | J9: US | K9: 2P | L9: 9.3 | M9: 2160797 | N9: 68300 | O9: 929143 | P9: 252659 | Q9: 3410899 | R9: 424 | S9: SSD | T9: INV06883 | U9: Transfer FG | V9: x | W9: Transfer | X9: 424 | Y9: 7 | Z9: HQ1 | AA9: US | AB9: 3410899 | AC9: =AB9/'Logistics record '!$AD$1 -> 128.898 | AD9: =SUMIF(VVMV!F:F,'FedEx Export'!T9,VVMV!O:O) -> 15.116015 | AE9: =AD9+AC9 -> 144.01402
AE10: =SUM(AC3:AC9) -> 584.86641
P12: Total in VND (Including VAT) | Q12: =SUM(Q3:Q9) -> 15476735
O13: =Q12/26367 -> 586.97368

Sheet FedEx Import
B1: VAT INVOICE NO. | C1: DEBIT NOTE NO. | D1: DEBIT NOTE DATE | E1: AWB | F1: SHIP DATE | G1: SHIPPER | H1: CONSIGNEE | I1: ORIG | J1: DEST | K1: SERV | L1: CHRGBL WGHT (KG) | M1: NET CHARGE | N1: OTHER CHARGE | O1: FUEL SURCHARGE | P1: VAT (5.26%) | Q1: TOTAL AMOUNT (VND) | R1: USD | S1: Type | T1: Who pays? | U1: Route | V1: VVMV customs fee | W1: TOTAL
B2: 1K26TFA-00029774 | C2: 734101623 | D2: 46199 | E2: 381335227154 | F2: 46160 | G2: DHL SUPPLY CHAIN MGMT PHILS. INC | H2: UNIGEN CORPORATION | I2: PH | J2: VN | K2: IE | L2: 0.8 | M2: 448955 | N2: 137374 | O2: 213254 | P2: 42058 | Q2: 841641 | R2: =Q2/'Logistics record '!$AD$1 -> 31.805646 | S2: Raw materials | U2: {=IFERROR( _xlfn.IFS( VLOOKUP(E2,[1]Material!F$5:U$90000,16,0)="LUC","Lucid", VLOOKUP(E2,[1]Material!F$5:U$90000,16,0)="FMC","FORD", OR(VLOOKUP(E2,[1]Material!F$5:U$90000,16,0)="PUR",VLOOKUP(E2,[1]Material!F$5:U$90000,16,0)="HLO"),"PURE", VLOOKUP(E2,[1]Material!F$5:U$90000,16,0)="AIC","AIC", OR(VLOOKUP(E2,[1]Material!F$5:U$90000,16,0)="AGI",VLOOKUP(E2,[1]Material!F$5:U$90000,16,0)="AGIGA"),"AGIGA", OR(LEFT(VLOOKUP(E2,[1]Material!F$5:U$90000,16,0),3)="EF-",VLOOKUP(E2,[1]Material!F$5:U$90000,16,0)="EFI"),"EFI", AND(ISNUMBER(VLOOKUP(E2,[1]Material!F$5:U$90000,16,0)),VLOOKUP(E2,[1]Material!F$5:U$90000,16,0)>=100,VLOOKUP(E2,[1]Material!F$5:U$90000,16,0)<=999,VLOOKUP(E2,[1]Material!F$5:U$90000,16,0)=INT(VLOOKUP(E2,[1]Material!F$5:U$90000,16,0))),"OEM", TRUE,"" ), "không tìm thấy trong file Import" )} -> EFI | V2: =IFERROR(_xlfn.XLOOKUP(E:E,VVMV!B:B,VVMV!J:J),0) -> 15.116015 | W2: =V2+R2 -> 46.921661
B3: 1K26TFA-00029774 | C3: 734101623 | D3: 46199 | E3: 381471618942 | F3: 46163 | G3: DHL SUPPLY CHAIN MGMT PHILS. INC | H3: UNIGEN CORPORATION | I3: PH | J3: VN | K3: IE | L3: 2.6 | M3: 633735 | N3: 136652 | O3: 308946 | P3: 56773 | Q3: 1136106 | R3: =Q3/'Logistics record '!$AD$1 -> 42.93349 | S3: Raw materials | U3: {=IFERROR( _xlfn.IFS( VLOOKUP(E3,[1]Material!F$5:U$90000,16,0)="LUC","Lucid", VLOOKUP(E3,[1]Material!F$5:U$90000,16,0)="FMC","FORD", OR(VLOOKUP(E3,[1]Material!F$5:U$90000,16,0)="PUR",VLOOKUP(E3,[1]Material!F$5:U$90000,16,0)="HLO"),"PURE", VLOOKUP(E3,[1]Material!F$5:U$90000,16,0)="AIC","AIC", OR(VLOOKUP(E3,[1]Material!F$5:U$90000,16,0)="AGI",VLOOKUP(E3,[1]Material!F$5:U$90000,16,0)="AGIGA"),"AGIGA", OR(LEFT(VLOOKUP(E3,[1]Material!F$5:U$90000,16,0),3)="EF-",VLOOKUP(E3,[1]Material!F$5:U$90000,16,0)="EFI"),"EFI", AND(ISNUMBER(VLOOKUP(E3,[1]Material!F$5:U$90000,16,0)),VLOOKUP(E3,[1]Material!F$5:U$90000,16,0)>=100,VLOOKUP(E3,[1]Material!F$5:U$90000,16,0)<=999,VLOOKUP(E3,[1]Material!F$5:U$90000,16,0)=INT(VLOOKUP(E3,[1]Material!F$5:U$90000,16,0))),"OEM", TRUE,"" ), "không tìm thấy trong file Import" )} -> PURE | V3: =IFERROR(_xlfn.XLOOKUP(E:E,VVMV!B:B,VVMV!J:J),0) -> 0 | W3: =V3+R3 -> 42.93349
B4: 1K26TFA-00029774 | C4: 734101623 | D4: 46199 | E4: 381501224770 | F4: 46164 | G4: DHL SUPPLY CHAIN MGMT PHILS. INC | H4: UNIGEN CORPORATION | I4: PH | J4: VN | K4: IE | L4: 6.3 | M4: 908289 | N4: 137068 | O4: 442791 | P4: 78277 | Q4: 1566425 | R4: =Q4/'Logistics record '!$AD$1 -> 59.195261 | S4: Raw materials | U4: {=IFERROR( _xlfn.IFS( VLOOKUP(E4,[1]Material!F$5:U$90000,16,0)="LUC","Lucid", VLOOKUP(E4,[1]Material!F$5:U$90000,16,0)="FMC","FORD", OR(VLOOKUP(E4,[1]Material!F$5:U$90000,16,0)="PUR",VLOOKUP(E4,[1]Material!F$5:U$90000,16,0)="HLO"),"PURE", VLOOKUP(E4,[1]Material!F$5:U$90000,16,0)="AIC","AIC", OR(VLOOKUP(E4,[1]Material!F$5:U$90000,16,0)="AGI",VLOOKUP(E4,[1]Material!F$5:U$90000,16,0)="AGIGA"),"AGIGA", OR(LEFT(VLOOKUP(E4,[1]Material!F$5:U$90000,16,0),3)="EF-",VLOOKUP(E4,[1]Material!F$5:U$90000,16,0)="EFI"),"EFI", AND(ISNUMBER(VLOOKUP(E4,[1]Material!F$5:U$90000,16,0)),VLOOKUP(E4,[1]Material!F$5:U$90000,16,0)>=100,VLOOKUP(E4,[1]Material!F$5:U$90000,16,0)<=999,VLOOKUP(E4,[1]Material!F$5:U$90000,16,0)=INT(VLOOKUP(E4,[1]Material!F$5:U$90000,16,0))),"OEM", TRUE,"" ), "không tìm thấy trong file Import" )} -> PURE | V4: =IFERROR(_xlfn.XLOOKUP(E:E,VVMV!B:B,VVMV!J:J),0) -> 15.116015 | W4: =V4+R4 -> 74.311277
B5: 1K26TFA-00029774 | C5: 734101623 | D5: 46199 | E5: 381600540944 | F5: 46169 | G5: DHL SUPPLY CHAIN MGMT PHILS. INC | H5: UNIGEN CORPORATION | I5: PH | J5: VN | K5: IE | L5: 5.4 | M5: 841155 | N5: 137496 | O5: 416372 | P5: 73378 | Q5: 1468401 | R5: =Q5/'Logistics record '!$AD$1 -> 55.49093 | S5: Raw materials | U5: {=IFERROR( _xlfn.IFS( VLOOKUP(E5,[1]Material!F$5:U$90000,16,0)="LUC","Lucid", VLOOKUP(E5,[1]Material!F$5:U$90000,16,0)="FMC","FORD", OR(VLOOKUP(E5,[1]Material!F$5:U$90000,16,0)="PUR",VLOOKUP(E5,[1]Material!F$5:U$90000,16,0)="HLO"),"PURE", VLOOKUP(E5,[1]Material!F$5:U$90000,16,0)="AIC","AIC", OR(VLOOKUP(E5,[1]Material!F$5:U$90000,16,0)="AGI",VLOOKUP(E5,[1]Material!F$5:U$90000,16,0)="AGIGA"),"AGIGA", OR(LEFT(VLOOKUP(E5,[1]Material!F$5:U$90000,16,0),3)="EF-",VLOOKUP(E5,[1]Material!F$5:U$90000,16,0)="EFI"),"EFI", AND(ISNUMBER(VLOOKUP(E5,[1]Material!F$5:U$90000,16,0)),VLOOKUP(E5,[1]Material!F$5:U$90000,16,0)>=100,VLOOKUP(E5,[1]Material!F$5:U$90000,16,0)<=999,VLOOKUP(E5,[1]Material!F$5:U$90000,16,0)=INT(VLOOKUP(E5,[1]Material!F$5:U$90000,16,0))),"OEM", TRUE,"" ), "không tìm thấy trong file Import" )} -> EFI | V5: =IFERROR(_xlfn.XLOOKUP(E:E,VVMV!B:B,VVMV!J:J),0) -> 15.116015 | W5: =V5+R5 -> 70.606946
B6: 1K26TFA-00029774 | C6: 734101623 | D6: 46199 | E6: 381633142753 | F6: 46170 | G6: DHL SUPPLY CHAIN MGMT PHILS. INC | H6: UNIGEN CORPORATION | I6: PH | J6: VN | K6: IE | L6: 2.6 | M6: 633735 | N6: 136969 | O6: 313699 | P6: 57040 | Q6: 1141443 | R6: =Q6/'Logistics record '!$AD$1 -> 43.135175 | S6: Raw materials | U6: {=IFERROR( _xlfn.IFS( VLOOKUP(E6,[1]Material!F$5:U$90000,16,0)="LUC","Lucid", VLOOKUP(E6,[1]Material!F$5:U$90000,16,0)="FMC","FORD", OR(VLOOKUP(E6,[1]Material!F$5:U$90000,16,0)="PUR",VLOOKUP(E6,[1]Material!F$5:U$90000,16,0)="HLO"),"PURE", VLOOKUP(E6,[1]Material!F$5:U$90000,16,0)="AIC","AIC", OR(VLOOKUP(E6,[1]Material!F$5:U$90000,16,0)="AGI",VLOOKUP(E6,[1]Material!F$5:U$90000,16,0)="AGIGA"),"AGIGA", OR(LEFT(VLOOKUP(E6,[1]Material!F$5:U$90000,16,0),3)="EF-",VLOOKUP(E6,[1]Material!F$5:U$90000,16,0)="EFI"),"EFI", AND(ISNUMBER(VLOOKUP(E6,[1]Material!F$5:U$90000,16,0)),VLOOKUP(E6,[1]Material!F$5:U$90000,16,0)>=100,VLOOKUP(E6,[1]Material!F$5:U$90000,16,0)<=999,VLOOKUP(E6,[1]Material!F$5:U$90000,16,0)=INT(VLOOKUP(E6,[1]Material!F$5:U$90000,16,0))),"OEM", TRUE,"" ), "không tìm thấy trong file Import" )} -> PURE | V6: =IFERROR(_xlfn.XLOOKUP(E:E,VVMV!B:B,VVMV!J:J),0) -> 15.116015 | W6: =V6+R6 -> 58.25119
B7: 1K26TFA-00029774 | C7: 734101623 | D7: 46199 | E7: 518337606988 | F7: 46170 | G7: MICROCHIP TECHNOLOGY OPS PHIL CORP | H7: UNIGEN VIETNAM HANOI CO LTD | I7: PH | J7: VN | K7: IE | L7: 29.7 | M7: 2509099 | N7: 138490 | O7: 1242004 | P7: 204593 | Q7: 4094186 | R7: =Q7/'Logistics record '!$AD$1 -> 154.71945 | S7: Raw materials | U7: {=IFERROR( _xlfn.IFS( VLOOKUP(E7,[1]Material!F$5:U$90000,16,0)="LUC","Lucid", VLOOKUP(E7,[1]Material!F$5:U$90000,16,0)="FMC","FORD", OR(VLOOKUP(E7,[1]Material!F$5:U$90000,16,0)="PUR",VLOOKUP(E7,[1]Material!F$5:U$90000,16,0)="HLO"),"PURE", VLOOKUP(E7,[1]Material!F$5:U$90000,16,0)="AIC","AIC", OR(VLOOKUP(E7,[1]Material!F$5:U$90000,16,0)="AGI",VLOOKUP(E7,[1]Material!F$5:U$90000,16,0)="AGIGA"),"AGIGA", OR(LEFT(VLOOKUP(E7,[1]Material!F$5:U$90000,16,0),3)="EF-",VLOOKUP(E7,[1]Material!F$5:U$90000,16,0)="EFI"),"EFI", AND(ISNUMBER(VLOOKUP(E7,[1]Material!F$5:U$90000,16,0)),VLOOKUP(E7,[1]Material!F$5:U$90000,16,0)>=100,VLOOKUP(E7,[1]Material!F$5:U$90000,16,0)<=999,VLOOKUP(E7,[1]Material!F$5:U$90000,16,0)=INT(VLOOKUP(E7,[1]Material!F$5:U$90000,16,0))),"OEM", TRUE,"" ), "không tìm thấy trong file Import" )} -> PURE | V7: =IFERROR(_xlfn.XLOOKUP(E:E,VVMV!B:B,VVMV!J:J),0) -> 15.116015 | W7: =V7+R7 -> 169.83546
B8: 1K26TFA-00029774 | C8: 734101623 | D8: 46199 | E8: 381794684335 | F8: 46177 | G8: DHL SUPPLY CHAIN MGMT PHILS. INC | H8: UNIGEN CORPORATION | I8: PH | J8: VN | K8: IE | L8: 8.8 | M8: 1076123 | N8: 136616 | O8: 529991 | P8: 91668 | Q8: 1834398 | R8: =Q8/'Logistics record '!$AD$1 -> 69.321971 | S8: Raw materials | U8: {=IFERROR( _xlfn.IFS( VLOOKUP(E8,[1]Material!F$5:U$90000,16,0)="LUC","Lucid", VLOOKUP(E8,[1]Material!F$5:U$90000,16,0)="FMC","FORD", OR(VLOOKUP(E8,[1]Material!F$5:U$90000,16,0)="PUR",VLOOKUP(E8,[1]Material!F$5:U$90000,16,0)="HLO"),"PURE", VLOOKUP(E8,[1]Material!F$5:U$90000,16,0)="AIC","AIC", OR(VLOOKUP(E8,[1]Material!F$5:U$90000,16,0)="AGI",VLOOKUP(E8,[1]Material!F$5:U$90000,16,0)="AGIGA"),"AGIGA", OR(LEFT(VLOOKUP(E8,[1]Material!F$5:U$90000,16,0),3)="EF-",VLOOKUP(E8,[1]Material!F$5:U$90000,16,0)="EFI"),"EFI", AND(ISNUMBER(VLOOKUP(E8,[1]Material!F$5:U$90000,16,0)),VLOOKUP(E8,[1]Material!F$5:U$90000,16,0)>=100,VLOOKUP(E8,[1]Material!F$5:U$90000,16,0)<=999,VLOOKUP(E8,[1]Material!F$5:U$90000,16,0)=INT(VLOOKUP(E8,[1]Material!F$5:U$90000,16,0))),"OEM", TRUE,"" ), "không tìm thấy trong file Import" )} -> PURE | V8: =IFERROR(_xlfn.XLOOKUP(E:E,VVMV!B:B,VVMV!J:J),0) -> 15.116015 | W8: =V8+R8 -> 84.437987
B9: 1K26TFA-00029774 | C9: 734101623 | D9: 46199 | E9: 381845821672 | F9: 46179 | G9: ANALOG DEVICES GEN. TRIAS, INC. | H9: UNIGEN CORPORATION | I9: PH | J9: VN | K9: IE | L9: 1.5 | M9: 495695 | N9: 136466 | O9: 244130 | P9: 46093 | Q9: 922384 | R9: =Q9/'Logistics record '!$AD$1 -> 34.856927 | S9: Raw materials | U9: {=IFERROR( _xlfn.IFS( VLOOKUP(E9,[1]Material!F$5:U$90000,16,0)="LUC","Lucid", VLOOKUP(E9,[1]Material!F$5:U$90000,16,0)="FMC","FORD", OR(VLOOKUP(E9,[1]Material!F$5:U$90000,16,0)="PUR",VLOOKUP(E9,[1]Material!F$5:U$90000,16,0)="HLO"),"PURE", VLOOKUP(E9,[1]Material!F$5:U$90000,16,0)="AIC","AIC", OR(VLOOKUP(E9,[1]Material!F$5:U$90000,16,0)="AGI",VLOOKUP(E9,[1]Material!F$5:U$90000,16,0)="AGIGA"),"AGIGA", OR(LEFT(VLOOKUP(E9,[1]Material!F$5:U$90000,16,0),3)="EF-",VLOOKUP(E9,[1]Material!F$5:U$90000,16,0)="EFI"),"EFI", AND(ISNUMBER(VLOOKUP(E9,[1]Material!F$5:U$90000,16,0)),VLOOKUP(E9,[1]Material!F$5:U$90000,16,0)>=100,VLOOKUP(E9,[1]Material!F$5:U$90000,16,0)<=999,VLOOKUP(E9,[1]Material!F$5:U$90000,16,0)=INT(VLOOKUP(E9,[1]Material!F$5:U$90000,16,0))),"OEM", TRUE,"" ), "không tìm thấy trong file Import" )} -> Lucid | V9: =IFERROR(_xlfn.XLOOKUP(E:E,VVMV!B:B,VVMV!J:J),0) -> 15.116015 | W9: =V9+R9 -> 49.972942
B10: 1K26TFA-00029774 | C10: 734101623 | D10: 46199 | E10: 518337618146 | F10: 46179 | G10: MICROCHIP TECHNOLOGY OPS PHIL CORP | H10: UNIGEN VIETNAM HANOI CO LTD | I10: PH | J10: VN | K10: IE | L10: 47.6 | M10: 3968419 | N10: 136466 | O10: 1954446 | P10: 318721 | Q10: 6378052 | R10: =Q10/'Logistics record '!$AD$1 -> 241.02683 | S10: Raw materials | U10: {=IFERROR( _xlfn.IFS( VLOOKUP(E10,[1]Material!F$5:U$90000,16,0)="LUC","Lucid", VLOOKUP(E10,[1]Material!F$5:U$90000,16,0)="FMC","FORD", OR(VLOOKUP(E10,[1]Material!F$5:U$90000,16,0)="PUR",VLOOKUP(E10,[1]Material!F$5:U$90000,16,0)="HLO"),"PURE", VLOOKUP(E10,[1]Material!F$5:U$90000,16,0)="AIC","AIC", OR(VLOOKUP(E10,[1]Material!F$5:U$90000,16,0)="AGI",VLOOKUP(E10,[1]Material!F$5:U$90000,16,0)="AGIGA"),"AGIGA", OR(LEFT(VLOOKUP(E10,[1]Material!F$5:U$90000,16,0),3)="EF-",VLOOKUP(E10,[1]Material!F$5:U$90000,16,0)="EFI"),"EFI", AND(ISNUMBER(VLOOKUP(E10,[1]Material!F$5:U$90000,16,0)),VLOOKUP(E10,[1]Material!F$5:U$90000,16,0)>=100,VLOOKUP(E10,[1]Material!F$5:U$90000,16,0)<=999,VLOOKUP(E10,[1]Material!F$5:U$90000,16,0)=INT(VLOOKUP(E10,[1]Material!F$5:U$90000,16,0))),"OEM", TRUE,"" ), "không tìm thấy trong file Import" )} -> PURE | V10: =IFERROR(_xlfn.XLOOKUP(E:E,VVMV!B:B,VVMV!J:J),0) -> 15.116015 | W10: =V10+R10 -> 256.14285
B11: 1K26TFA-00029774 | C11: 734101623 | D11: 46199 | E11: 382048162769 | F11: 46189 | G11: DHL SUPPLY CHAIN MGMT PHILS. INC | H11: UNIGEN CORPORATION | I11: PH | J11: VN | K11: IE | L11: 3 | M11: 633735 | N11: 139007 | O11: 272506 | P11: 54980 | Q11: 1100228 | R11: =Q11/'Logistics record '!$AD$1 -> 41.577659 | S11: Raw materials | U11: {=IFERROR( _xlfn.IFS( VLOOKUP(E11,[1]Material!F$5:U$90000,16,0)="LUC","Lucid", VLOOKUP(E11,[1]Material!F$5:U$90000,16,0)="FMC","FORD", OR(VLOOKUP(E11,[1]Material!F$5:U$90000,16,0)="PUR",VLOOKUP(E11,[1]Material!F$5:U$90000,16,0)="HLO"),"PURE", VLOOKUP(E11,[1]Material!F$5:U$90000,16,0)="AIC","AIC", OR(VLOOKUP(E11,[1]Material!F$5:U$90000,16,0)="AGI",VLOOKUP(E11,[1]Material!F$5:U$90000,16,0)="AGIGA"),"AGIGA", OR(LEFT(VLOOKUP(E11,[1]Material!F$5:U$90000,16,0),3)="EF-",VLOOKUP(E11,[1]Material!F$5:U$90000,16,0)="EFI"),"EFI", AND(ISNUMBER(VLOOKUP(E11,[1]Material!F$5:U$90000,16,0)),VLOOKUP(E11,[1]Material!F$5:U$90000,16,0)>=100,VLOOKUP(E11,[1]Material!F$5:U$90000,16,0)<=999,VLOOKUP(E11,[1]Material!F$5:U$90000,16,0)=INT(VLOOKUP(E11,[1]Material!F$5:U$90000,16,0))),"OEM", TRUE,"" ), "không tìm thấy trong file Import" )} -> PURE | V11: =IFERROR(_xlfn.XLOOKUP(E:E,VVMV!B:B,VVMV!J:J),0) -> 15.116015 | W11: =V11+R11 -> 56.693674
B12: 1K26TFA-00029774 | C12: 734101623 | D12: 46199 | E12: 873186448972 | F12: 46191 | G12: CYMMETRIK SHENZHEN PRINTING CO. LTD | H12: UNIGEN VIETNAM HANOI CO LTD | I12: CN | J12: VN | K12: 2P | L12: 2.4 | M12: 395415 | N12: 388350 | O12: 170028 | P12: 50170 | Q12: 1003963 | R12: =Q12/'Logistics record '!$AD$1 -> 37.9398 | S12: Raw materials | U12: {=IFERROR( _xlfn.IFS( VLOOKUP(E12,[1]Material!F$5:U$90000,16,0)="LUC","Lucid", VLOOKUP(E12,[1]Material!F$5:U$90000,16,0)="FMC","FORD", OR(VLOOKUP(E12,[1]Material!F$5:U$90000,16,0)="PUR",VLOOKUP(E12,[1]Material!F$5:U$90000,16,0)="HLO"),"PURE", VLOOKUP(E12,[1]Material!F$5:U$90000,16,0)="AIC","AIC", OR(VLOOKUP(E12,[1]Material!F$5:U$90000,16,0)="AGI",VLOOKUP(E12,[1]Material!F$5:U$90000,16,0)="AGIGA"),"AGIGA", OR(LEFT(VLOOKUP(E12,[1]Material!F$5:U$90000,16,0),3)="EF-",VLOOKUP(E12,[1]Material!F$5:U$90000,16,0)="EFI"),"EFI", AND(ISNUMBER(VLOOKUP(E12,[1]Material!F$5:U$90000,16,0)),VLOOKUP(E12,[1]Material!F$5:U$90000,16,0)>=100,VLOOKUP(E12,[1]Material!F$5:U$90000,16,0)<=999,VLOOKUP(E12,[1]Material!F$5:U$90000,16,0)=INT(VLOOKUP(E12,[1]Material!F$5:U$90000,16,0))),"OEM", TRUE,"" ), "không tìm thấy trong file Import" )} -> PURE | V12: =IFERROR(_xlfn.XLOOKUP(E:E,VVMV!B:B,VVMV!J:J),0) -> 15.116015 | W12: =V12+R12 -> 53.055816
B13: 1K26TFA-00029784 | C13: 734101625 | D13: 46199 | E13: 510007349877 | F13: 46150 | G13: SINO FAITH TECHNOLOGY DVPT LTD | H13: UNIGEN VIETNAM HANOI CO.LTD | I13: HK | J13: VN | K13: IE | L13: 3.8 | M13: 470100 | N13: 0 | O13: 212720 | P13: 35916 | Q13: 718736 | R13: =Q13/'Logistics record '!$AD$1 -> 27.161061 | S13: Raw materials | U13: {=IFERROR( _xlfn.IFS( VLOOKUP(E13,[1]Material!F$5:U$90000,16,0)="LUC","Lucid", VLOOKUP(E13,[1]Material!F$5:U$90000,16,0)="FMC","FORD", OR(VLOOKUP(E13,[1]Material!F$5:U$90000,16,0)="PUR",VLOOKUP(E13,[1]Material!F$5:U$90000,16,0)="HLO"),"PURE", VLOOKUP(E13,[1]Material!F$5:U$90000,16,0)="AIC","AIC", OR(VLOOKUP(E13,[1]Material!F$5:U$90000,16,0)="AGI",VLOOKUP(E13,[1]Material!F$5:U$90000,16,0)="AGIGA"),"AGIGA", OR(LEFT(VLOOKUP(E13,[1]Material!F$5:U$90000,16,0),3)="EF-",VLOOKUP(E13,[1]Material!F$5:U$90000,16,0)="EFI"),"EFI", AND(ISNUMBER(VLOOKUP(E13,[1]Material!F$5:U$90000,16,0)),VLOOKUP(E13,[1]Material!F$5:U$90000,16,0)>=100,VLOOKUP(E13,[1]Material!F$5:U$90000,16,0)<=999,VLOOKUP(E13,[1]Material!F$5:U$90000,16,0)=INT(VLOOKUP(E13,[1]Material!F$5:U$90000,16,0))),"OEM", TRUE,"" ), "không tìm thấy trong file Import" )} -> FORD | V13: =IFERROR(_xlfn.XLOOKUP(E:E,VVMV!B:B,VVMV!J:J),0) -> 0 | W13: =V13+R13 -> 27.161061
... B15: 1K26TFA-00029784 | C15: 734101625 | D15: 46199 | E15: 871633572370 | F15: 46154 | G15: CYMMETRIK SHENZHEN PRINTING CO. LTD | H15: UNIGEN VIETNAM HANOI CO LTD | I15: CN | J15: VN | K15: 2P | L15: 14.4 | M15: 1003834 | N15: 0 | O15: 476821 | P15: 77882 | Q15: 1558537 | R15: =Q15/'Logistics record '!$AD$1 -> 58.897173 | S15: Raw materials | U15: {=IFERROR( _xlfn.IFS( VLOOKUP(E15,[1]Material!F$5:U$90000,16,0)="LUC","Lucid", VLOOKUP(E15,[1]Material!F$5:U$90000,16,0)="FMC","FORD", OR(VLOOKUP(E15,[1]Material!F$5:U$90000,16,0)="PUR",VLOOKUP(E15,[1]Material!F$5:U$90000,16,0)="HLO"),"PURE", VLOOKUP(E15,[1]Material!F$5:U$90000,16,0)="AIC","AIC", OR(VLOOKUP(E15,[1]Material!F$5:U$90000,16,0)="AGI",VLOOKUP(E15,[1]Material!F$5:U$90000,16,0)="AGIGA"),"AGIGA", OR(LEFT(VLOOKUP(E15,[1]Material!F$5:U$90000,16,0),3)="EF-",VLOOKUP(E15,[1]Material!F$5:U$90000,16,0)="EFI"),"EFI", AND(ISNUMBER(VLOOKUP(E15,[1]Material!F$5:U$90000,16,0)),VLOOKUP(E15,[1]Material!F$5:U$90000,16,0)>=100,VLOOKUP(E15,[1]Material!F$5:U$90000,16,0)<=999,VLOOKUP(E15,[1]Material!F$5:U$90000,16,0)=INT(VLOOKUP(E15,[1]Material!F$5:U$90000,16,0))),"OEM", TRUE,"" ), "không tìm thấy trong file Import" )} -> PURE | V15: =IFERROR(_xlfn.XLOOKUP(E:E,VVMV!B:B,VVMV!J:J),0) -> 0 | W15: =V15+R15 -> 58.897173
B16: 1K26TFA-00029784 | C16: 734101625 | D16: 46199 | E16: 871686783285 | F16: 46154 | G16: UNIGEN SHENZHEN | H16: UNIGEN VIET NAM HA NOI CO.LTD | I16: CN | J16: VN | K16: 2P | L16: 0.5 | M16: 343361 | N16: 0 | O16: 163096 | P16: 26640 | Q16: 533097 | R16: =Q16/'Logistics record '!$AD$1 -> 20.145756 | S16: Raw materials | U16: OEM | V16: =IFERROR(_xlfn.XLOOKUP(E:E,VVMV!B:B,VVMV!J:J),0) -> 0 | W16: =V16+R16 -> 20.145756
B17: 1K26TFA-00029784 | C17: 734101625 | D17: 46199 | E17: 518027666436 | F17: 46155 | G17: MICROCHIP TECHNOLOGY (THAILAND). | H17: UNIGEN VIETNAM HANOI CO., LTD | I17: TH | J17: VN | K17: IE | L17: 17.6 | M17: 1120404 | N17: 0 | O17: 532192 | P17: 86927 | Q17: 1739523 | R17: =Q17/'Logistics record '!$AD$1 -> 65.736641 | S17: Raw materials | U17: {=IFERROR( _xlfn.IFS( VLOOKUP(E17,[1]Material!F$5:U$90000,16,0)="LUC","Lucid", VLOOKUP(E17,[1]Material!F$5:U$90000,16,0)="FMC","FORD", OR(VLOOKUP(E17,[1]Material!F$5:U$90000,16,0)="PUR",VLOOKUP(E17,[1]Material!F$5:U$90000,16,0)="HLO"),"PURE", VLOOKUP(E17,[1]Material!F$5:U$90000,16,0)="AIC","AIC", OR(VLOOKUP(E17,[1]Material!F$5:U$90000,16,0)="AGI",VLOOKUP(E17,[1]Material!F$5:U$90000,16,0)="AGIGA"),"AGIGA", OR(LEFT(VLOOKUP(E17,[1]Material!F$5:U$90000,16,0),3)="EF-",VLOOKUP(E17,[1]Material!F$5:U$90000,16,0)="EFI"),"EFI", AND(ISNUMBER(VLOOKUP(E17,[1]Material!F$5:U$90000,16,0)),VLOOKUP(E17,[1]Material!F$5:U$90000,16,0)>=100,VLOOKUP(E17,[1]Material!F$5:U$90000,16,0)<=999,VLOOKUP(E17,[1]Material!F$5:U$90000,16,0)=INT(VLOOKUP(E17,[1]Material!F$5:U$90000,16,0))),"OEM", TRUE,"" ), "không tìm thấy trong file Import" )} -> PURE | V17: =IFERROR(_xlfn.XLOOKUP(E:E,VVMV!B:B,VVMV!J:J),0) -> 0 | W17: =V17+R17 -> 65.736641
B18: 1K26TFA-00029784 | C18: 734101625 | D18: 46199 | E18: 871735931826 | F18: 46156 | G18: TONG LAY DOO INDUSTRIAL CO LTD. | H18: UNIGEN VIETNAM HANOI CO., LTD. | I18: TW | J18: VN | K18: IE | L18: 7.9 | M18: 749957 | N18: 0 | O18: 356230 | P18: 58185 | Q18: 1164372 | R18: =Q18/'Logistics record '!$AD$1 -> 44.001663 | S18: Raw materials | U18: {=IFERROR( _xlfn.IFS( VLOOKUP(E18,[1]Material!F$5:U$90000,16,0)="LUC","Lucid", VLOOKUP(E18,[1]Material!F$5:U$90000,16,0)="FMC","FORD", OR(VLOOKUP(E18,[1]Material!F$5:U$90000,16,0)="PUR",VLOOKUP(E18,[1]Material!F$5:U$90000,16,0)="HLO"),"PURE", VLOOKUP(E18,[1]Material!F$5:U$90000,16,0)="AIC","AIC", OR(VLOOKUP(E18,[1]Material!F$5:U$90000,16,0)="AGI",VLOOKUP(E18,[1]Material!F$5:U$90000,16,0)="AGIGA"),"AGIGA", OR(LEFT(VLOOKUP(E18,[1]Material!F$5:U$90000,16,0),3)="EF-",VLOOKUP(E18,[1]Material!F$5:U$90000,16,0)="EFI"),"EFI", AND(ISNUMBER(VLOOKUP(E18,[1]Material!F$5:U$90000,16,0)),VLOOKUP(E18,[1]Material!F$5:U$90000,16,0)>=100,VLOOKUP(E18,[1]Material!F$5:U$90000,16,0)<=999,VLOOKUP(E18,[1]Material!F$5:U$90000,16,0)=INT(VLOOKUP(E18,[1]Material!F$5:U$90000,16,0))),"OEM", TRUE,"" ), "không tìm thấy trong file Import" )} -> EFI | V18: =IFERROR(_xlfn.XLOOKUP(E:E,VVMV!B:B,VVMV!J:J),0) -> 15.116015 | W18: =V18+R18 -> 59.117678
B19: 1K26TFA-00029784 | C19: 734101625 | D19: 46199 | E19: 472187362457 | F19: 46156 | G19: HEILIND ASIA PACIFIC (SG) PTE LTD | H19: UNIGEN VIETNAM HANOI CO., LTD. | I19: SG | J19: VN | K19: IE | L19: 11.7 | M19: 793805 | N19: 0 | O19: 377057 | P19: 61587 | Q19: 1232449 | R19: =Q19/'Logistics record '!$AD$1 -> 46.574295 | S19: Raw materials | U19: {=IFERROR( _xlfn.IFS( VLOOKUP(E19,[1]Material!F$5:U$90000,16,0)="LUC","Lucid", VLOOKUP(E19,[1]Material!F$5:U$90000,16,0)="FMC","FORD", OR(VLOOKUP(E19,[1]Material!F$5:U$90000,16,0)="PUR",VLOOKUP(E19,[1]Material!F$5:U$90000,16,0)="HLO"),"PURE", VLOOKUP(E19,[1]Material!F$5:U$90000,16,0)="AIC","AIC", OR(VLOOKUP(E19,[1]Material!F$5:U$90000,16,0)="AGI",VLOOKUP(E19,[1]Material!F$5:U$90000,16,0)="AGIGA"),"AGIGA", OR(LEFT(VLOOKUP(E19,[1]Material!F$5:U$90000,16,0),3)="EF-",VLOOKUP(E19,[1]Material!F$5:U$90000,16,0)="EFI"),"EFI", AND(ISNUMBER(VLOOKUP(E19,[1]Material!F$5:U$90000,16,0)),VLOOKUP(E19,[1]Material!F$5:U$90000,16,0)>=100,VLOOKUP(E19,[1]Material!F$5:U$90000,16,0)<=999,VLOOKUP(E19,[1]Material!F$5:U$90000,16,0)=INT(VLOOKUP(E19,[1]Material!F$5:U$90000,16,0))),"OEM", TRUE,"" ), "không tìm thấy trong file Import" )} -> EFI | V19: =IFERROR(_xlfn.XLOOKUP(E:E,VVMV!B:B,VVMV!J:J),0) -> 15.116015 | W19: =V19+R19 -> 61.690311
B20: 1K26TFA-00029784 | C20: 734101625 | D20: 46199 | E20: 871789217180 | F20: 46156 | G20: ELEMENT14 PTE LTD | H20: UNIGEN CORPORATION | I20: SG | J20: VN | K20: IE | L20: 2.5 | M20: 346269 | N20: 0 | O20: 164478 | P20: 26865 | Q20: 537612 | R20: =Q20/'Logistics record '!$AD$1 -> 20.316378 | S20: Raw materials | U20: {=IFERROR( _xlfn.IFS( VLOOKUP(E20,[1]Material!F$5:U$90000,16,0)="LUC","Lucid", VLOOKUP(E20,[1]Material!F$5:U$90000,16,0)="FMC","FORD", OR(VLOOKUP(E20,[1]Material!F$5:U$90000,16,0)="PUR",VLOOKUP(E20,[1]Material!F$5:U$90000,16,0)="HLO"),"PURE", VLOOKUP(E20,[1]Material!F$5:U$90000,16,0)="AIC","AIC", OR(VLOOKUP(E20,[1]Material!F$5:U$90000,16,0)="AGI",VLOOKUP(E20,[1]Material!F$5:U$90000,16,0)="AGIGA"),"AGIGA", OR(LEFT(VLOOKUP(E20,[1]Material!F$5:U$90000,16,0),3)="EF-",VLOOKUP(E20,[1]Material!F$5:U$90000,16,0)="EFI"),"EFI", AND(ISNUMBER(VLOOKUP(E20,[1]Material!F$5:U$90000,16,0)),VLOOKUP(E20,[1]Material!F$5:U$90000,16,0)>=100,VLOOKUP(E20,[1]Material!F$5:U$90000,16,0)<=999,VLOOKUP(E20,[1]Material!F$5:U$90000,16,0)=INT(VLOOKUP(E20,[1]Material!F$5:U$90000,16,0))),"OEM", TRUE,"" ), "không tìm thấy trong file Import" )} -> EFI | V20: =IFERROR(_xlfn.XLOOKUP(E:E,VVMV!B:B,VVMV!J:J),0) -> 15.116015 | W20: =V20+R20 -> 35.432394
B21: 1K26TFA-00029784 | C21: 734101625 | D21: 46199 | E21: 871832889351 | F21: 46157 | G21: VITALSYSTEM TECHNOLOGY PTE LTD | H21: UNIGEN VIETNAM HANOI | I21: SG | J21: VN | K21: IE | L21: 7.7 | M21: 689279 | N21: 0 | O21: 327408 | P21: 53478 | Q21: 1070165 | R21: =Q21/'Logistics record '!$AD$1 -> 40.441577 | S21: Raw materials | U21: {=IFERROR( _xlfn.IFS( VLOOKUP(E21,[1]Material!F$5:U$90000,16,0)="LUC","Lucid", VLOOKUP(E21,[1]Material!F$5:U$90000,16,0)="FMC","FORD", OR(VLOOKUP(E21,[1]Material!F$5:U$90000,16,0)="PUR",VLOOKUP(E21,[1]Material!F$5:U$90000,16,0)="HLO"),"PURE", VLOOKUP(E21,[1]Material!F$5:U$90000,16,0)="AIC","AIC", OR(VLOOKUP(E21,[1]Material!F$5:U$90000,16,0)="AGI",VLOOKUP(E21,[1]Material!F$5:U$90000,16,0)="AGIGA"),"AGIGA", OR(LEFT(VLOOKUP(E21,[1]Material!F$5:U$90000,16,0),3)="EF-",VLOOKUP(E21,[1]Material!F$5:U$90000,16,0)="EFI"),"EFI", AND(ISNUMBER(VLOOKUP(E21,[1]Material!F$5:U$90000,16,0)),VLOOKUP(E21,[1]Material!F$5:U$90000,16,0)>=100,VLOOKUP(E21,[1]Material!F$5:U$90000,16,0)<=999,VLOOKUP(E21,[1]Material!F$5:U$90000,16,0)=INT(VLOOKUP(E21,[1]Material!F$5:U$90000,16,0))),"OEM", TRUE,"" ), "không tìm thấy trong file Import" )} -> OEM | V21: =IFERROR(_xlfn.XLOOKUP(E:E,VVMV!B:B,VVMV!J:J),0) -> 0 | W21: =V21+R21 -> 40.441577
B22: 1K26TFA-00029784 | C22: 734101625 | D22: 46199 | E22: 871830794035 | F22: 46157 | G22: SUNLORD ELECTRONICS TECHNOLOGY PTE | H22: UNIGEN VIET NAM HA NOI CO.LTD | I22: SG | J22: VN | K22: IE | L22: 2.1 | M22: 346269 | N22: 0 | O22: 164478 | P22: 26865 | Q22: 537612 | R22: =Q22/'Logistics record '!$AD$1 -> 20.316378 | S22: Raw materials | U22: {=IFERROR( _xlfn.IFS( VLOOKUP(E22,[1]Material!F$5:U$90000,16,0)="LUC","Lucid", VLOOKUP(E22,[1]Material!F$5:U$90000,16,0)="FMC","FORD", OR(VLOOKUP(E22,[1]Material!F$5:U$90000,16,0)="PUR",VLOOKUP(E22,[1]Material!F$5:U$90000,16,0)="HLO"),"PURE", VLOOKUP(E22,[1]Material!F$5:U$90000,16,0)="AIC","AIC", OR(VLOOKUP(E22,[1]Material!F$5:U$90000,16,0)="AGI",VLOOKUP(E22,[1]Material!F$5:U$90000,16,0)="AGIGA"),"AGIGA", OR(LEFT(VLOOKUP(E22,[1]Material!F$5:U$90000,16,0),3)="EF-",VLOOKUP(E22,[1]Material!F$5:U$90000,16,0)="EFI"),"EFI", AND(ISNUMBER(VLOOKUP(E22,[1]Material!F$5:U$90000,16,0)),VLOOKUP(E22,[1]Material!F$5:U$90000,16,0)>=100,VLOOKUP(E22,[1]Material!F$5:U$90000,16,0)<=999,VLOOKUP(E22,[1]Material!F$5:U$90000,16,0)=INT(VLOOKUP(E22,[1]Material!F$5:U$90000,16,0))),"OEM", TRUE,"" ), "không tìm thấy trong file Import" )} -> PURE | V22: =IFERROR(_xlfn.XLOOKUP(E:E,VVMV!B:B,VVMV!J:J),0) -> 15.116015 | W22: =V22+R22 -> 35.432394
B23: 1K26TFA-00029784 | C23: 734101625 | D23: 46199 | E23: 871835099990 | F23: 46157 | G23: WT MICROELECTRONICS (S) PTE LTD | H23: UNIGEN VIETNAM HANOI CO.,LTD | I23: SG | J23: VN | K23: IE | L23: 15.5 | M23: 850898 | N23: 0 | O23: 404177 | P23: 66017 | Q23: 1321092 | R23: =Q23/'Logistics record '!$AD$1 -> 49.924118 | S23: Raw materials | U23: {=IFERROR( _xlfn.IFS( VLOOKUP(E23,[1]Material!F$5:U$90000,16,0)="LUC","Lucid", VLOOKUP(E23,[1]Material!F$5:U$90000,16,0)="FMC","FORD", OR(VLOOKUP(E23,[1]Material!F$5:U$90000,16,0)="PUR",VLOOKUP(E23,[1]Material!F$5:U$90000,16,0)="HLO"),"PURE", VLOOKUP(E23,[1]Material!F$5:U$90000,16,0)="AIC","AIC", OR(VLOOKUP(E23,[1]Material!F$5:U$90000,16,0)="AGI",VLOOKUP(E23,[1]Material!F$5:U$90000,16,0)="AGIGA"),"AGIGA", OR(LEFT(VLOOKUP(E23,[1]Material!F$5:U$90000,16,0),3)="EF-",VLOOKUP(E23,[1]Material!F$5:U$90000,16,0)="EFI"),"EFI", AND(ISNUMBER(VLOOKUP(E23,[1]Material!F$5:U$90000,16,0)),VLOOKUP(E23,[1]Material!F$5:U$90000,16,0)>=100,VLOOKUP(E23,[1]Material!F$5:U$90000,16,0)<=999,VLOOKUP(E23,[1]Material!F$5:U$90000,16,0)=INT(VLOOKUP(E23,[1]Material!F$5:U$90000,16,0))),"OEM", TRUE,"" ), "không tìm thấy trong file Import" )} -> EFI | V23: =IFERROR(_xlfn.XLOOKUP(E:E,VVMV!B:B,VVMV!J:J),0) -> 0 | W23: =V23+R23 -> 49.924118
B24: 1K26TFA-00029784 | C24: 734101625 | D24: 46199 | E24: 523488275340 | F24: 46157 | G24: WPG SOUTH ASIA PTE. LTD | H24: UNIGEN CORPORATION | I24: SG | J24: VN | K24: IE | L24: 6.1 | M24: 620487 | N24: 0 | O24: 294731 | P24: 48140 | Q24: 963358 | R24: =Q24/'Logistics record '!$AD$1 -> 36.405336 | S24: Raw materials | U24: {=IFERROR( _xlfn.IFS( VLOOKUP(E24,[1]Material!F$5:U$90000,16,0)="LUC","Lucid", VLOOKUP(E24,[1]Material!F$5:U$90000,16,0)="FMC","FORD", OR(VLOOKUP(E24,[1]Material!F$5:U$90000,16,0)="PUR",VLOOKUP(E24,[1]Material!F$5:U$90000,16,0)="HLO"),"PURE", VLOOKUP(E24,[1]Material!F$5:U$90000,16,0)="AIC","AIC", OR(VLOOKUP(E24,[1]Material!F$5:U$90000,16,0)="AGI",VLOOKUP(E24,[1]Material!F$5:U$90000,16,0)="AGIGA"),"AGIGA", OR(LEFT(VLOOKUP(E24,[1]Material!F$5:U$90000,16,0),3)="EF-",VLOOKUP(E24,[1]Material!F$5:U$90000,16,0)="EFI"),"EFI", AND(ISNUMBER(VLOOKUP(E24,[1]Material!F$5:U$90000,16,0)),VLOOKUP(E24,[1]Material!F$5:U$90000,16,0)>=100,VLOOKUP(E24,[1]Material!F$5:U$90000,16,0)<=999,VLOOKUP(E24,[1]Material!F$5:U$90000,16,0)=INT(VLOOKUP(E24,[1]Material!F$5:U$90000,16,0))),"OEM", TRUE,"" ), "không tìm thấy trong file Import" )} -> Lucid | V24: =IFERROR(_xlfn.XLOOKUP(E:E,VVMV!B:B,VVMV!J:J),0) -> 0 | W24: =V24+R24 -> 36.405336
B25: 1K26TFA-00029784 | C25: 734101625 | D25: 46199 | E25: 484361666828 | F25: 46157 | G25: COILCRAFT SINGAPORE PTE LTD | H25: UNIGEN VIETNAM HANOI | I25: SG | J25: VN | K25: IE | L25: 5.2 | M25: 574625 | N25: 0 | O25: 272947 | P25: 44582 | Q25: 892154 | R25: =Q25/'Logistics record '!$AD$1 -> 33.714534 | S25: Raw materials | U25: {=IFERROR( _xlfn.IFS( VLOOKUP(E25,[1]Material!F$5:U$90000,16,0)="LUC","Lucid", VLOOKUP(E25,[1]Material!F$5:U$90000,16,0)="FMC","FORD", OR(VLOOKUP(E25,[1]Material!F$5:U$90000,16,0)="PUR",VLOOKUP(E25,[1]Material!F$5:U$90000,16,0)="HLO"),"PURE", VLOOKUP(E25,[1]Material!F$5:U$90000,16,0)="AIC","AIC", OR(VLOOKUP(E25,[1]Material!F$5:U$90000,16,0)="AGI",VLOOKUP(E25,[1]Material!F$5:U$90000,16,0)="AGIGA"),"AGIGA", OR(LEFT(VLOOKUP(E25,[1]Material!F$5:U$90000,16,0),3)="EF-",VLOOKUP(E25,[1]Material!F$5:U$90000,16,0)="EFI"),"EFI", AND(ISNUMBER(VLOOKUP(E25,[1]Material!F$5:U$90000,16,0)),VLOOKUP(E25,[1]Material!F$5:U$90000,16,0)>=100,VLOOKUP(E25,[1]Material!F$5:U$90000,16,0)<=999,VLOOKUP(E25,[1]Material!F$5:U$90000,16,0)=INT(VLOOKUP(E25,[1]Material!F$5:U$90000,16,0))),"OEM", TRUE,"" ), "không tìm thấy trong file Import" )} -> Lucid | V25: =IFERROR(_xlfn.XLOOKUP(E:E,VVMV!B:B,VVMV!J:J),0) -> 15.116015 | W25: =V25+R25 -> 48.830549
B26: 1K26TFA-00029784 | C26: 734101625 | D26: 46199 | E26: 871831431473 | F26: 46158 | G26: SUNLORD ELECTRONICS TECHNOLOGY PTE | H26: UNIGEN VIET NAM HA NOI CO.LTD | I26: HK | J26: VN | K26: IE | L26: 36.4 | M26: 1974224 | N26: 0 | O26: 937756 | P26: 153170 | Q26: 3065150 | R26: =Q26/'Logistics record '!$AD$1 -> 115.83214 | S26: Raw materials | U26: {=IFERROR( _xlfn.IFS( VLOOKUP(E26,[1]Material!F$5:U$90000,16,0)="LUC","Lucid", VLOOKUP(E26,[1]Material!F$5:U$90000,16,0)="FMC","FORD", OR(VLOOKUP(E26,[1]Material!F$5:U$90000,16,0)="PUR",VLOOKUP(E26,[1]Material!F$5:U$90000,16,0)="HLO"),"PURE", VLOOKUP(E26,[1]Material!F$5:U$90000,16,0)="AIC","AIC", OR(VLOOKUP(E26,[1]Material!F$5:U$90000,16,0)="AGI",VLOOKUP(E26,[1]Material!F$5:U$90000,16,0)="AGIGA"),"AGIGA", OR(LEFT(VLOOKUP(E26,[1]Material!F$5:U$90000,16,0),3)="EF-",VLOOKUP(E26,[1]Material!F$5:U$90000,16,0)="EFI"),"EFI", AND(ISNUMBER(VLOOKUP(E26,[1]Material!F$5:U$90000,16,0)),VLOOKUP(E26,[1]Material!F$5:U$90000,16,0)>=100,VLOOKUP(E26,[1]Material!F$5:U$90000,16,0)<=999,VLOOKUP(E26,[1]Material!F$5:U$90000,16,0)=INT(VLOOKUP(E26,[1]Material!F$5:U$90000,16,0))),"OEM", TRUE,"" ), "không tìm thấy trong file Import" )} -> OEM | V26: =IFERROR(_xlfn.XLOOKUP(E:E,VVMV!B:B,VVMV!J:J),0) -> 15.116015 | W26: =V26+R26 -> 130.94815
B27: 1K26TFA-00029784 | C27: 734101625 | D27: 46199 | E27: 381352210471 | F27: 46158 | G27: ANALOG DEVICES (THAILAND) CO.,LTD | H27: UNIGEN CORPORATION | I27: TH | J27: VN | K27: IE | L27: 2 | M27: 455598 | N27: 0 | O27: 216409 | P27: 35348 | Q27: 707355 | R27: =Q27/'Logistics record '!$AD$1 -> 26.730973 | S27: Raw materials | U27: {=IFERROR( _xlfn.IFS( VLOOKUP(E27,[1]Material!F$5:U$90000,16,0)="LUC","Lucid", VLOOKUP(E27,[1]Material!F$5:U$90000,16,0)="FMC","FORD", OR(VLOOKUP(E27,[1]Material!F$5:U$90000,16,0)="PUR",VLOOKUP(E27,[1]Material!F$5:U$90000,16,0)="HLO"),"PURE", VLOOKUP(E27,[1]Material!F$5:U$90000,16,0)="AIC","AIC", OR(VLOOKUP(E27,[1]Material!F$5:U$90000,16,0)="AGI",VLOOKUP(E27,[1]Material!F$5:U$90000,16,0)="AGIGA"),"AGIGA", OR(LEFT(VLOOKUP(E27,[1]Material!F$5:U$90000,16,0),3)="EF-",VLOOKUP(E27,[1]Material!F$5:U$90000,16,0)="EFI"),"EFI", AND(ISNUMBER(VLOOKUP(E27,[1]Material!F$5:U$90000,16,0)),VLOOKUP(E27,[1]Material!F$5:U$90000,16,0)>=100,VLOOKUP(E27,[1]Material!F$5:U$90000,16,0)<=999,VLOOKUP(E27,[1]Material!F$5:U$90000,16,0)=INT(VLOOKUP(E27,[1]Material!F$5:U$90000,16,0))),"OEM", TRUE,"" ), "không tìm thấy trong file Import" )} -> PURE | V27: =IFERROR(_xlfn.XLOOKUP(E:E,VVMV!B:B,VVMV!J:J),0) -> 15.116015 | W27: =V27+R27 -> 41.846988
B28: 1K26TFA-00029784 | C28: 734101625 | D28: 46199 | E28: 871907578288 | F28: 46160 | G28: ELEMENT14 PTE LTD | H28: UNIGEN CORPORATION | I28: SG | J28: VN | K28: IE | L28: 3.7 | M28: 470100 | N28: 0 | O28: 229174 | P28: 36782 | Q28: 736056 | R28: =Q28/'Logistics record '!$AD$1 -> 27.815585 | S28: Raw materials | U28: {=IFERROR( _xlfn.IFS( VLOOKUP(E28,[1]Material!F$5:U$90000,16,0)="LUC","Lucid", VLOOKUP(E28,[1]Material!F$5:U$90000,16,0)="FMC","FORD", OR(VLOOKUP(E28,[1]Material!F$5:U$90000,16,0)="PUR",VLOOKUP(E28,[1]Material!F$5:U$90000,16,0)="HLO"),"PURE", VLOOKUP(E28,[1]Material!F$5:U$90000,16,0)="AIC","AIC", OR(VLOOKUP(E28,[1]Material!F$5:U$90000,16,0)="AGI",VLOOKUP(E28,[1]Material!F$5:U$90000,16,0)="AGIGA"),"AGIGA", OR(LEFT(VLOOKUP(E28,[1]Material!F$5:U$90000,16,0),3)="EF-",VLOOKUP(E28,[1]Material!F$5:U$90000,16,0)="EFI"),"EFI", AND(ISNUMBER(VLOOKUP(E28,[1]Material!F$5:U$90000,16,0)),VLOOKUP(E28,[1]Material!F$5:U$90000,16,0)>=100,VLOOKUP(E28,[1]Material!F$5:U$90000,16,0)<=999,VLOOKUP(E28,[1]Material!F$5:U$90000,16,0)=INT(VLOOKUP(E28,[1]Material!F$5:U$90000,16,0))),"OEM", TRUE,"" ), "không tìm thấy trong file Import" )} -> FORD | V28: =IFERROR(_xlfn.XLOOKUP(E:E,VVMV!B:B,VVMV!J:J),0) -> 0 | W28: =V28+R28 -> 27.815585
... B56: 1K26TFA-00029784 | C56: 734101625 | D56: 46199 | E56: 472187612303 | F56: 46171 | G56: HEILIND ASIA PACIFIC | H56: UNIGEN VIETNAM HANOI CO., LTD. | I56: HK | J56: VN | K56: IE | L56: 26.5 | M56: 1440650 | N56: 0 | O56: 713122 | P56: 113288 | Q56: 2267060 | R56: =Q56/'Logistics record '!$AD$1 -> 85.672285 | S56: Raw materials | U56: {=IFERROR( _xlfn.IFS( VLOOKUP(E56,[1]Material!F$5:U$90000,16,0)="LUC","Lucid", VLOOKUP(E56,[1]Material!F$5:U$90000,16,0)="FMC","FORD", OR(VLOOKUP(E56,[1]Material!F$5:U$90000,16,0)="PUR",VLOOKUP(E56,[1]Material!F$5:U$90000,16,0)="HLO"),"PURE", VLOOKUP(E56,[1]Material!F$5:U$90000,16,0)="AIC","AIC", OR(VLOOKUP(E56,[1]Material!F$5:U$90000,16,0)="AGI",VLOOKUP(E56,[1]Material!F$5:U$90000,16,0)="AGIGA"),"AGIGA", OR(LEFT(VLOOKUP(E56,[1]Material!F$5:U$90000,16,0),3)="EF-",VLOOKUP(E56,[1]Material!F$5:U$90000,16,0)="EFI"),"EFI", AND(ISNUMBER(VLOOKUP(E56,[1]Material!F$5:U$90000,16,0)),VLOOKUP(E56,[1]Material!F$5:U$90000,16,0)>=100,VLOOKUP(E56,[1]Material!F$5:U$90000,16,0)<=999,VLOOKUP(E56,[1]Material!F$5:U$90000,16,0)=INT(VLOOKUP(E56,[1]Material!F$5:U$90000,16,0))),"OEM", TRUE,"" ), "không tìm thấy trong file Import" )} -> EFI | V56: =IFERROR(_xlfn.XLOOKUP(E:E,VVMV!B:B,VVMV!J:J),0) -> 15.116015 | W56: =V56+R56 -> 100.7883
B57: 1K26TFA-00029784 | C57: 734101625 | D57: 46199 | E57: 809262197260 | F57: 46171 | G57: UNIGEN HK LTD | H57: UNIGEN VIETNAM HANOI | I57: HK | J57: VN | K57: 2P | L57: 31.8 | M57: 1914085 | N57: 0 | O57: 947472 | P57: 150518 | Q57: 3012075 | R57: =Q57/'Logistics record '!$AD$1 -> 113.82643 | S57: Raw materials | U57: {=IFERROR( _xlfn.IFS( VLOOKUP(E57,[1]Material!F$5:U$90000,16,0)="LUC","Lucid", VLOOKUP(E57,[1]Material!F$5:U$90000,16,0)="FMC","FORD", OR(VLOOKUP(E57,[1]Material!F$5:U$90000,16,0)="PUR",VLOOKUP(E57,[1]Material!F$5:U$90000,16,0)="HLO"),"PURE", VLOOKUP(E57,[1]Material!F$5:U$90000,16,0)="AIC","AIC", OR(VLOOKUP(E57,[1]Material!F$5:U$90000,16,0)="AGI",VLOOKUP(E57,[1]Material!F$5:U$90000,16,0)="AGIGA"),"AGIGA", OR(LEFT(VLOOKUP(E57,[1]Material!F$5:U$90000,16,0),3)="EF-",VLOOKUP(E57,[1]Material!F$5:U$90000,16,0)="EFI"),"EFI", AND(ISNUMBER(VLOOKUP(E57,[1]Material!F$5:U$90000,16,0)),VLOOKUP(E57,[1]Material!F$5:U$90000,16,0)>=100,VLOOKUP(E57,[1]Material!F$5:U$90000,16,0)<=999,VLOOKUP(E57,[1]Material!F$5:U$90000,16,0)=INT(VLOOKUP(E57,[1]Material!F$5:U$90000,16,0))),"OEM", TRUE,"" ), "không tìm thấy trong file Import" )} -> OEM | V57: =IFERROR(_xlfn.XLOOKUP(E:E,VVMV!B:B,VVMV!J:J),0) -> 15.116015 | W57: =V57+R57 -> 128.94245 | Y57: Checking additional Handling charge
B58: 1K26TFA-00029784 | C58: 734101625 | D58: 46199 | E58: 381606778459 | F58: 46171 | G58: TEXAS INSTRUMENTS ASIA LIMITED | H58: UNIGEN VIETNAM HANOI CO., LTD. | I58: CN | J58: VN | K58: IE | L58: 8.3 | M58: 569407 | N58: 0 | O58: 281856 | P58: 44776 | Q58: 896039 | R58: =Q58/'Logistics record '!$AD$1 -> 33.861348 | S58: Raw materials | U58: {=IFERROR( _xlfn.IFS( VLOOKUP(E58,[1]Material!F$5:U$90000,16,0)="LUC","Lucid", VLOOKUP(E58,[1]Material!F$5:U$90000,16,0)="FMC","FORD", OR(VLOOKUP(E58,[1]Material!F$5:U$90000,16,0)="PUR",VLOOKUP(E58,[1]Material!F$5:U$90000,16,0)="HLO"),"PURE", VLOOKUP(E58,[1]Material!F$5:U$90000,16,0)="AIC","AIC", OR(VLOOKUP(E58,[1]Material!F$5:U$90000,16,0)="AGI",VLOOKUP(E58,[1]Material!F$5:U$90000,16,0)="AGIGA"),"AGIGA", OR(LEFT(VLOOKUP(E58,[1]Material!F$5:U$90000,16,0),3)="EF-",VLOOKUP(E58,[1]Material!F$5:U$90000,16,0)="EFI"),"EFI", AND(ISNUMBER(VLOOKUP(E58,[1]Material!F$5:U$90000,16,0)),VLOOKUP(E58,[1]Material!F$5:U$90000,16,0)>=100,VLOOKUP(E58,[1]Material!F$5:U$90000,16,0)<=999,VLOOKUP(E58,[1]Material!F$5:U$90000,16,0)=INT(VLOOKUP(E58,[1]Material!F$5:U$90000,16,0))),"OEM", TRUE,"" ), "không tìm thấy trong file Import" )} -> OEM | V58: =IFERROR(_xlfn.XLOOKUP(E:E,VVMV!B:B,VVMV!J:J),0) -> 15.116015 | W58: =V58+R58 -> 48.977364
B59: 1K26TFA-00029784 | C59: 734101625 | D59: 46199 | E59: 872205227423 | F59: 46171 | G59: AMA INTERNATIONAL FREIGHT LTD | H59: UNIGEN VIETNAM HANOI CO., LTD. | I59: HK | J59: VN | K59: IE | L59: 13.2 | M59: 873677 | N59: 0 | O59: 432470 | P59: 68703 | Q59: 1374850 | R59: =Q59/'Logistics record '!$AD$1 -> 51.955634 | S59: Raw materials | U59: {=IFERROR( _xlfn.IFS( VLOOKUP(E59,[1]Material!F$5:U$90000,16,0)="LUC","Lucid", VLOOKUP(E59,[1]Material!F$5:U$90000,16,0)="FMC","FORD", OR(VLOOKUP(E59,[1]Material!F$5:U$90000,16,0)="PUR",VLOOKUP(E59,[1]Material!F$5:U$90000,16,0)="HLO"),"PURE", VLOOKUP(E59,[1]Material!F$5:U$90000,16,0)="AIC","AIC", OR(VLOOKUP(E59,[1]Material!F$5:U$90000,16,0)="AGI",VLOOKUP(E59,[1]Material!F$5:U$90000,16,0)="AGIGA"),"AGIGA", OR(LEFT(VLOOKUP(E59,[1]Material!F$5:U$90000,16,0),3)="EF-",VLOOKUP(E59,[1]Material!F$5:U$90000,16,0)="EFI"),"EFI", AND(ISNUMBER(VLOOKUP(E59,[1]Material!F$5:U$90000,16,0)),VLOOKUP(E59,[1]Material!F$5:U$90000,16,0)>=100,VLOOKUP(E59,[1]Material!F$5:U$90000,16,0)<=999,VLOOKUP(E59,[1]Material!F$5:U$90000,16,0)=INT(VLOOKUP(E59,[1]Material!F$5:U$90000,16,0))),"OEM", TRUE,"" ), "không tìm thấy trong file Import" )} -> EFI | V59: =IFERROR(_xlfn.XLOOKUP(E:E,VVMV!B:B,VVMV!J:J),0) -> 15.116015 | W59: =V59+R59 -> 67.07165
B60: 1K26TFA-00029784 | C60: 734101625 | D60: 46199 | E60: 872375217260 | F60: 46171 | G60: UNIGEN TECHNOLOGY SDN BHD | H60: UNIGEN VIETNAM HA NOI CO.LTD. | I60: MY | J60: VN | K60: 2P | L60: 0.5 | M60: 300774 | N60: 0 | O60: 148883 | P60: 23652 | Q60: 473309 | R60: =Q60/'Logistics record '!$AD$1 -> 17.886365 | S60: Raw materials | U60: {=IFERROR( _xlfn.IFS( VLOOKUP(E60,[1]Material!F$5:U$90000,16,0)="LUC","Lucid", VLOOKUP(E60,[1]Material!F$5:U$90000,16,0)="FMC","FORD", OR(VLOOKUP(E60,[1]Material!F$5:U$90000,16,0)="PUR",VLOOKUP(E60,[1]Material!F$5:U$90000,16,0)="HLO"),"PURE", VLOOKUP(E60,[1]Material!F$5:U$90000,16,0)="AIC","AIC", OR(VLOOKUP(E60,[1]Material!F$5:U$90000,16,0)="AGI",VLOOKUP(E60,[1]Material!F$5:U$90000,16,0)="AGIGA"),"AGIGA", OR(LEFT(VLOOKUP(E60,[1]Material!F$5:U$90000,16,0),3)="EF-",VLOOKUP(E60,[1]Material!F$5:U$90000,16,0)="EFI"),"EFI", AND(ISNUMBER(VLOOKUP(E60,[1]Material!F$5:U$90000,16,0)),VLOOKUP(E60,[1]Material!F$5:U$90000,16,0)>=100,VLOOKUP(E60,[1]Material!F$5:U$90000,16,0)<=999,VLOOKUP(E60,[1]Material!F$5:U$90000,16,0)=INT(VLOOKUP(E60,[1]Material!F$5:U$90000,16,0))),"OEM", TRUE,"" ), "không tìm thấy trong file Import" )} -> OEM | V60: =IFERROR(_xlfn.XLOOKUP(E:E,VVMV!B:B,VVMV!J:J),0) -> 15.116015 | W60: =V60+R60 -> 33.002381
B61: 1K26TFA-00029784 | C61: 734101625 | D61: 46199 | E61: 381660504209 | F61: 46171 | G61: TEXAS INSTRUMENTS SOUTHEAST ASIA PT | H61: UNIGEN VIETNAM HANOI CO., LTD. | I61: SG | J61: VN | K61: IE | L61: 11.5 | M61: 785649 | N61: 0 | O61: 388896 | P61: 61781 | Q61: 1236326 | R61: =Q61/'Logistics record '!$AD$1 -> 46.720807 | S61: Raw materials | U61: {=IFERROR( _xlfn.IFS( VLOOKUP(E61,[1]Material!F$5:U$90000,16,0)="LUC","Lucid", VLOOKUP(E61,[1]Material!F$5:U$90000,16,0)="FMC","FORD", OR(VLOOKUP(E61,[1]Material!F$5:U$90000,16,0)="PUR",VLOOKUP(E61,[1]Material!F$5:U$90000,16,0)="HLO"),"PURE", VLOOKUP(E61,[1]Material!F$5:U$90000,16,0)="AIC","AIC", OR(VLOOKUP(E61,[1]Material!F$5:U$90000,16,0)="AGI",VLOOKUP(E61,[1]Material!F$5:U$90000,16,0)="AGIGA"),"AGIGA", OR(LEFT(VLOOKUP(E61,[1]Material!F$5:U$90000,16,0),3)="EF-",VLOOKUP(E61,[1]Material!F$5:U$90000,16,0)="EFI"),"EFI", AND(ISNUMBER(VLOOKUP(E61,[1]Material!F$5:U$90000,16,0)),VLOOKUP(E61,[1]Material!F$5:U$90000,16,0)>=100,VLOOKUP(E61,[1]Material!F$5:U$90000,16,0)<=999,VLOOKUP(E61,[1]Material!F$5:U$90000,16,0)=INT(VLOOKUP(E61,[1]Material!F$5:U$90000,16,0))),"OEM", TRUE,"" ), "không tìm thấy trong file Import" )} -> PURE | V61: =IFERROR(_xlfn.XLOOKUP(E:E,VVMV!B:B,VVMV!J:J),0) -> 15.116015 | W61: =V61+R61 -> 61.836823
B62: 1K26TFA-00029784 | C62: 734101625 | D62: 46199 | E62: 872378270097 | F62: 46171 | G62: VITALSYSTEM TECHNOLOGY PTE LTD | H62: UNIGEN VIETNAM HANOI | I62: SG | J62: VN | K62: 2P | L62: 7.8 | M62: 703054 | N62: 0 | O62: 348012 | P62: 55286 | Q62: 1106352 | R62: =Q62/'Logistics record '!$AD$1 -> 41.809085 | S62: Raw materials | U62: {=IFERROR( _xlfn.IFS( VLOOKUP(E62,[1]Material!F$5:U$90000,16,0)="LUC","Lucid", VLOOKUP(E62,[1]Material!F$5:U$90000,16,0)="FMC","FORD", OR(VLOOKUP(E62,[1]Material!F$5:U$90000,16,0)="PUR",VLOOKUP(E62,[1]Material!F$5:U$90000,16,0)="HLO"),"PURE", VLOOKUP(E62,[1]Material!F$5:U$90000,16,0)="AIC","AIC", OR(VLOOKUP(E62,[1]Material!F$5:U$90000,16,0)="AGI",VLOOKUP(E62,[1]Material!F$5:U$90000,16,0)="AGIGA"),"AGIGA", OR(LEFT(VLOOKUP(E62,[1]Material!F$5:U$90000,16,0),3)="EF-",VLOOKUP(E62,[1]Material!F$5:U$90000,16,0)="EFI"),"EFI", AND(ISNUMBER(VLOOKUP(E62,[1]Material!F$5:U$90000,16,0)),VLOOKUP(E62,[1]Material!F$5:U$90000,16,0)>=100,VLOOKUP(E62,[1]Material!F$5:U$90000,16,0)<=999,VLOOKUP(E62,[1]Material!F$5:U$90000,16,0)=INT(VLOOKUP(E62,[1]Material!F$5:U$90000,16,0))),"OEM", TRUE,"" ), "không tìm thấy trong file Import" )} -> PURE | V62: =IFERROR(_xlfn.XLOOKUP(E:E,VVMV!B:B,VVMV!J:J),0) -> 15.116015 | W62: =V62+R62 -> 56.9251
B63: 1K26TFA-00029784 | C63: 734101625 | D63: 46199 | E63: 381681556134 | F63: 46172 | G63: TEXAS INSTRUMENTS SOUTHEAST ASIA PT | H63: UNIGEN VIETNAM HANOI CO., LTD. | I63: SG | J63: VN | K63: IE | L63: 70.6 | M63: 3225849 | N63: 0 | O63: 1596795 | P63: 253671 | Q63: 5076315 | R63: =Q63/'Logistics record '!$AD$1 -> 191.83414 | S63: Raw materials | U63: {=IFERROR( _xlfn.IFS( VLOOKUP(E63,[1]Material!F$5:U$90000,16,0)="LUC","Lucid", VLOOKUP(E63,[1]Material!F$5:U$90000,16,0)="FMC","FORD", OR(VLOOKUP(E63,[1]Material!F$5:U$90000,16,0)="PUR",VLOOKUP(E63,[1]Material!F$5:U$90000,16,0)="HLO"),"PURE", VLOOKUP(E63,[1]Material!F$5:U$90000,16,0)="AIC","AIC", OR(VLOOKUP(E63,[1]Material!F$5:U$90000,16,0)="AGI",VLOOKUP(E63,[1]Material!F$5:U$90000,16,0)="AGIGA"),"AGIGA", OR(LEFT(VLOOKUP(E63,[1]Material!F$5:U$90000,16,0),3)="EF-",VLOOKUP(E63,[1]Material!F$5:U$90000,16,0)="EFI"),"EFI", AND(ISNUMBER(VLOOKUP(E63,[1]Material!F$5:U$90000,16,0)),VLOOKUP(E63,[1]Material!F$5:U$90000,16,0)>=100,VLOOKUP(E63,[1]Material!F$5:U$90000,16,0)<=999,VLOOKUP(E63,[1]Material!F$5:U$90000,16,0)=INT(VLOOKUP(E63,[1]Material!F$5:U$90000,16,0))),"OEM", TRUE,"" ), "không tìm thấy trong file Import" )} -> Lucid | V63: =IFERROR(_xlfn.XLOOKUP(E:E,VVMV!B:B,VVMV!J:J),0) -> 15.116015 | W63: =V63+R63 -> 206.95015
B64: 1K26TFA-00029784 | C64: 734101625 | D64: 46199 | E64: 381664000889 | F64: 46172 | G64: TEXAS INSTRUMENTS SOUTHEAST ASIA PT | H64: UNIGEN VIETNAM HANOI CO., LTD. | I64: SG | J64: VN | K64: IE | L64: 27.7 | M64: 1455948 | N64: 0 | O64: 720694 | P64: 114491 | Q64: 2291133 | R64: =Q64/'Logistics record '!$AD$1 -> 86.582004 | S64: Raw materials | U64: {=IFERROR( _xlfn.IFS( VLOOKUP(E64,[1]Material!F$5:U$90000,16,0)="LUC","Lucid", VLOOKUP(E64,[1]Material!F$5:U$90000,16,0)="FMC","FORD", OR(VLOOKUP(E64,[1]Material!F$5:U$90000,16,0)="PUR",VLOOKUP(E64,[1]Material!F$5:U$90000,16,0)="HLO"),"PURE", VLOOKUP(E64,[1]Material!F$5:U$90000,16,0)="AIC","AIC", OR(VLOOKUP(E64,[1]Material!F$5:U$90000,16,0)="AGI",VLOOKUP(E64,[1]Material!F$5:U$90000,16,0)="AGIGA"),"AGIGA", OR(LEFT(VLOOKUP(E64,[1]Material!F$5:U$90000,16,0),3)="EF-",VLOOKUP(E64,[1]Material!F$5:U$90000,16,0)="EFI"),"EFI", AND(ISNUMBER(VLOOKUP(E64,[1]Material!F$5:U$90000,16,0)),VLOOKUP(E64,[1]Material!F$5:U$90000,16,0)>=100,VLOOKUP(E64,[1]Material!F$5:U$90000,16,0)<=999,VLOOKUP(E64,[1]Material!F$5:U$90000,16,0)=INT(VLOOKUP(E64,[1]Material!F$5:U$90000,16,0))),"OEM", TRUE,"" ), "không tìm thấy trong file Import" )} -> PURE | V64: =IFERROR(_xlfn.XLOOKUP(E:E,VVMV!B:B,VVMV!J:J),0) -> 15.116015 | W64: =V64+R64 -> 101.69802
B65: 1K26TFA-00029784 | C65: 734101625 | D65: 46199 | E65: 527529842090 | F65: 46172 | G65: MICROCHIP TECHNOLOGY (THAILAND). | H65: UNIGEN VIETNAM HANOI CO., LTD | I65: TH | J65: VN | K65: IE | L65: 6.4 | M65: 720489 | N65: 0 | O65: 356642 | P65: 56657 | Q65: 1133788 | R65: =Q65/'Logistics record '!$AD$1 -> 42.845892 | S65: Raw materials | U65: {=IFERROR( _xlfn.IFS( VLOOKUP(E65,[1]Material!F$5:U$90000,16,0)="LUC","Lucid", VLOOKUP(E65,[1]Material!F$5:U$90000,16,0)="FMC","FORD", OR(VLOOKUP(E65,[1]Material!F$5:U$90000,16,0)="PUR",VLOOKUP(E65,[1]Material!F$5:U$90000,16,0)="HLO"),"PURE", VLOOKUP(E65,[1]Material!F$5:U$90000,16,0)="AIC","AIC", OR(VLOOKUP(E65,[1]Material!F$5:U$90000,16,0)="AGI",VLOOKUP(E65,[1]Material!F$5:U$90000,16,0)="AGIGA"),"AGIGA", OR(LEFT(VLOOKUP(E65,[1]Material!F$5:U$90000,16,0),3)="EF-",VLOOKUP(E65,[1]Material!F$5:U$90000,16,0)="EFI"),"EFI", AND(ISNUMBER(VLOOKUP(E65,[1]Material!F$5:U$90000,16,0)),VLOOKUP(E65,[1]Material!F$5:U$90000,16,0)>=100,VLOOKUP(E65,[1]Material!F$5:U$90000,16,0)<=999,VLOOKUP(E65,[1]Material!F$5:U$90000,16,0)=INT(VLOOKUP(E65,[1]Material!F$5:U$90000,16,0))),"OEM", TRUE,"" ), "không tìm thấy trong file Import" )} -> PURE | V65: =IFERROR(_xlfn.XLOOKUP(E:E,VVMV!B:B,VVMV!J:J),0) -> 15.116015 | W65: =V65+R65 -> 57.961908
B66: 1K26TFA-00029784 | C66: 734101625 | D66: 46199 | E66: 381669260252 | F66: 46172 | G66: TEXAS INSTRUMENTS ASIA LIMITED | H66: UNIGEN VIETNAM HANOI CO., LTD. | I66: CN | J66: VN | K66: IE | L66: 1.1 | M66: 359912 | N66: 0 | O66: 178156 | P66: 28302 | Q66: 566370 | R66: =Q66/'Logistics record '!$AD$1 -> 21.403144 | S66: Raw materials | U66: {=IFERROR( _xlfn.IFS( VLOOKUP(E66,[1]Material!F$5:U$90000,16,0)="LUC","Lucid", VLOOKUP(E66,[1]Material!F$5:U$90000,16,0)="FMC","FORD", OR(VLOOKUP(E66,[1]Material!F$5:U$90000,16,0)="PUR",VLOOKUP(E66,[1]Material!F$5:U$90000,16,0)="HLO"),"PURE", VLOOKUP(E66,[1]Material!F$5:U$90000,16,0)="AIC","AIC", OR(VLOOKUP(E66,[1]Material!F$5:U$90000,16,0)="AGI",VLOOKUP(E66,[1]Material!F$5:U$90000,16,0)="AGIGA"),"AGIGA", OR(LEFT(VLOOKUP(E66,[1]Material!F$5:U$90000,16,0),3)="EF-",VLOOKUP(E66,[1]Material!F$5:U$90000,16,0)="EFI"),"EFI", AND(ISNUMBER(VLOOKUP(E66,[1]Material!F$5:U$90000,16,0)),VLOOKUP(E66,[1]Material!F$5:U$90000,16,0)>=100,VLOOKUP(E66,[1]Material!F$5:U$90000,16,0)<=999,VLOOKUP(E66,[1]Material!F$5:U$90000,16,0)=INT(VLOOKUP(E66,[1]Material!F$5:U$90000,16,0))),"OEM", TRUE,"" ), "không tìm thấy trong file Import" )} -> PURE | V66: =IFERROR(_xlfn.XLOOKUP(E:E,VVMV!B:B,VVMV!J:J),0) -> 15.116015 | W66: =V66+R66 -> 36.51916
B67: 1K26TFA-00029784 | C67: 734101625 | D67: 46199 | E67: 872449029491 | F67: 46174 | G67: ARC ELECTRO INDUSTRY CORP | H67: UNIGEN VIETNAM HANOI CO., LTD | I67: TW | J67: VN | K67: IE | L67: 0.5 | M67: 374870 | N67: 0 | O67: 184623 | P67: 29429 | Q67: 588922 | R67: =Q67/'Logistics record '!$AD$1 -> 22.255385 | S67: Raw materials | U67: {=IFERROR( _xlfn.IFS( VLOOKUP(E67,[1]Material!F$5:U$90000,16,0)="LUC","Lucid", VLOOKUP(E67,[1]Material!F$5:U$90000,16,0)="FMC","FORD", OR(VLOOKUP(E67,[1]Material!F$5:U$90000,16,0)="PUR",VLOOKUP(E67,[1]Material!F$5:U$90000,16,0)="HLO"),"PURE", VLOOKUP(E67,[1]Material!F$5:U$90000,16,0)="AIC","AIC", OR(VLOOKUP(E67,[1]Material!F$5:U$90000,16,0)="AGI",VLOOKUP(E67,[1]Material!F$5:U$90000,16,0)="AGIGA"),"AGIGA", OR(LEFT(VLOOKUP(E67,[1]Material!F$5:U$90000,16,0),3)="EF-",VLOOKUP(E67,[1]Material!F$5:U$90000,16,0)="EFI"),"EFI", AND(ISNUMBER(VLOOKUP(E67,[1]Material!F$5:U$90000,16,0)),VLOOKUP(E67,[1]Material!F$5:U$90000,16,0)>=100,VLOOKUP(E67,[1]Material!F$5:U$90000,16,0)<=999,VLOOKUP(E67,[1]Material!F$5:U$90000,16,0)=INT(VLOOKUP(E67,[1]Material!F$5:U$90000,16,0))),"OEM", TRUE,"" ), "không tìm thấy trong file Import" )} -> AIC | V67: =IFERROR(_xlfn.XLOOKUP(E:E,VVMV!B:B,VVMV!J:J),0) -> 15.116015 | W67: =V67+R67 -> 37.3714
B68: 1K26TFA-00029784 | C68: 734101625 | D68: 46199 | E68: 486261304420 | F68: 46174 | G68: KINGSTON TECHNOLOGY FAR EAST CORP. | H68: UNIGEN VIETNAM HANOI | I68: TW | J68: VN | K68: IE | L68: 64.3 | M68: 3684125 | N68: 0 | O68: 1814432 | P68: 289224 | Q68: 5787781 | R68: =Q68/'Logistics record '!$AD$1 -> 218.72047 | S68: Raw materials | U68: {=IFERROR( _xlfn.IFS( VLOOKUP(E68,[1]Material!F$5:U$90000,16,0)="LUC","Lucid", VLOOKUP(E68,[1]Material!F$5:U$90000,16,0)="FMC","FORD", OR(VLOOKUP(E68,[1]Material!F$5:U$90000,16,0)="PUR",VLOOKUP(E68,[1]Material!F$5:U$90000,16,0)="HLO"),"PURE", VLOOKUP(E68,[1]Material!F$5:U$90000,16,0)="AIC","AIC", OR(VLOOKUP(E68,[1]Material!F$5:U$90000,16,0)="AGI",VLOOKUP(E68,[1]Material!F$5:U$90000,16,0)="AGIGA"),"AGIGA", OR(LEFT(VLOOKUP(E68,[1]Material!F$5:U$90000,16,0),3)="EF-",VLOOKUP(E68,[1]Material!F$5:U$90000,16,0)="EFI"),"EFI", AND(ISNUMBER(VLOOKUP(E68,[1]Material!F$5:U$90000,16,0)),VLOOKUP(E68,[1]Material!F$5:U$90000,16,0)>=100,VLOOKUP(E68,[1]Material!F$5:U$90000,16,0)<=999,VLOOKUP(E68,[1]Material!F$5:U$90000,16,0)=INT(VLOOKUP(E68,[1]Material!F$5:U$90000,16,0))),"OEM", TRUE,"" ), "không tìm thấy trong file Import" )} -> PURE | V68: =IFERROR(_xlfn.XLOOKUP(E:E,VVMV!B:B,VVMV!J:J),0) -> 15.116015 | W68: =V68+R68 -> 233.83648
B69: 1K26TFA-00029784 | C69: 734101625 | D69: 46199 | E69: 527529851635 | F69: 46175 | G69: MICROCHIP TECHNOLOGY (THAILAND). | H69: UNIGEN VIETNAM HANOI CO., LTD | I69: TH | J69: VN | K69: IE | L69: 8.8 | M69: 853622 | N69: 0 | O69: 420409 | P69: 67014 | Q69: 1341045 | R69: =Q69/'Logistics record '!$AD$1 -> 50.678142 | S69: Raw materials | U69: {=IFERROR( _xlfn.IFS( VLOOKUP(E69,[1]Material!F$5:U$90000,16,0)="LUC","Lucid", VLOOKUP(E69,[1]Material!F$5:U$90000,16,0)="FMC","FORD", OR(VLOOKUP(E69,[1]Material!F$5:U$90000,16,0)="PUR",VLOOKUP(E69,[1]Material!F$5:U$90000,16,0)="HLO"),"PURE", VLOOKUP(E69,[1]Material!F$5:U$90000,16,0)="AIC","AIC", OR(VLOOKUP(E69,[1]Material!F$5:U$90000,16,0)="AGI",VLOOKUP(E69,[1]Material!F$5:U$90000,16,0)="AGIGA"),"AGIGA", OR(LEFT(VLOOKUP(E69,[1]Material!F$5:U$90000,16,0),3)="EF-",VLOOKUP(E69,[1]Material!F$5:U$90000,16,0)="EFI"),"EFI", AND(ISNUMBER(VLOOKUP(E69,[1]Material!F$5:U$90000,16,0)),VLOOKUP(E69,[1]Material!F$5:U$90000,16,0)>=100,VLOOKUP(E69,[1]Material!F$5:U$90000,16,0)<=999,VLOOKUP(E69,[1]Material!F$5:U$90000,16,0)=INT(VLOOKUP(E69,[1]Material!F$5:U$90000,16,0))),"OEM", TRUE,"" ), "không tìm thấy trong file Import" )} -> PURE | V69: =IFERROR(_xlfn.XLOOKUP(E:E,VVMV!B:B,VVMV!J:J),0) -> 15.116015 | W69: =V69+R69 -> 65.794158
... B76: 1K26TFA-00029784 | C76: 734101625 | D76: 46199 | E76: 872525360230 | F76: 46176 | G76: WT MICROELECTRONICS (S) PTE LTD | H76: UNIGEN VIETNAM HANOI CO.,LTD | I76: SG | J76: VN | K76: IE | L76: 7.2 | M76: 666349 | N76: 0 | O76: 328177 | P76: 52312 | Q76: 1046838 | R76: =Q76/'Logistics record '!$AD$1 -> 39.560048 | S76: Raw materials | U76: {=IFERROR( _xlfn.IFS( VLOOKUP(E76,[1]Material!F$5:U$90000,16,0)="LUC","Lucid", VLOOKUP(E76,[1]Material!F$5:U$90000,16,0)="FMC","FORD", OR(VLOOKUP(E76,[1]Material!F$5:U$90000,16,0)="PUR",VLOOKUP(E76,[1]Material!F$5:U$90000,16,0)="HLO"),"PURE", VLOOKUP(E76,[1]Material!F$5:U$90000,16,0)="AIC","AIC", OR(VLOOKUP(E76,[1]Material!F$5:U$90000,16,0)="AGI",VLOOKUP(E76,[1]Material!F$5:U$90000,16,0)="AGIGA"),"AGIGA", OR(LEFT(VLOOKUP(E76,[1]Material!F$5:U$90000,16,0),3)="EF-",VLOOKUP(E76,[1]Material!F$5:U$90000,16,0)="EFI"),"EFI", AND(ISNUMBER(VLOOKUP(E76,[1]Material!F$5:U$90000,16,0)),VLOOKUP(E76,[1]Material!F$5:U$90000,16,0)>=100,VLOOKUP(E76,[1]Material!F$5:U$90000,16,0)<=999,VLOOKUP(E76,[1]Material!F$5:U$90000,16,0)=INT(VLOOKUP(E76,[1]Material!F$5:U$90000,16,0))),"OEM", TRUE,"" ), "không tìm thấy trong file Import" )} -> EFI | V76: =IFERROR(_xlfn.XLOOKUP(E:E,VVMV!B:B,VVMV!J:J),0) -> 15.116015 | W76: =V76+R76 -> 54.676064
B77: 1K26TFA-00029784 | C77: 734101625 | D77: 46199 | E77: 872577301890 | F77: 46176 | G77: SHIRLEY LIU | H77: UNIGEN VIETNAM HANOI CO., LTD. | I77: CN | J77: VN | K77: IE | L77: 0.6 | M77: 295365 | N77: 0 | O77: 145467 | P77: 23188 | Q77: 464020 | R77: =Q77/'Logistics record '!$AD$1 -> 17.535334 | S77: Raw materials | U77: OEM | V77: =IFERROR(_xlfn.XLOOKUP(E:E,VVMV!B:B,VVMV!J:J),0) -> 0 | W77: =V77+R77 -> 17.535334
B78: 1K26TFA-00029784 | C78: 734101625 | D78: 46199 | E78: 872628217295 | F78: 46177 | G78: ACE TECHNOLOGY (TAIWAN) CO., LTD. | H78: UNIGEN VIET NAM HA NOI CO.LTD. | I78: TW | J78: VN | K78: IE | L78: 1.9 | M78: 413236 | N78: 0 | O78: 203519 | P78: 32441 | Q78: 649196 | R78: =Q78/'Logistics record '!$AD$1 -> 24.533142 | S78: Raw materials | U78: {=IFERROR( _xlfn.IFS( VLOOKUP(E78,[1]Material!F$5:U$90000,16,0)="LUC","Lucid", VLOOKUP(E78,[1]Material!F$5:U$90000,16,0)="FMC","FORD", OR(VLOOKUP(E78,[1]Material!F$5:U$90000,16,0)="PUR",VLOOKUP(E78,[1]Material!F$5:U$90000,16,0)="HLO"),"PURE", VLOOKUP(E78,[1]Material!F$5:U$90000,16,0)="AIC","AIC", OR(VLOOKUP(E78,[1]Material!F$5:U$90000,16,0)="AGI",VLOOKUP(E78,[1]Material!F$5:U$90000,16,0)="AGIGA"),"AGIGA", OR(LEFT(VLOOKUP(E78,[1]Material!F$5:U$90000,16,0),3)="EF-",VLOOKUP(E78,[1]Material!F$5:U$90000,16,0)="EFI"),"EFI", AND(ISNUMBER(VLOOKUP(E78,[1]Material!F$5:U$90000,16,0)),VLOOKUP(E78,[1]Material!F$5:U$90000,16,0)>=100,VLOOKUP(E78,[1]Material!F$5:U$90000,16,0)<=999,VLOOKUP(E78,[1]Material!F$5:U$90000,16,0)=INT(VLOOKUP(E78,[1]Material!F$5:U$90000,16,0))),"OEM", TRUE,"" ), "không tìm thấy trong file Import" )} -> OEM | V78: =IFERROR(_xlfn.XLOOKUP(E:E,VVMV!B:B,VVMV!J:J),0) -> 15.116015 | W78: =V78+R78 -> 39.649157
B79: 1K26TFA-00029784 | C79: 734101625 | D79: 46199 | E79: 872629406576 | F79: 46177 | G79: STEADFAST INDUSTRIAL PTE LTD | H79: UNIGEN VIETNAM HANOI CO., LTD | I79: SG | J79: VN | K79: IE | L79: 40.3 | M79: 1937794 | N79: 0 | O79: 954364 | P79: 152128 | Q79: 3044286 | R79: =Q79/'Logistics record '!$AD$1 -> 115.04369 | S79: Raw materials | U79: {=IFERROR( _xlfn.IFS( VLOOKUP(E79,[1]Material!F$5:U$90000,16,0)="LUC","Lucid", VLOOKUP(E79,[1]Material!F$5:U$90000,16,0)="FMC","FORD", OR(VLOOKUP(E79,[1]Material!F$5:U$90000,16,0)="PUR",VLOOKUP(E79,[1]Material!F$5:U$90000,16,0)="HLO"),"PURE", VLOOKUP(E79,[1]Material!F$5:U$90000,16,0)="AIC","AIC", OR(VLOOKUP(E79,[1]Material!F$5:U$90000,16,0)="AGI",VLOOKUP(E79,[1]Material!F$5:U$90000,16,0)="AGIGA"),"AGIGA", OR(LEFT(VLOOKUP(E79,[1]Material!F$5:U$90000,16,0),3)="EF-",VLOOKUP(E79,[1]Material!F$5:U$90000,16,0)="EFI"),"EFI", AND(ISNUMBER(VLOOKUP(E79,[1]Material!F$5:U$90000,16,0)),VLOOKUP(E79,[1]Material!F$5:U$90000,16,0)>=100,VLOOKUP(E79,[1]Material!F$5:U$90000,16,0)<=999,VLOOKUP(E79,[1]Material!F$5:U$90000,16,0)=INT(VLOOKUP(E79,[1]Material!F$5:U$90000,16,0))),"OEM", TRUE,"" ), "không tìm thấy trong file Import" )} -> PURE | V79: =IFERROR(_xlfn.XLOOKUP(E:E,VVMV!B:B,VVMV!J:J),0) -> 15.116015 | W79: =V79+R79 -> 130.1597
B80: 1K26TFA-00029784 | C80: 734101625 | D80: 46199 | E80: 809262197638 | F80: 46177 | G80: UNIGEN (HK) LTD | H80: UNIGEN VIETNAM HANOI | I80: HK | J80: VN | K80: 2P | L80: 52.6 | M80: 3136243 | N80: 0 | O80: 1544600 | P80: 246212 | Q80: 4927055 | R80: =Q80/'Logistics record '!$AD$1 -> 186.1936 | S80: Raw materials | U80: {=IFERROR( _xlfn.IFS( VLOOKUP(E80,[1]Material!F$5:U$90000,16,0)="LUC","Lucid", VLOOKUP(E80,[1]Material!F$5:U$90000,16,0)="FMC","FORD", OR(VLOOKUP(E80,[1]Material!F$5:U$90000,16,0)="PUR",VLOOKUP(E80,[1]Material!F$5:U$90000,16,0)="HLO"),"PURE", VLOOKUP(E80,[1]Material!F$5:U$90000,16,0)="AIC","AIC", OR(VLOOKUP(E80,[1]Material!F$5:U$90000,16,0)="AGI",VLOOKUP(E80,[1]Material!F$5:U$90000,16,0)="AGIGA"),"AGIGA", OR(LEFT(VLOOKUP(E80,[1]Material!F$5:U$90000,16,0),3)="EF-",VLOOKUP(E80,[1]Material!F$5:U$90000,16,0)="EFI"),"EFI", AND(ISNUMBER(VLOOKUP(E80,[1]Material!F$5:U$90000,16,0)),VLOOKUP(E80,[1]Material!F$5:U$90000,16,0)>=100,VLOOKUP(E80,[1]Material!F$5:U$90000,16,0)<=999,VLOOKUP(E80,[1]Material!F$5:U$90000,16,0)=INT(VLOOKUP(E80,[1]Material!F$5:U$90000,16,0))),"OEM", TRUE,"" ), "không tìm thấy trong file Import" )} -> OEM | V80: =IFERROR(_xlfn.XLOOKUP(E:E,VVMV!B:B,VVMV!J:J),0) -> 15.116015 | W80: =V80+R80 -> 201.30961
B81: 1K26TFA-00029784 | C81: 734101625 | D81: 46199 | E81: 381795282566 | F81: 46177 | G81: ANALOG DEVICES (THAILAND) CO.,LTD | H81: UNIGEN CORPORATION | I81: TH | J81: VN | K81: IE | L81: 6 | M81: 693863 | N81: 0 | O81: 341728 | P81: 54472 | Q81: 1090063 | R81: =Q81/'Logistics record '!$AD$1 -> 41.193523 | S81: Raw materials | U81: {=IFERROR( _xlfn.IFS( VLOOKUP(E81,[1]Material!F$5:U$90000,16,0)="LUC","Lucid", VLOOKUP(E81,[1]Material!F$5:U$90000,16,0)="FMC","FORD", OR(VLOOKUP(E81,[1]Material!F$5:U$90000,16,0)="PUR",VLOOKUP(E81,[1]Material!F$5:U$90000,16,0)="HLO"),"PURE", VLOOKUP(E81,[1]Material!F$5:U$90000,16,0)="AIC","AIC", OR(VLOOKUP(E81,[1]Material!F$5:U$90000,16,0)="AGI",VLOOKUP(E81,[1]Material!F$5:U$90000,16,0)="AGIGA"),"AGIGA", OR(LEFT(VLOOKUP(E81,[1]Material!F$5:U$90000,16,0),3)="EF-",VLOOKUP(E81,[1]Material!F$5:U$90000,16,0)="EFI"),"EFI", AND(ISNUMBER(VLOOKUP(E81,[1]Material!F$5:U$90000,16,0)),VLOOKUP(E81,[1]Material!F$5:U$90000,16,0)>=100,VLOOKUP(E81,[1]Material!F$5:U$90000,16,0)<=999,VLOOKUP(E81,[1]Material!F$5:U$90000,16,0)=INT(VLOOKUP(E81,[1]Material!F$5:U$90000,16,0))),"OEM", TRUE,"" ), "không tìm thấy trong file Import" )} -> PURE | V81: =IFERROR(_xlfn.XLOOKUP(E:E,VVMV!B:B,VVMV!J:J),0) -> 15.116015 | W81: =V81+R81 -> 56.309538
B82: 1K26TFA-00029784 | C82: 734101625 | D82: 46199 | E82: 872631660330 | F82: 46177 | G82: BRAIN POWER | H82: UNIGEN VIETNAM HANOI CO., LTD | I82: HK | J82: VN | K82: IE | L82: 12.4 | M82: 856260 | N82: 0 | O82: 421708 | P82: 67221 | Q82: 1345189 | R82: =Q82/'Logistics record '!$AD$1 -> 50.834744 | S82: Raw materials | U82: {=IFERROR( _xlfn.IFS( VLOOKUP(E82,[1]Material!F$5:U$90000,16,0)="LUC","Lucid", VLOOKUP(E82,[1]Material!F$5:U$90000,16,0)="FMC","FORD", OR(VLOOKUP(E82,[1]Material!F$5:U$90000,16,0)="PUR",VLOOKUP(E82,[1]Material!F$5:U$90000,16,0)="HLO"),"PURE", VLOOKUP(E82,[1]Material!F$5:U$90000,16,0)="AIC","AIC", OR(VLOOKUP(E82,[1]Material!F$5:U$90000,16,0)="AGI",VLOOKUP(E82,[1]Material!F$5:U$90000,16,0)="AGIGA"),"AGIGA", OR(LEFT(VLOOKUP(E82,[1]Material!F$5:U$90000,16,0),3)="EF-",VLOOKUP(E82,[1]Material!F$5:U$90000,16,0)="EFI"),"EFI", AND(ISNUMBER(VLOOKUP(E82,[1]Material!F$5:U$90000,16,0)),VLOOKUP(E82,[1]Material!F$5:U$90000,16,0)>=100,VLOOKUP(E82,[1]Material!F$5:U$90000,16,0)<=999,VLOOKUP(E82,[1]Material!F$5:U$90000,16,0)=INT(VLOOKUP(E82,[1]Material!F$5:U$90000,16,0))),"OEM", TRUE,"" ), "không tìm thấy trong file Import" )} -> OEM | V82: =IFERROR(_xlfn.XLOOKUP(E:E,VVMV!B:B,VVMV!J:J),0) -> 15.116015 | W82: =V82+R82 -> 65.95076
B83: 1K26TFA-00029784 | C83: 734101625 | D83: 46199 | E83: 381747821205 | F83: 46177 | G83: TEXAS INSTRUMENTS ASIA LIMITED | H83: UNIGEN VIETNAM HANOI CO., LTD. | I83: CN | J83: VN | K83: IE | L83: 16.8 | M83: 1273454 | N83: 0 | O83: 627176 | P83: 99973 | Q83: 2000603 | R83: =Q83/'Logistics record '!$AD$1 -> 75.602864 | S83: Raw materials | U83: {=IFERROR( _xlfn.IFS( VLOOKUP(E83,[1]Material!F$5:U$90000,16,0)="LUC","Lucid", VLOOKUP(E83,[1]Material!F$5:U$90000,16,0)="FMC","FORD", OR(VLOOKUP(E83,[1]Material!F$5:U$90000,16,0)="PUR",VLOOKUP(E83,[1]Material!F$5:U$90000,16,0)="HLO"),"PURE", VLOOKUP(E83,[1]Material!F$5:U$90000,16,0)="AIC","AIC", OR(VLOOKUP(E83,[1]Material!F$5:U$90000,16,0)="AGI",VLOOKUP(E83,[1]Material!F$5:U$90000,16,0)="AGIGA"),"AGIGA", OR(LEFT(VLOOKUP(E83,[1]Material!F$5:U$90000,16,0),3)="EF-",VLOOKUP(E83,[1]Material!F$5:U$90000,16,0)="EFI"),"EFI", AND(ISNUMBER(VLOOKUP(E83,[1]Material!F$5:U$90000,16,0)),VLOOKUP(E83,[1]Material!F$5:U$90000,16,0)>=100,VLOOKUP(E83,[1]Material!F$5:U$90000,16,0)<=999,VLOOKUP(E83,[1]Material!F$5:U$90000,16,0)=INT(VLOOKUP(E83,[1]Material!F$5:U$90000,16,0))),"OEM", TRUE,"" ), "không tìm thấy trong file Import" )} -> Lucid | V83: =IFERROR(_xlfn.XLOOKUP(E:E,VVMV!B:B,VVMV!J:J),0) -> 15.116015 | W83: =V83+R83 -> 90.71888
B84: 1K26TFA-00029784 | C84: 734101625 | D84: 46199 | E84: 381751868559 | F84: 46177 | G84: TEXAS INSTRUMENTS ASIA LIMITED | H84: UNIGEN VIETNAM HANOI CO., LTD. | I84: CN | J84: VN | K84: IE | L84: 3.4 | M84: 383591 | N84: 0 | O84: 188919 | P84: 30114 | Q84: 602624 | R84: =Q84/'Logistics record '!$AD$1 -> 22.773184 | S84: Raw materials | U84: {=IFERROR( _xlfn.IFS( VLOOKUP(E84,[1]Material!F$5:U$90000,16,0)="LUC","Lucid", VLOOKUP(E84,[1]Material!F$5:U$90000,16,0)="FMC","FORD", OR(VLOOKUP(E84,[1]Material!F$5:U$90000,16,0)="PUR",VLOOKUP(E84,[1]Material!F$5:U$90000,16,0)="HLO"),"PURE", VLOOKUP(E84,[1]Material!F$5:U$90000,16,0)="AIC","AIC", OR(VLOOKUP(E84,[1]Material!F$5:U$90000,16,0)="AGI",VLOOKUP(E84,[1]Material!F$5:U$90000,16,0)="AGIGA"),"AGIGA", OR(LEFT(VLOOKUP(E84,[1]Material!F$5:U$90000,16,0),3)="EF-",VLOOKUP(E84,[1]Material!F$5:U$90000,16,0)="EFI"),"EFI", AND(ISNUMBER(VLOOKUP(E84,[1]Material!F$5:U$90000,16,0)),VLOOKUP(E84,[1]Material!F$5:U$90000,16,0)>=100,VLOOKUP(E84,[1]Material!F$5:U$90000,16,0)<=999,VLOOKUP(E84,[1]Material!F$5:U$90000,16,0)=INT(VLOOKUP(E84,[1]Material!F$5:U$90000,16,0))),"OEM", TRUE,"" ), "không tìm thấy trong file Import" )} -> OEM | V84: =IFERROR(_xlfn.XLOOKUP(E:E,VVMV!B:B,VVMV!J:J),0) -> 15.116015 | W84: =V84+R84 -> 37.8892
B85: 1K26TFA-00029784 | C85: 734101625 | D85: 46199 | E85: 477592566243 | F85: 46178 | G85: QUALCOMM CDMA TECHNOLOGIES ASIA-PAC | H85: UNIGEN VIETNAM HANOI CO. LTD | I85: SG | J85: VN | K85: IE | L85: 230.6 | M85: 10420502 | N85: 0 | O85: 5132097 | P85: 818067 | Q85: 16370666 | R85: =Q85/'Logistics record '!$AD$1 -> 618.6481 | S85: Raw materials | U85: {=IFERROR( _xlfn.IFS( VLOOKUP(E85,[1]Material!F$5:U$90000,16,0)="LUC","Lucid", VLOOKUP(E85,[1]Material!F$5:U$90000,16,0)="FMC","FORD", OR(VLOOKUP(E85,[1]Material!F$5:U$90000,16,0)="PUR",VLOOKUP(E85,[1]Material!F$5:U$90000,16,0)="HLO"),"PURE", VLOOKUP(E85,[1]Material!F$5:U$90000,16,0)="AIC","AIC", OR(VLOOKUP(E85,[1]Material!F$5:U$90000,16,0)="AGI",VLOOKUP(E85,[1]Material!F$5:U$90000,16,0)="AGIGA"),"AGIGA", OR(LEFT(VLOOKUP(E85,[1]Material!F$5:U$90000,16,0),3)="EF-",VLOOKUP(E85,[1]Material!F$5:U$90000,16,0)="EFI"),"EFI", AND(ISNUMBER(VLOOKUP(E85,[1]Material!F$5:U$90000,16,0)),VLOOKUP(E85,[1]Material!F$5:U$90000,16,0)>=100,VLOOKUP(E85,[1]Material!F$5:U$90000,16,0)<=999,VLOOKUP(E85,[1]Material!F$5:U$90000,16,0)=INT(VLOOKUP(E85,[1]Material!F$5:U$90000,16,0))),"OEM", TRUE,"" ), "không tìm thấy trong file Import" )} -> Lucid | V85: =IFERROR(_xlfn.XLOOKUP(E:E,VVMV!B:B,VVMV!J:J),0) -> 15.116015 | W85: =V85+R85 -> 633.76411
B86: 1K26TFA-00029784 | C86: 734101625 | D86: 46199 | E86: 472187366030 | F86: 46178 | G86: HEILIND ASIA PACIFIC (SG) PTE LTD | H86: UNIGEN VIETNAM HANOI CO., LTD. | I86: SG | J86: VN | K86: IE | L86: 10.9 | M86: 777492 | N86: 0 | O86: 382915 | P86: 61037 | Q86: 1221444 | R86: =Q86/'Logistics record '!$AD$1 -> 46.158416 | S86: Raw materials | U86: {=IFERROR( _xlfn.IFS( VLOOKUP(E86,[1]Material!F$5:U$90000,16,0)="LUC","Lucid", VLOOKUP(E86,[1]Material!F$5:U$90000,16,0)="FMC","FORD", OR(VLOOKUP(E86,[1]Material!F$5:U$90000,16,0)="PUR",VLOOKUP(E86,[1]Material!F$5:U$90000,16,0)="HLO"),"PURE", VLOOKUP(E86,[1]Material!F$5:U$90000,16,0)="AIC","AIC", OR(VLOOKUP(E86,[1]Material!F$5:U$90000,16,0)="AGI",VLOOKUP(E86,[1]Material!F$5:U$90000,16,0)="AGIGA"),"AGIGA", OR(LEFT(VLOOKUP(E86,[1]Material!F$5:U$90000,16,0),3)="EF-",VLOOKUP(E86,[1]Material!F$5:U$90000,16,0)="EFI"),"EFI", AND(ISNUMBER(VLOOKUP(E86,[1]Material!F$5:U$90000,16,0)),VLOOKUP(E86,[1]Material!F$5:U$90000,16,0)>=100,VLOOKUP(E86,[1]Material!F$5:U$90000,16,0)<=999,VLOOKUP(E86,[1]Material!F$5:U$90000,16,0)=INT(VLOOKUP(E86,[1]Material!F$5:U$90000,16,0))),"OEM", TRUE,"" ), "không tìm thấy trong file Import" )} -> PURE | V86: =IFERROR(_xlfn.XLOOKUP(E:E,VVMV!B:B,VVMV!J:J),0) -> 15.116015 | W86: =V86+R86 -> 61.274431
B87: 1K26TFA-00029784 | C87: 734101625 | D87: 46199 | E87: 527529858787 | F87: 46178 | G87: MICROCHIP TECHNOLOGY (THAILAND). | H87: UNIGEN VIETNAM HANOI CO., LTD | I87: TH | J87: VN | K87: IE | L87: 17.6 | M87: 1120404 | N87: 0 | O87: 551799 | P87: 87958 | Q87: 1760161 | R87: =Q87/'Logistics record '!$AD$1 -> 66.516552 | S87: Raw materials | U87: {=IFERROR( _xlfn.IFS( VLOOKUP(E87,[1]Material!F$5:U$90000,16,0)="LUC","Lucid", VLOOKUP(E87,[1]Material!F$5:U$90000,16,0)="FMC","FORD", OR(VLOOKUP(E87,[1]Material!F$5:U$90000,16,0)="PUR",VLOOKUP(E87,[1]Material!F$5:U$90000,16,0)="HLO"),"PURE", VLOOKUP(E87,[1]Material!F$5:U$90000,16,0)="AIC","AIC", OR(VLOOKUP(E87,[1]Material!F$5:U$90000,16,0)="AGI",VLOOKUP(E87,[1]Material!F$5:U$90000,16,0)="AGIGA"),"AGIGA", OR(LEFT(VLOOKUP(E87,[1]Material!F$5:U$90000,16,0),3)="EF-",VLOOKUP(E87,[1]Material!F$5:U$90000,16,0)="EFI"),"EFI", AND(ISNUMBER(VLOOKUP(E87,[1]Material!F$5:U$90000,16,0)),VLOOKUP(E87,[1]Material!F$5:U$90000,16,0)>=100,VLOOKUP(E87,[1]Material!F$5:U$90000,16,0)<=999,VLOOKUP(E87,[1]Material!F$5:U$90000,16,0)=INT(VLOOKUP(E87,[1]Material!F$5:U$90000,16,0))),"OEM", TRUE,"" ), "không tìm thấy trong file Import" )} -> PURE | V87: =IFERROR(_xlfn.XLOOKUP(E:E,VVMV!B:B,VVMV!J:J),0) -> 15.116015 | W87: =V87+R87 -> 81.632567
B88: 1K26TFA-00029784 | C88: 734101625 | D88: 46199 | E88: 515199060191 | F88: 46178 | G88: AVNET ASIA PTE LTD | H88: UNIGEN VIETNAM HANOI CO LTD | I88: SG | J88: VN | K88: IE | L88: 72.2 | M88: 3316718 | N88: 679700 | O88: 1968236 | P88: 313741 | Q88: 6278395 | R88: =Q88/'Logistics record '!$AD$1 -> 237.26079 | S88: Raw materials | U88: {=IFERROR( _xlfn.IFS( VLOOKUP(E88,[1]Material!F$5:U$90000,16,0)="LUC","Lucid", VLOOKUP(E88,[1]Material!F$5:U$90000,16,0)="FMC","FORD", OR(VLOOKUP(E88,[1]Material!F$5:U$90000,16,0)="PUR",VLOOKUP(E88,[1]Material!F$5:U$90000,16,0)="HLO"),"PURE", VLOOKUP(E88,[1]Material!F$5:U$90000,16,0)="AIC","AIC", OR(VLOOKUP(E88,[1]Material!F$5:U$90000,16,0)="AGI",VLOOKUP(E88,[1]Material!F$5:U$90000,16,0)="AGIGA"),"AGIGA", OR(LEFT(VLOOKUP(E88,[1]Material!F$5:U$90000,16,0),3)="EF-",VLOOKUP(E88,[1]Material!F$5:U$90000,16,0)="EFI"),"EFI", AND(ISNUMBER(VLOOKUP(E88,[1]Material!F$5:U$90000,16,0)),VLOOKUP(E88,[1]Material!F$5:U$90000,16,0)>=100,VLOOKUP(E88,[1]Material!F$5:U$90000,16,0)<=999,VLOOKUP(E88,[1]Material!F$5:U$90000,16,0)=INT(VLOOKUP(E88,[1]Material!F$5:U$90000,16,0))),"OEM", TRUE,"" ), "không tìm thấy trong file Import" )} -> PURE | V88: =IFERROR(_xlfn.XLOOKUP(E:E,VVMV!B:B,VVMV!J:J),0) -> 15.116015 | W88: =V88+R88 -> 252.3768
B89: 1K26TFA-00029784 | C89: 734101625 | D89: 46199 | E89: 872628363850 | F89: 46178 | G89: ISU PETASYS HUNAN | H89: UNIGEN VIETNAM HA NOI CO., LTD | I89: CN | J89: VN | K89: IE | L89: 31.1 | M89: 2161152 | N89: 0 | O89: 1064367 | P89: 169662 | Q89: 3395181 | R89: =Q89/'Logistics record '!$AD$1 -> 128.30402 | S89: Raw materials | U89: {=IFERROR( _xlfn.IFS( VLOOKUP(E89,[1]Material!F$5:U$90000,16,0)="LUC","Lucid", VLOOKUP(E89,[1]Material!F$5:U$90000,16,0)="FMC","FORD", OR(VLOOKUP(E89,[1]Material!F$5:U$90000,16,0)="PUR",VLOOKUP(E89,[1]Material!F$5:U$90000,16,0)="HLO"),"PURE", VLOOKUP(E89,[1]Material!F$5:U$90000,16,0)="AIC","AIC", OR(VLOOKUP(E89,[1]Material!F$5:U$90000,16,0)="AGI",VLOOKUP(E89,[1]Material!F$5:U$90000,16,0)="AGIGA"),"AGIGA", OR(LEFT(VLOOKUP(E89,[1]Material!F$5:U$90000,16,0),3)="EF-",VLOOKUP(E89,[1]Material!F$5:U$90000,16,0)="EFI"),"EFI", AND(ISNUMBER(VLOOKUP(E89,[1]Material!F$5:U$90000,16,0)),VLOOKUP(E89,[1]Material!F$5:U$90000,16,0)>=100,VLOOKUP(E89,[1]Material!F$5:U$90000,16,0)<=999,VLOOKUP(E89,[1]Material!F$5:U$90000,16,0)=INT(VLOOKUP(E89,[1]Material!F$5:U$90000,16,0))),"OEM", TRUE,"" ), "không tìm thấy trong file Import" )} -> PURE | V89: =IFERROR(_xlfn.XLOOKUP(E:E,VVMV!B:B,VVMV!J:J),0) -> 15.116015 | W89: =V89+R89 -> 143.42004
... B139: 1K26TFA-00029784 | C139: 734101625 | D139: 46199 | E139: 382085402744 | F139: 46191 | G139: TEXAS INSTRUMENTS SOUTHEAST ASIA PT | H139: UNIGEN VIETNAM HANOI CO., LTD. | I139: SG | J139: VN | K139: 2P | L139: 3.4 | M139: 451485 | N139: 0 | O139: 194139 | P139: 33960 | Q139: 679584 | R139: =Q139/'Logistics record '!$AD$1 -> 25.681506 | S139: Raw materials | U139: {=IFERROR( _xlfn.IFS( VLOOKUP(E139,[1]Material!F$5:U$90000,16,0)="LUC","Lucid", VLOOKUP(E139,[1]Material!F$5:U$90000,16,0)="FMC","FORD", OR(VLOOKUP(E139,[1]Material!F$5:U$90000,16,0)="PUR",VLOOKUP(E139,[1]Material!F$5:U$90000,16,0)="HLO"),"PURE", VLOOKUP(E139,[1]Material!F$5:U$90000,16,0)="AIC","AIC", OR(VLOOKUP(E139,[1]Material!F$5:U$90000,16,0)="AGI",VLOOKUP(E139,[1]Material!F$5:U$90000,16,0)="AGIGA"),"AGIGA", OR(LEFT(VLOOKUP(E139,[1]Material!F$5:U$90000,16,0),3)="EF-",VLOOKUP(E139,[1]Material!F$5:U$90000,16,0)="EFI"),"EFI", AND(ISNUMBER(VLOOKUP(E139,[1]Material!F$5:U$90000,16,0)),VLOOKUP(E139,[1]Material!F$5:U$90000,16,0)>=100,VLOOKUP(E139,[1]Material!F$5:U$90000,16,0)<=999,VLOOKUP(E139,[1]Material!F$5:U$90000,16,0)=INT(VLOOKUP(E139,[1]Material!F$5:U$90000,16,0))),"OEM", TRUE,"" ), "không tìm thấy trong file Import" )} -> PURE | V139: =IFERROR(_xlfn.XLOOKUP(E:E,VVMV!B:B,VVMV!J:J),0) -> 15.116015 | W139: =V139+R139 -> 40.797521
P145: Total in VND (Including VAT) | Q145: =SUM(Q2:Q141) -> 257825954
Q146: =+Q145/'Logistics record '!AD1 -> 9743.2527
A149: Tên tài khoản ngân hàng : Công ty TNHH FedEx Express Việt Nam
A150: Tên ngân hàng : Citibank N.A. (Việt Nam)
A151: Số tài khoản : 200888xxxxxxxxx
A152: (Trong đó xxxxxxxxx là số tài khoản FedEx gồm 9 chữ số của bạn)
A153: Tên chi nhánh : Citibank, N.A. – Chi nhánh Hà Nội
A154: Mã ngân hàng : 01605001
A155: Địa chỉ chi nhánh : Tầng 12A và Tầng 12B, Tòa nhà Horison Tower, Số 40 Cát Linh, Phường Ô Chợ Dừa, Thành phố Hà Nội, Việt Nam
A156: Mã Swift : CITIVNVX

Sheet VVMV
A1: No | B1: HBL No. | C1: Invoice No | D1: Shipper | E1: Type | F1: Type | G1: Route | H1: Who pays | I1: Remark | J1: USD Customs | K1: USD Trucking | L1: USD FREIGHT | M1: Local charge | N1: Mode | O1: TOTAL USD | P1: Destination/ Shipper's country | Q1: Custom No | R1: CD Date | S1: Quantity | V1: Service charge - Amount VND | Z1: Sub-Total (vnd) | AC1: Pay on be half of Unigen - Amount VND | AF1: Sub-Total (vnd) | AG1: TOTAL AMOUNT
R2: CD Date | V2: Customs fee | W2: Trucking fee | X2: Inpection fee/ Handling | Y2: EXW, OF, LOCAL CHARGE | Z2: Total | AA2: VAT | AB2: Total (Included vAT) | AC2: Infrastructure fee, lphq | AD2: Local charge | AE2: Storage charge, labor, | AI2: LoẠI HÌNH
S3: Mode | T3: Kgs | U3: CBM
A4: 1 | B4: PSHPH2650073 | C4: 175-2650008 | D4: MIN AIK TECHNOLOGY CO., LTD | E4: =IF(OR(AI4="E11", AI4="E13", AI4="E15", AI4="G13"), "Import", "Export") -> Import | F4: {=_xlfn.IFS( OR(AI4="E11", AI4="E15"), "Raw materials", OR(AI4="E13", AI4="G13"), "Equipments + Toolings", TRUE, RIGHT(C4, 8) )} -> Raw materials | G4: {=IF(E4="Import", IFERROR( _xlfn.IFS( VLOOKUP(B4,[1]Material!F$5:U$90000,16,0)="LUC","Lucid", VLOOKUP(B4,[1]Material!F$5:U$90000,16,0)="FMC","FORD", OR(VLOOKUP(B4,[1]Material!F$5:U$90000,16,0)="PUR",VLOOKUP(B4,[1]Material!F$5:U$90000,16,0)="HLO"),"PURE", VLOOKUP(B4,[1]Material!F$5:U$90000,16,0)="AIC","AIC", OR(VLOOKUP(B4,[1]Material!F$5:U$90000,16,0)="AGI",VLOOKUP(B4,[1]Material!F$5:U$90000,16,0)="AGIGA"),"AGIGA", OR(LEFT(VLOOKUP(B4,[1]Material!F$5:U$90000,16,0),3)="EF-",VLOOKUP(B4,[1]Material!F$5:U$90000,16,0)="EFI"),"EFI", AND(ISNUMBER(VLOOKUP(B4,[1]Material!F$5:U$90000,16,0)),VLOOKUP(B4,[1]Material!F$5:U$90000,16,0)>=100,VLOOKUP(B4,[1]Material!F$5:U$90000,16,0)<=999,VLOOKUP(B4,[1]Material!F$5:U$90000,16,0)=INT(VLOOKUP(B4,[1]Material!F$5:U$90000,16,0))),"OEM", TRUE,"" ), "không tìm thấy trong file Import" ), VLOOKUP(F4,'[2]Export shipment'!B:Y,24,0) )} -> PURE | J4: =(V4+X4+AA4)/'Logistics record '!$AD$1 -> 15.116015 | K4: =W4/'Logistics record '!$AD$1 -> 143.60215 | L4: =Y4/'Logistics record '!$AD$1 -> 1418.7974 | M4: =AF4/'Logistics record '!$AD$1 -> 179.11964 | N4: {=_xlfn.IFS( OR(UPPER(S4)="AIR", UPPER(S4)="CPN"), "AIR", UPPER(S4)="TC", "LOCAL", TRUE, "SEA" )} -> SEA | O4: =M4+L4+K4+J4 -> 1756.6352 | P4: TW | Q4: 108262405640 | R4: 46163 | S4: LCL | T4: 1941.5 | U4: 11.73 | V4: 400000 | W4: 3800000 | Y4: 37544216 | Z4: =SUM(V4:Y4) -> 41744216 | AA4: 0 | AB4: =+AA4+Z4 -> 41744216 | AC4: 31064 | AE4: 4708800 | AF4: =+SUM(AC4:AE4) -> 4739864 | AG4: =+AF4+AB4 -> 46484080 | AI4: =VLOOKUP(Q4,[3]Sheet1!B$11:G$1489,6,0) -> E11
A5: 2 | B5: HVSZ26055635 | C5: KRM26CI015 | D5: SHENZHEN KERAIMEI PRECISION HARDWARE CO.,LTD. | E5: =IF(OR(AI5="E11", AI5="E13", AI5="E15", AI5="G13"), "Import", "Export") -> Import | F5: {=_xlfn.IFS( OR(AI5="E11", AI5="E15"), "Raw materials", OR(AI5="E13", AI5="G13"), "Equipments + Toolings", TRUE, RIGHT(C5, 8) )} -> Raw materials | G5: {=IF(E5="Import", IFERROR( _xlfn.IFS( VLOOKUP(B5,[1]Material!F$5:U$90000,16,0)="LUC","Lucid", VLOOKUP(B5,[1]Material!F$5:U$90000,16,0)="FMC","FORD", OR(VLOOKUP(B5,[1]Material!F$5:U$90000,16,0)="PUR",VLOOKUP(B5,[1]Material!F$5:U$90000,16,0)="HLO"),"PURE", VLOOKUP(B5,[1]Material!F$5:U$90000,16,0)="AIC","AIC", OR(VLOOKUP(B5,[1]Material!F$5:U$90000,16,0)="AGI",VLOOKUP(B5,[1]Material!F$5:U$90000,16,0)="AGIGA"),"AGIGA", OR(LEFT(VLOOKUP(B5,[1]Material!F$5:U$90000,16,0),3)="EF-",VLOOKUP(B5,[1]Material!F$5:U$90000,16,0)="EFI"),"EFI", AND(ISNUMBER(VLOOKUP(B5,[1]Material!F$5:U$90000,16,0)),VLOOKUP(B5,[1]Material!F$5:U$90000,16,0)>=100,VLOOKUP(B5,[1]Material!F$5:U$90000,16,0)<=999,VLOOKUP(B5,[1]Material!F$5:U$90000,16,0)=INT(VLOOKUP(B5,[1]Material!F$5:U$90000,16,0))),"OEM", TRUE,"" ), "không tìm thấy trong file Import" ), VLOOKUP(F5,'[2]Export shipment'!B:Y,24,0) )} -> OEM | J5: =(V5+X5+AA5)/'Logistics record '!$AD$1 -> 15.116015 | K5: =W5/'Logistics record '!$AD$1 -> 22.674023 | L5: =Y5/'Logistics record '!$AD$1 -> 214.11326 | M5: =AF5/'Logistics record '!$AD$1 -> 18.304739 | N5: {=_xlfn.IFS( OR(UPPER(S5)="AIR", UPPER(S5)="CPN"), "AIR", UPPER(S5)="TC", "LOCAL", TRUE, "SEA" )} -> AIR | O5: =M5+L5+K5+J5 -> 270.20803 | P5: CN | Q5: 108269406010 | R5: 46164 | S5: AIR | T5: 37 | V5: 400000 | W5: 600000 | Y5: 5665865 | Z5: =SUM(V5:Y5) -> 6665865 | AA5: 0 | AB5: =+AA5+Z5 -> 6665865 | AE5: 484380 | AF5: =+SUM(AC5:AE5) -> 484380 | AG5: =+AF5+AB5 -> 7150245 | AI5: =VLOOKUP(Q5,[3]Sheet1!B$11:G$1489,6,0) -> E11
A6: 3 | B6: 871789217180 | C6: 7729911-13 | D6: Element 14 Pte Ltd | E6: =IF(OR(AI6="E11", AI6="E13", AI6="E15", AI6="G13"), "Import", "Export") -> Import | F6: {=_xlfn.IFS( OR(AI6="E11", AI6="E15"), "Raw materials", OR(AI6="E13", AI6="G13"), "Equipments + Toolings", TRUE, RIGHT(C6, 8) )} -> Raw materials | G6: {=IF(E6="Import", IFERROR( _xlfn.IFS( VLOOKUP(B6,[1]Material!F$5:U$90000,16,0)="LUC","Lucid", VLOOKUP(B6,[1]Material!F$5:U$90000,16,0)="FMC","FORD", OR(VLOOKUP(B6,[1]Material!F$5:U$90000,16,0)="PUR",VLOOKUP(B6,[1]Material!F$5:U$90000,16,0)="HLO"),"PURE", VLOOKUP(B6,[1]Material!F$5:U$90000,16,0)="AIC","AIC", OR(VLOOKUP(B6,[1]Material!F$5:U$90000,16,0)="AGI",VLOOKUP(B6,[1]Material!F$5:U$90000,16,0)="AGIGA"),"AGIGA", OR(LEFT(VLOOKUP(B6,[1]Material!F$5:U$90000,16,0),3)="EF-",VLOOKUP(B6,[1]Material!F$5:U$90000,16,0)="EFI"),"EFI", AND(ISNUMBER(VLOOKUP(B6,[1]Material!F$5:U$90000,16,0)),VLOOKUP(B6,[1]Material!F$5:U$90000,16,0)>=100,VLOOKUP(B6,[1]Material!F$5:U$90000,16,0)<=999,VLOOKUP(B6,[1]Material!F$5:U$90000,16,0)=INT(VLOOKUP(B6,[1]Material!F$5:U$90000,16,0))),"OEM", TRUE,"" ), "không tìm thấy trong file Import" ), VLOOKUP(F6,'[2]Export shipment'!B:Y,24,0) )} -> EFI | J6: =(V6+X6+AA6)/'Logistics record '!$AD$1 -> 15.116015 | K6: =W6/'Logistics record '!$AD$1 -> 0 | L6: =Y6/'Logistics record '!$AD$1 -> 0 | M6: =AF6/'Logistics record '!$AD$1 -> 0 | N6: {=_xlfn.IFS( OR(UPPER(S6)="AIR", UPPER(S6)="CPN"), "AIR", UPPER(S6)="TC", "LOCAL", TRUE, "SEA" )} -> AIR | O6: =M6+L6+K6+J6 -> 15.116015 | P6: SG | Q6: 108269465950 | R6: 46167 | S6: CPN | T6: 1.5 | V6: 400000 | Z6: =SUM(V6:Y6) -> 400000 | AA6: 0 | AB6: =+AA6+Z6 -> 400000 | AF6: =+SUM(AC6:AE6) -> 0 | AG6: =+AF6+AB6 -> 400000 | AI6: =VLOOKUP(Q6,[3]Sheet1!B$11:G$1489,6,0) -> E11
A7: 4 | B7: 492830077795 | C7: 030162972 | D7: ARROW ELECTRONICS, INC. | E7: =IF(OR(AI7="E11", AI7="E13", AI7="E15", AI7="G13"), "Import", "Export") -> Import | F7: {=_xlfn.IFS( OR(AI7="E11", AI7="E15"), "Raw materials", OR(AI7="E13", AI7="G13"), "Equipments + Toolings", TRUE, RIGHT(C7, 8) )} -> Raw materials | G7: {=IF(E7="Import", IFERROR( _xlfn.IFS( VLOOKUP(B7,[1]Material!F$5:U$90000,16,0)="LUC","Lucid", VLOOKUP(B7,[1]Material!F$5:U$90000,16,0)="FMC","FORD", OR(VLOOKUP(B7,[1]Material!F$5:U$90000,16,0)="PUR",VLOOKUP(B7,[1]Material!F$5:U$90000,16,0)="HLO"),"PURE", VLOOKUP(B7,[1]Material!F$5:U$90000,16,0)="AIC","AIC", OR(VLOOKUP(B7,[1]Material!F$5:U$90000,16,0)="AGI",VLOOKUP(B7,[1]Material!F$5:U$90000,16,0)="AGIGA"),"AGIGA", OR(LEFT(VLOOKUP(B7,[1]Material!F$5:U$90000,16,0),3)="EF-",VLOOKUP(B7,[1]Material!F$5:U$90000,16,0)="EFI"),"EFI", AND(ISNUMBER(VLOOKUP(B7,[1]Material!F$5:U$90000,16,0)),VLOOKUP(B7,[1]Material!F$5:U$90000,16,0)>=100,VLOOKUP(B7,[1]Material!F$5:U$90000,16,0)<=999,VLOOKUP(B7,[1]Material!F$5:U$90000,16,0)=INT(VLOOKUP(B7,[1]Material!F$5:U$90000,16,0))),"OEM", TRUE,"" ), "không tìm thấy trong file Import" ), VLOOKUP(F7,'[2]Export shipment'!B:Y,24,0) )} -> EFI | J7: =(V7+X7+AA7)/'Logistics record '!$AD$1 -> 15.116015 | K7: =W7/'Logistics record '!$AD$1 -> 0 | L7: =Y7/'Logistics record '!$AD$1 -> 0 | M7: =AF7/'Logistics record '!$AD$1 -> 0 | N7: {=_xlfn.IFS( OR(UPPER(S7)="AIR", UPPER(S7)="CPN"), "AIR", UPPER(S7)="TC", "LOCAL", TRUE, "SEA" )} -> AIR | O7: =M7+L7+K7+J7 -> 15.116015 | P7: US | Q7: 108271894950 | R7: 46167 | S7: CPN | T7: 4.1 | V7: 400000 | Z7: =SUM(V7:Y7) -> 400000 | AA7: 0 | AB7: =+AA7+Z7 -> 400000 | AF7: =+SUM(AC7:AE7) -> 0 | AG7: =+AF7+AB7 -> 400000 | AI7: =VLOOKUP(Q7,[3]Sheet1!B$11:G$1489,6,0) -> E11
A8: 5 | B8: 3254330553 | C8: 7595332-05 | D8: TTI INC | E8: =IF(OR(AI8="E11", AI8="E13", AI8="E15", AI8="G13"), "Import", "Export") -> Import | F8: {=_xlfn.IFS( OR(AI8="E11", AI8="E15"), "Raw materials", OR(AI8="E13", AI8="G13"), "Equipments + Toolings", TRUE, RIGHT(C8, 8) )} -> Raw materials | G8: {=IF(E8="Import", IFERROR( _xlfn.IFS( VLOOKUP(B8,[1]Material!F$5:U$90000,16,0)="LUC","Lucid", VLOOKUP(B8,[1]Material!F$5:U$90000,16,0)="FMC","FORD", OR(VLOOKUP(B8,[1]Material!F$5:U$90000,16,0)="PUR",VLOOKUP(B8,[1]Material!F$5:U$90000,16,0)="HLO"),"PURE", VLOOKUP(B8,[1]Material!F$5:U$90000,16,0)="AIC","AIC", OR(VLOOKUP(B8,[1]Material!F$5:U$90000,16,0)="AGI",VLOOKUP(B8,[1]Material!F$5:U$90000,16,0)="AGIGA"),"AGIGA", OR(LEFT(VLOOKUP(B8,[1]Material!F$5:U$90000,16,0),3)="EF-",VLOOKUP(B8,[1]Material!F$5:U$90000,16,0)="EFI"),"EFI", AND(ISNUMBER(VLOOKUP(B8,[1]Material!F$5:U$90000,16,0)),VLOOKUP(B8,[1]Material!F$5:U$90000,16,0)>=100,VLOOKUP(B8,[1]Material!F$5:U$90000,16,0)<=999,VLOOKUP(B8,[1]Material!F$5:U$90000,16,0)=INT(VLOOKUP(B8,[1]Material!F$5:U$90000,16,0))),"OEM", TRUE,"" ), "không tìm thấy trong file Import" ), VLOOKUP(F8,'[2]Export shipment'!B:Y,24,0) )} -> FORD | J8: =(V8+X8+AA8)/'Logistics record '!$AD$1 -> 15.116015 | K8: =W8/'Logistics record '!$AD$1 -> 0 | L8: =Y8/'Logistics record '!$AD$1 -> 0 | M8: =AF8/'Logistics record '!$AD$1 -> 0 | N8: {=_xlfn.IFS( OR(UPPER(S8)="AIR", UPPER(S8)="CPN"), "AIR", UPPER(S8)="TC", "LOCAL", TRUE, "SEA" )} -> AIR | O8: =M8+L8+K8+J8 -> 15.116015 | P8: US | Q8: 108272217760 | R8: 46167 | S8: CPN | T8: 3.1 | V8: 400000 | Z8: =SUM(V8:Y8) -> 400000 | AA8: 0 | AB8: =+AA8+Z8 -> 400000 | AF8: =+SUM(AC8:AE8) -> 0 | AG8: =+AF8+AB8 -> 400000 | AI8: =VLOOKUP(Q8,[3]Sheet1!B$11:G$1489,6,0) -> E11
A9: 6 | B9: 8XN5256 | C9: 1591CPM | D9: KIOXIA CORPORATION C/O KIOXIA AMERICA INC | E9: =IF(OR(AI9="E11", AI9="E13", AI9="E15", AI9="G13"), "Import", "Export") -> Import | F9: {=_xlfn.IFS( OR(AI9="E11", AI9="E15"), "Raw materials", OR(AI9="E13", AI9="G13"), "Equipments + Toolings", TRUE, RIGHT(C9, 8) )} -> Raw materials | G9: {=IF(E9="Import", IFERROR( _xlfn.IFS( VLOOKUP(B9,[1]Material!F$5:U$90000,16,0)="LUC","Lucid", VLOOKUP(B9,[1]Material!F$5:U$90000,16,0)="FMC","FORD", OR(VLOOKUP(B9,[1]Material!F$5:U$90000,16,0)="PUR",VLOOKUP(B9,[1]Material!F$5:U$90000,16,0)="HLO"),"PURE", VLOOKUP(B9,[1]Material!F$5:U$90000,16,0)="AIC","AIC", OR(VLOOKUP(B9,[1]Material!F$5:U$90000,16,0)="AGI",VLOOKUP(B9,[1]Material!F$5:U$90000,16,0)="AGIGA"),"AGIGA", OR(LEFT(VLOOKUP(B9,[1]Material!F$5:U$90000,16,0),3)="EF-",VLOOKUP(B9,[1]Material!F$5:U$90000,16,0)="EFI"),"EFI", AND(ISNUMBER(VLOOKUP(B9,[1]Material!F$5:U$90000,16,0)),VLOOKUP(B9,[1]Material!F$5:U$90000,16,0)>=100,VLOOKUP(B9,[1]Material!F$5:U$90000,16,0)<=999,VLOOKUP(B9,[1]Material!F$5:U$90000,16,0)=INT(VLOOKUP(B9,[1]Material!F$5:U$90000,16,0))),"OEM", TRUE,"" ), "không tìm thấy trong file Import" ), VLOOKUP(F9,'[2]Export shipment'!B:Y,24,0) )} -> PURE | H9: =VLOOKUP(B9,[4]Export!I$3627:J$3898,2,0) -> #N/A | I9: CIP | J9: =(V9+X9+AA9)/'Logistics record '!$AD$1 -> 15.116015 | K9: =W9/'Logistics record '!$AD$1 -> 0 | L9: =Y9/'Logistics record '!$AD$1 -> 0 | M9: =AF9/'Logistics record '!$AD$1 -> 60.75051 | N9: {=_xlfn.IFS( OR(UPPER(S9)="AIR", UPPER(S9)="CPN"), "AIR", UPPER(S9)="TC", "LOCAL", TRUE, "SEA" )} -> AIR | O9: =M9+L9+K9+J9 -> 75.866526 | P9: JP | Q9: 108275044140 | R9: 46167 | S9: AIR | T9: 3.4 | V9: 400000 | Z9: =SUM(V9:Y9) -> 400000 | AA9: 0 | AB9: =+AA9+Z9 -> 400000 | AD9: 1220400 | AE9: 387180 | AF9: =+SUM(AC9:AE9) -> 1607580 | AG9: =+AF9+AB9 -> 2007580 | AI9: =VLOOKUP(Q9,[3]Sheet1!B$11:G$1489,6,0) -> E11
A10: 7 | B10: 8XN5262 | C10: 1591CPU | D10: KIOXIA CORPORATION C/O KIOXIA AMERICA INC | E10: =IF(OR(AI10="E11", AI10="E13", AI10="E15", AI10="G13"), "Import", "Export") -> Import | F10: {=_xlfn.IFS( OR(AI10="E11", AI10="E15"), "Raw materials", OR(AI10="E13", AI10="G13"), "Equipments + Toolings", TRUE, RIGHT(C10, 8) )} -> Raw materials | G10: {=IF(E10="Import", IFERROR( _xlfn.IFS( VLOOKUP(B10,[1]Material!F$5:U$90000,16,0)="LUC","Lucid", VLOOKUP(B10,[1]Material!F$5:U$90000,16,0)="FMC","FORD", OR(VLOOKUP(B10,[1]Material!F$5:U$90000,16,0)="PUR",VLOOKUP(B10,[1]Material!F$5:U$90000,16,0)="HLO"),"PURE", VLOOKUP(B10,[1]Material!F$5:U$90000,16,0)="AIC","AIC", OR(VLOOKUP(B10,[1]Material!F$5:U$90000,16,0)="AGI",VLOOKUP(B10,[1]Material!F$5:U$90000,16,0)="AGIGA"),"AGIGA", OR(LEFT(VLOOKUP(B10,[1]Material!F$5:U$90000,16,0),3)="EF-",VLOOKUP(B10,[1]Material!F$5:U$90000,16,0)="EFI"),"EFI", AND(ISNUMBER(VLOOKUP(B10,[1]Material!F$5:U$90000,16,0)),VLOOKUP(B10,[1]Material!F$5:U$90000,16,0)>=100,VLOOKUP(B10,[1]Material!F$5:U$90000,16,0)<=999,VLOOKUP(B10,[1]Material!F$5:U$90000,16,0)=INT(VLOOKUP(B10,[1]Material!F$5:U$90000,16,0))),"OEM", TRUE,"" ), "không tìm thấy trong file Import" ), VLOOKUP(F10,'[2]Export shipment'!B:Y,24,0) )} -> PURE | H10: =VLOOKUP(B10,[4]Export!I$3627:J$3898,2,0) -> #N/A | I10: CIP | J10: =(V10+X10+AA10)/'Logistics record '!$AD$1 -> 15.116015 | K10: =W10/'Logistics record '!$AD$1 -> 0 | L10: =Y10/'Logistics record '!$AD$1 -> 0 | M10: =AF10/'Logistics record '!$AD$1 -> 60.75051 | N10: {=_xlfn.IFS( OR(UPPER(S10)="AIR", UPPER(S10)="CPN"), "AIR", UPPER(S10)="TC", "LOCAL", TRUE, "SEA" )} -> AIR | O10: =M10+L10+K10+J10 -> 75.866526 | P10: JP | Q10: 108275053500 | R10: 46167 | S10: AIR | T10: 3.4 | V10: 400000 | Z10: =SUM(V10:Y10) -> 400000 | AA10: 0 | AB10: =+AA10+Z10 -> 400000 | AD10: 1220400 | AE10: 387180 | AF10: =+SUM(AC10:AE10) -> 1607580 | AG10: =+AF10+AB10 -> 2007580 | AI10: =VLOOKUP(Q10,[3]Sheet1!B$11:G$1489,6,0) -> E11
A11: 8 | B11: 8XN5254 | C11: 1591CPK | D11: KIOXIA CORPORATION C/O KIOXIA AMERICA INC | E11: =IF(OR(AI11="E11", AI11="E13", AI11="E15", AI11="G13"), "Import", "Export") -> Import | F11: {=_xlfn.IFS( OR(AI11="E11", AI11="E15"), "Raw materials", OR(AI11="E13", AI11="G13"), "Equipments + Toolings", TRUE, RIGHT(C11, 8) )} -> Raw materials | G11: {=IF(E11="Import", IFERROR( _xlfn.IFS( VLOOKUP(B11,[1]Material!F$5:U$90000,16,0)="LUC","Lucid", VLOOKUP(B11,[1]Material!F$5:U$90000,16,0)="FMC","FORD", OR(VLOOKUP(B11,[1]Material!F$5:U$90000,16,0)="PUR",VLOOKUP(B11,[1]Material!F$5:U$90000,16,0)="HLO"),"PURE", VLOOKUP(B11,[1]Material!F$5:U$90000,16,0)="AIC","AIC", OR(VLOOKUP(B11,[1]Material!F$5:U$90000,16,0)="AGI",VLOOKUP(B11,[1]Material!F$5:U$90000,16,0)="AGIGA"),"AGIGA", OR(LEFT(VLOOKUP(B11,[1]Material!F$5:U$90000,16,0),3)="EF-",VLOOKUP(B11,[1]Material!F$5:U$90000,16,0)="EFI"),"EFI", AND(ISNUMBER(VLOOKUP(B11,[1]Material!F$5:U$90000,16,0)),VLOOKUP(B11,[1]Material!F$5:U$90000,16,0)>=100,VLOOKUP(B11,[1]Material!F$5:U$90000,16,0)<=999,VLOOKUP(B11,[1]Material!F$5:U$90000,16,0)=INT(VLOOKUP(B11,[1]Material!F$5:U$90000,16,0))),"OEM", TRUE,"" ), "không tìm thấy trong file Import" ), VLOOKUP(F11,'[2]Export shipment'!B:Y,24,0) )} -> PURE | H11: =VLOOKUP(B11,[4]Export!I$3627:J$3898,2,0) -> #N/A | I11: CIP | J11: =(V11+X11+AA11)/'Logistics record '!$AD$1 -> 15.116015 | K11: =W11/'Logistics record '!$AD$1 -> 0 | L11: =Y11/'Logistics record '!$AD$1 -> 0 | M11: =AF11/'Logistics record '!$AD$1 -> 60.75051 | N11: {=_xlfn.IFS( OR(UPPER(S11)="AIR", UPPER(S11)="CPN"), "AIR", UPPER(S11)="TC", "LOCAL", TRUE, "SEA" )} -> AIR | O11: =M11+L11+K11+J11 -> 75.866526 | P11: JP | Q11: 108275208420 | R11: 46167 | S11: AIR | T11: 3.4 | V11: 400000 | Z11: =SUM(V11:Y11) -> 400000 | AA11: 0 | AB11: =+AA11+Z11 -> 400000 | AD11: 1220400 | AE11: 387180 | AF11: =+SUM(AC11:AE11) -> 1607580 | AG11: =+AF11+AB11 -> 2007580 | AI11: =VLOOKUP(Q11,[3]Sheet1!B$11:G$1489,6,0) -> E11
A12: 9 | B12: 8XN5259 | C12: 1591CPR | D12: KIOXIA CORPORATION C/O KIOXIA AMERICA INC | E12: =IF(OR(AI12="E11", AI12="E13", AI12="E15", AI12="G13"), "Import", "Export") -> Import | F12: {=_xlfn.IFS( OR(AI12="E11", AI12="E15"), "Raw materials", OR(AI12="E13", AI12="G13"), "Equipments + Toolings", TRUE, RIGHT(C12, 8) )} -> Raw materials | G12: {=IF(E12="Import", IFERROR( _xlfn.IFS( VLOOKUP(B12,[1]Material!F$5:U$90000,16,0)="LUC","Lucid", VLOOKUP(B12,[1]Material!F$5:U$90000,16,0)="FMC","FORD", OR(VLOOKUP(B12,[1]Material!F$5:U$90000,16,0)="PUR",VLOOKUP(B12,[1]Material!F$5:U$90000,16,0)="HLO"),"PURE", VLOOKUP(B12,[1]Material!F$5:U$90000,16,0)="AIC","AIC", OR(VLOOKUP(B12,[1]Material!F$5:U$90000,16,0)="AGI",VLOOKUP(B12,[1]Material!F$5:U$90000,16,0)="AGIGA"),"AGIGA", OR(LEFT(VLOOKUP(B12,[1]Material!F$5:U$90000,16,0),3)="EF-",VLOOKUP(B12,[1]Material!F$5:U$90000,16,0)="EFI"),"EFI", AND(ISNUMBER(VLOOKUP(B12,[1]Material!F$5:U$90000,16,0)),VLOOKUP(B12,[1]Material!F$5:U$90000,16,0)>=100,VLOOKUP(B12,[1]Material!F$5:U$90000,16,0)<=999,VLOOKUP(B12,[1]Material!F$5:U$90000,16,0)=INT(VLOOKUP(B12,[1]Material!F$5:U$90000,16,0))),"OEM", TRUE,"" ), "không tìm thấy trong file Import" ), VLOOKUP(F12,'[2]Export shipment'!B:Y,24,0) )} -> PURE | H12: =VLOOKUP(B12,[4]Export!I$3627:J$3898,2,0) -> #N/A | I12: CIP | J12: =(V12+X12+AA12)/'Logistics record '!$AD$1 -> 15.116015 | K12: =W12/'Logistics record '!$AD$1 -> 0 | L12: =Y12/'Logistics record '!$AD$1 -> 0 | M12: =AF12/'Logistics record '!$AD$1 -> 60.75051 | N12: {=_xlfn.IFS( OR(UPPER(S12)="AIR", UPPER(S12)="CPN"), "AIR", UPPER(S12)="TC", "LOCAL", TRUE, "SEA" )} -> AIR | O12: =M12+L12+K12+J12 -> 75.866526 | P12: JP | Q12: 108275280630 | R12: 46167 | S12: AIR | T12: 3.4 | V12: 400000 | Z12: =SUM(V12:Y12) -> 400000 | AA12: 0 | AB12: =+AA12+Z12 -> 400000 | AD12: 1220400 | AE12: 387180 | AF12: =+SUM(AC12:AE12) -> 1607580 | AG12: =+AF12+AB12 -> 2007580 | AI12: =VLOOKUP(Q12,[3]Sheet1!B$11:G$1489,6,0) -> E11
A13: 10 | B13: 8XN5270 | C13: 1591CR2 | D13: KIOXIA CORPORATION C/O KIOXIA AMERICA INC | E13: =IF(OR(AI13="E11", AI13="E13", AI13="E15", AI13="G13"), "Import", "Export") -> Import | F13: {=_xlfn.IFS( OR(AI13="E11", AI13="E15"), "Raw materials", OR(AI13="E13", AI13="G13"), "Equipments + Toolings", TRUE, RIGHT(C13, 8) )} -> Raw materials | G13: {=IF(E13="Import", IFERROR( _xlfn.IFS( VLOOKUP(B13,[1]Material!F$5:U$90000,16,0)="LUC","Lucid", VLOOKUP(B13,[1]Material!F$5:U$90000,16,0)="FMC","FORD", OR(VLOOKUP(B13,[1]Material!F$5:U$90000,16,0)="PUR",VLOOKUP(B13,[1]Material!F$5:U$90000,16,0)="HLO"),"PURE", VLOOKUP(B13,[1]Material!F$5:U$90000,16,0)="AIC","AIC", OR(VLOOKUP(B13,[1]Material!F$5:U$90000,16,0)="AGI",VLOOKUP(B13,[1]Material!F$5:U$90000,16,0)="AGIGA"),"AGIGA", OR(LEFT(VLOOKUP(B13,[1]Material!F$5:U$90000,16,0),3)="EF-",VLOOKUP(B13,[1]Material!F$5:U$90000,16,0)="EFI"),"EFI", AND(ISNUMBER(VLOOKUP(B13,[1]Material!F$5:U$90000,16,0)),VLOOKUP(B13,[1]Material!F$5:U$90000,16,0)>=100,VLOOKUP(B13,[1]Material!F$5:U$90000,16,0)<=999,VLOOKUP(B13,[1]Material!F$5:U$90000,16,0)=INT(VLOOKUP(B13,[1]Material!F$5:U$90000,16,0))),"OEM", TRUE,"" ), "không tìm thấy trong file Import" ), VLOOKUP(F13,'[2]Export shipment'!B:Y,24,0) )} -> PURE | H13: =VLOOKUP(B13,[4]Export!I$3627:J$3898,2,0) -> #N/A | I13: CIP | J13: =(V13+X13+AA13)/'Logistics record '!$AD$1 -> 15.116015 | K13: =W13/'Logistics record '!$AD$1 -> 0 | L13: =Y13/'Logistics record '!$AD$1 -> 0 | M13: =AF13/'Logistics record '!$AD$1 -> 60.75051 | N13: {=_xlfn.IFS( OR(UPPER(S13)="AIR", UPPER(S13)="CPN"), "AIR", UPPER(S13)="TC", "LOCAL", TRUE, "SEA" )} -> AIR | O13: =M13+L13+K13+J13 -> 75.866526 | P13: JP | Q13: 108275293120 | R13: 46167 | S13: AIR | T13: 3.4 | V13: 400000 | Z13: =SUM(V13:Y13) -> 400000 | AA13: 0 | AB13: =+AA13+Z13 -> 400000 | AD13: 1220400 | AE13: 387180 | AF13: =+SUM(AC13:AE13) -> 1607580 | AG13: =+AF13+AB13 -> 2007580 | AI13: =VLOOKUP(Q13,[3]Sheet1!B$11:G$1489,6,0) -> E11
A14: 11 | B14: 8XN5255 | C14: 1591CPL | D14: KIOXIA CORPORATION C/O KIOXIA AMERICA INC | E14: =IF(OR(AI14="E11", AI14="E13", AI14="E15", AI14="G13"), "Import", "Export") -> Import | F14: {=_xlfn.IFS( OR(AI14="E11", AI14="E15"), "Raw materials", OR(AI14="E13", AI14="G13"), "Equipments + Toolings", TRUE, RIGHT(C14, 8) )} -> Raw materials | G14: {=IF(E14="Import", IFERROR( _xlfn.IFS( VLOOKUP(B14,[1]Material!F$5:U$90000,16,0)="LUC","Lucid", VLOOKUP(B14,[1]Material!F$5:U$90000,16,0)="FMC","FORD", OR(VLOOKUP(B14,[1]Material!F$5:U$90000,16,0)="PUR",VLOOKUP(B14,[1]Material!F$5:U$90000,16,0)="HLO"),"PURE", VLOOKUP(B14,[1]Material!F$5:U$90000,16,0)="AIC","AIC", OR(VLOOKUP(B14,[1]Material!F$5:U$90000,16,0)="AGI",VLOOKUP(B14,[1]Material!F$5:U$90000,16,0)="AGIGA"),"AGIGA", OR(LEFT(VLOOKUP(B14,[1]Material!F$5:U$90000,16,0),3)="EF-",VLOOKUP(B14,[1]Material!F$5:U$90000,16,0)="EFI"),"EFI", AND(ISNUMBER(VLOOKUP(B14,[1]Material!F$5:U$90000,16,0)),VLOOKUP(B14,[1]Material!F$5:U$90000,16,0)>=100,VLOOKUP(B14,[1]Material!F$5:U$90000,16,0)<=999,VLOOKUP(B14,[1]Material!F$5:U$90000,16,0)=INT(VLOOKUP(B14,[1]Material!F$5:U$90000,16,0))),"OEM", TRUE,"" ), "không tìm thấy trong file Import" ), VLOOKUP(F14,'[2]Export shipment'!B:Y,24,0) )} -> PURE | H14: =VLOOKUP(B14,[4]Export!I$3627:J$3898,2,0) -> #N/A | I14: CIP | J14: =(V14+X14+AA14)/'Logistics record '!$AD$1 -> 15.116015 | K14: =W14/'Logistics record '!$AD$1 -> 0 | L14: =Y14/'Logistics record '!$AD$1 -> 0 | M14: =AF14/'Logistics record '!$AD$1 -> 60.75051 | N14: {=_xlfn.IFS( OR(UPPER(S14)="AIR", UPPER(S14)="CPN"), "AIR", UPPER(S14)="TC", "LOCAL", TRUE, "SEA" )} -> AIR | O14: =M14+L14+K14+J14 -> 75.866526 | P14: JP | Q14: 108275340830 | R14: 46167 | S14: AIR | T14: 3.4 | V14: 400000 | Z14: =SUM(V14:Y14) -> 400000 | AA14: 0 | AB14: =+AA14+Z14 -> 400000 | AD14: 1220400 | AE14: 387180 | AF14: =+SUM(AC14:AE14) -> 1607580 | AG14: =+AF14+AB14 -> 2007580 | AI14: =VLOOKUP(Q14,[3]Sheet1!B$11:G$1489,6,0) -> E11
A15: 12 | B15: 8XN5912 | C15: 1591CT7 | D15: KIOXIA CORPORATION C/O KIOXIA AMERICA INC | E15: =IF(OR(AI15="E11", AI15="E13", AI15="E15", AI15="G13"), "Import", "Export") -> Import | F15: {=_xlfn.IFS( OR(AI15="E11", AI15="E15"), "Raw materials", OR(AI15="E13", AI15="G13"), "Equipments + Toolings", TRUE, RIGHT(C15, 8) )} -> Raw materials | G15: {=IF(E15="Import", IFERROR( _xlfn.IFS( VLOOKUP(B15,[1]Material!F$5:U$90000,16,0)="LUC","Lucid", VLOOKUP(B15,[1]Material!F$5:U$90000,16,0)="FMC","FORD", OR(VLOOKUP(B15,[1]Material!F$5:U$90000,16,0)="PUR",VLOOKUP(B15,[1]Material!F$5:U$90000,16,0)="HLO"),"PURE", VLOOKUP(B15,[1]Material!F$5:U$90000,16,0)="AIC","AIC", OR(VLOOKUP(B15,[1]Material!F$5:U$90000,16,0)="AGI",VLOOKUP(B15,[1]Material!F$5:U$90000,16,0)="AGIGA"),"AGIGA", OR(LEFT(VLOOKUP(B15,[1]Material!F$5:U$90000,16,0),3)="EF-",VLOOKUP(B15,[1]Material!F$5:U$90000,16,0)="EFI"),"EFI", AND(ISNUMBER(VLOOKUP(B15,[1]Material!F$5:U$90000,16,0)),VLOOKUP(B15,[1]Material!F$5:U$90000,16,0)>=100,VLOOKUP(B15,[1]Material!F$5:U$90000,16,0)<=999,VLOOKUP(B15,[1]Material!F$5:U$90000,16,0)=INT(VLOOKUP(B15,[1]Material!F$5:U$90000,16,0))),"OEM", TRUE,"" ), "không tìm thấy trong file Import" ), VLOOKUP(F15,'[2]Export shipment'!B:Y,24,0) )} -> PURE | H15: =VLOOKUP(B15,[4]Export!I$3627:J$3898,2,0) -> #N/A | I15: CIP | J15: =(V15+X15+AA15)/'Logistics record '!$AD$1 -> 15.116015 | K15: =W15/'Logistics record '!$AD$1 -> 0 | L15: =Y15/'Logistics record '!$AD$1 -> 0 | M15: =AF15/'Logistics record '!$AD$1 -> 60.75051 | N15: {=_xlfn.IFS( OR(UPPER(S15)="AIR", UPPER(S15)="CPN"), "AIR", UPPER(S15)="TC", "LOCAL", TRUE, "SEA" )} -> AIR | O15: =M15+L15+K15+J15 -> 75.866526 | P15: JP | Q15: 108275392150 | R15: 46167 | S15: AIR | T15: 4.8 | V15: 400000 | Z15: =SUM(V15:Y15) -> 400000 | AA15: 0 | AB15: =+AA15+Z15 -> 400000 | AD15: 1220400 | AE15: 387180 | AF15: =+SUM(AC15:AE15) -> 1607580 | AG15: =+AF15+AB15 -> 2007580 | AI15: =VLOOKUP(Q15,[3]Sheet1!B$11:G$1489,6,0) -> E11
A16: 13 | B16: 8XN5273 | C16: 1591CR5 | D16: KIOXIA CORPORATION C/O KIOXIA AMERICA INC | E16: =IF(OR(AI16="E11", AI16="E13", AI16="E15", AI16="G13"), "Import", "Export") -> Import | F16: {=_xlfn.IFS( OR(AI16="E11", AI16="E15"), "Raw materials", OR(AI16="E13", AI16="G13"), "Equipments + Toolings", TRUE, RIGHT(C16, 8) )} -> Raw materials | G16: {=IF(E16="Import", IFERROR( _xlfn.IFS( VLOOKUP(B16,[1]Material!F$5:U$90000,16,0)="LUC","Lucid", VLOOKUP(B16,[1]Material!F$5:U$90000,16,0)="FMC","FORD", OR(VLOOKUP(B16,[1]Material!F$5:U$90000,16,0)="PUR",VLOOKUP(B16,[1]Material!F$5:U$90000,16,0)="HLO"),"PURE", VLOOKUP(B16,[1]Material!F$5:U$90000,16,0)="AIC","AIC", OR(VLOOKUP(B16,[1]Material!F$5:U$90000,16,0)="AGI",VLOOKUP(B16,[1]Material!F$5:U$90000,16,0)="AGIGA"),"AGIGA", OR(LEFT(VLOOKUP(B16,[1]Material!F$5:U$90000,16,0),3)="EF-",VLOOKUP(B16,[1]Material!F$5:U$90000,16,0)="EFI"),"EFI", AND(ISNUMBER(VLOOKUP(B16,[1]Material!F$5:U$90000,16,0)),VLOOKUP(B16,[1]Material!F$5:U$90000,16,0)>=100,VLOOKUP(B16,[1]Material!F$5:U$90000,16,0)<=999,VLOOKUP(B16,[1]Material!F$5:U$90000,16,0)=INT(VLOOKUP(B16,[1]Material!F$5:U$90000,16,0))),"OEM", TRUE,"" ), "không tìm thấy trong file Import" ), VLOOKUP(F16,'[2]Export shipment'!B:Y,24,0) )} -> PURE | H16: =VLOOKUP(B16,[4]Export!I$3627:J$3898,2,0) -> #N/A | I16: CIP | J16: =(V16+X16+AA16)/'Logistics record '!$AD$1 -> 15.116015 | K16: =W16/'Logistics record '!$AD$1 -> 0 | L16: =Y16/'Logistics record '!$AD$1 -> 0 | M16: =AF16/'Logistics record '!$AD$1 -> 60.75051 | N16: {=_xlfn.IFS( OR(UPPER(S16)="AIR", UPPER(S16)="CPN"), "AIR", UPPER(S16)="TC", "LOCAL", TRUE, "SEA" )} -> AIR | O16: =M16+L16+K16+J16 -> 75.866526 | P16: JP | Q16: 108275443950 | R16: 46167 | S16: AIR | T16: 3.4 | V16: 400000 | Z16: =SUM(V16:Y16) -> 400000 | AA16: 0 | AB16: =+AA16+Z16 -> 400000 | AD16: 1220400 | AE16: 387180 | AF16: =+SUM(AC16:AE16) -> 1607580 | AG16: =+AF16+AB16 -> 2007580 | AI16: =VLOOKUP(Q16,[3]Sheet1!B$11:G$1489,6,0) -> E11
A17: 14 | B17: 8XN5266 | C17: 1591CPY | D17: KIOXIA CORPORATION C/O KIOXIA AMERICA INC | E17: =IF(OR(AI17="E11", AI17="E13", AI17="E15", AI17="G13"), "Import", "Export") -> Import | F17: {=_xlfn.IFS( OR(AI17="E11", AI17="E15"), "Raw materials", OR(AI17="E13", AI17="G13"), "Equipments + Toolings", TRUE, RIGHT(C17, 8) )} -> Raw materials | G17: {=IF(E17="Import", IFERROR( _xlfn.IFS( VLOOKUP(B17,[1]Material!F$5:U$90000,16,0)="LUC","Lucid", VLOOKUP(B17,[1]Material!F$5:U$90000,16,0)="FMC","FORD", OR(VLOOKUP(B17,[1]Material!F$5:U$90000,16,0)="PUR",VLOOKUP(B17,[1]Material!F$5:U$90000,16,0)="HLO"),"PURE", VLOOKUP(B17,[1]Material!F$5:U$90000,16,0)="AIC","AIC", OR(VLOOKUP(B17,[1]Material!F$5:U$90000,16,0)="AGI",VLOOKUP(B17,[1]Material!F$5:U$90000,16,0)="AGIGA"),"AGIGA", OR(LEFT(VLOOKUP(B17,[1]Material!F$5:U$90000,16,0),3)="EF-",VLOOKUP(B17,[1]Material!F$5:U$90000,16,0)="EFI"),"EFI", AND(ISNUMBER(VLOOKUP(B17,[1]Material!F$5:U$90000,16,0)),VLOOKUP(B17,[1]Material!F$5:U$90000,16,0)>=100,VLOOKUP(B17,[1]Material!F$5:U$90000,16,0)<=999,VLOOKUP(B17,[1]Material!F$5:U$90000,16,0)=INT(VLOOKUP(B17,[1]Material!F$5:U$90000,16,0))),"OEM", TRUE,"" ), "không tìm thấy trong file Import" ), VLOOKUP(F17,'[2]Export shipment'!B:Y,24,0) )} -> PURE | H17: =VLOOKUP(B17,[4]Export!I$3627:J$3898,2,0) -> #N/A | I17: CIP | J17: =(V17+X17+AA17)/'Logistics record '!$AD$1 -> 15.116015 | K17: =W17/'Logistics record '!$AD$1 -> 0 | L17: =Y17/'Logistics record '!$AD$1 -> 0 | M17: =AF17/'Logistics record '!$AD$1 -> 60.75051 | N17: {=_xlfn.IFS( OR(UPPER(S17)="AIR", UPPER(S17)="CPN"), "AIR", UPPER(S17)="TC", "LOCAL", TRUE, "SEA" )} -> AIR | O17: =M17+L17+K17+J17 -> 75.866526 | P17: JP | Q17: 108275447120 | R17: 46167 | S17: AIR | T17: 3.4 | V17: 400000 | Z17: =SUM(V17:Y17) -> 400000 | AA17: 0 | AB17: =+AA17+Z17 -> 400000 | AD17: 1220400 | AE17: 387180 | AF17: =+SUM(AC17:AE17) -> 1607580 | AG17: =+AF17+AB17 -> 2007580 | AI17: =VLOOKUP(Q17,[3]Sheet1!B$11:G$1489,6,0) -> E11
A18: 15 | B18: 8XN5252 | C18: 1591CPH | D18: KIOXIA CORPORATION C/O KIOXIA AMERICA INC | E18: =IF(OR(AI18="E11", AI18="E13", AI18="E15", AI18="G13"), "Import", "Export") -> Import | F18: {=_xlfn.IFS( OR(AI18="E11", AI18="E15"), "Raw materials", OR(AI18="E13", AI18="G13"), "Equipments + Toolings", TRUE, RIGHT(C18, 8) )} -> Raw materials | G18: {=IF(E18="Import", IFERROR( _xlfn.IFS( VLOOKUP(B18,[1]Material!F$5:U$90000,16,0)="LUC","Lucid", VLOOKUP(B18,[1]Material!F$5:U$90000,16,0)="FMC","FORD", OR(VLOOKUP(B18,[1]Material!F$5:U$90000,16,0)="PUR",VLOOKUP(B18,[1]Material!F$5:U$90000,16,0)="HLO"),"PURE", VLOOKUP(B18,[1]Material!F$5:U$90000,16,0)="AIC","AIC", OR(VLOOKUP(B18,[1]Material!F$5:U$90000,16,0)="AGI",VLOOKUP(B18,[1]Material!F$5:U$90000,16,0)="AGIGA"),"AGIGA", OR(LEFT(VLOOKUP(B18,[1]Material!F$5:U$90000,16,0),3)="EF-",VLOOKUP(B18,[1]Material!F$5:U$90000,16,0)="EFI"),"EFI", AND(ISNUMBER(VLOOKUP(B18,[1]Material!F$5:U$90000,16,0)),VLOOKUP(B18,[1]Material!F$5:U$90000,16,0)>=100,VLOOKUP(B18,[1]Material!F$5:U$90000,16,0)<=999,VLOOKUP(B18,[1]Material!F$5:U$90000,16,0)=INT(VLOOKUP(B18,[1]Material!F$5:U$90000,16,0))),"OEM", TRUE,"" ), "không tìm thấy trong file Import" ), VLOOKUP(F18,'[2]Export shipment'!B:Y,24,0) )} -> PURE | H18: =VLOOKUP(B18,[4]Export!I$3627:J$3898,2,0) -> #N/A | I18: CIP | J18: =(V18+X18+AA18)/'Logistics record '!$AD$1 -> 15.116015 | K18: =W18/'Logistics record '!$AD$1 -> 0 | L18: =Y18/'Logistics record '!$AD$1 -> 0 | M18: =AF18/'Logistics record '!$AD$1 -> 60.75051 | N18: {=_xlfn.IFS( OR(UPPER(S18)="AIR", UPPER(S18)="CPN"), "AIR", UPPER(S18)="TC", "LOCAL", TRUE, "SEA" )} -> AIR | O18: =M18+L18+K18+J18 -> 75.866526 | P18: JP | Q18: 108275454120 | R18: 46167 | S18: AIR | T18: 3.4 | V18: 400000 | Z18: =SUM(V18:Y18) -> 400000 | AA18: 0 | AB18: =+AA18+Z18 -> 400000 | AD18: 1220400 | AE18: 387180 | AF18: =+SUM(AC18:AE18) -> 1607580 | AG18: =+AF18+AB18 -> 2007580 | AI18: =VLOOKUP(Q18,[3]Sheet1!B$11:G$1489,6,0) -> E11
A19: 16 | B19: 8XN5275 | C19: 1591CR7 | D19: KIOXIA CORPORATION C/O KIOXIA AMERICA INC | E19: =IF(OR(AI19="E11", AI19="E13", AI19="E15", AI19="G13"), "Import", "Export") -> Import | F19: {=_xlfn.IFS( OR(AI19="E11", AI19="E15"), "Raw materials", OR(AI19="E13", AI19="G13"), "Equipments + Toolings", TRUE, RIGHT(C19, 8) )} -> Raw materials | G19: {=IF(E19="Import", IFERROR( _xlfn.IFS( VLOOKUP(B19,[1]Material!F$5:U$90000,16,0)="LUC","Lucid", VLOOKUP(B19,[1]Material!F$5:U$90000,16,0)="FMC","FORD", OR(VLOOKUP(B19,[1]Material!F$5:U$90000,16,0)="PUR",VLOOKUP(B19,[1]Material!F$5:U$90000,16,0)="HLO"),"PURE", VLOOKUP(B19,[1]Material!F$5:U$90000,16,0)="AIC","AIC", OR(VLOOKUP(B19,[1]Material!F$5:U$90000,16,0)="AGI",VLOOKUP(B19,[1]Material!F$5:U$90000,16,0)="AGIGA"),"AGIGA", OR(LEFT(VLOOKUP(B19,[1]Material!F$5:U$90000,16,0),3)="EF-",VLOOKUP(B19,[1]Material!F$5:U$90000,16,0)="EFI"),"EFI", AND(ISNUMBER(VLOOKUP(B19,[1]Material!F$5:U$90000,16,0)),VLOOKUP(B19,[1]Material!F$5:U$90000,16,0)>=100,VLOOKUP(B19,[1]Material!F$5:U$90000,16,0)<=999,VLOOKUP(B19,[1]Material!F$5:U$90000,16,0)=INT(VLOOKUP(B19,[1]Material!F$5:U$90000,16,0))),"OEM", TRUE,"" ), "không tìm thấy trong file Import" ), VLOOKUP(F19,'[2]Export shipment'!B:Y,24,0) )} -> PURE | H19: =VLOOKUP(B19,[4]Export!I$3627:J$3898,2,0) -> #N/A | I19: CIP | J19: =(V19+X19+AA19)/'Logistics record '!$AD$1 -> 15.116015 | K19: =W19/'Logistics record '!$AD$1 -> 0 | L19: =Y19/'Logistics record '!$AD$1 -> 0 | M19: =AF19/'Logistics record '!$AD$1 -> 60.75051 | N19: {=_xlfn.IFS( OR(UPPER(S19)="AIR", UPPER(S19)="CPN"), "AIR", UPPER(S19)="TC", "LOCAL", TRUE, "SEA" )} -> AIR | O19: =M19+L19+K19+J19 -> 75.866526 | P19: JP | Q19: 108275486100 | R19: 46167 | S19: AIR | T19: 2.7 | V19: 400000 | Z19: =SUM(V19:Y19) -> 400000 | AA19: 0 | AB19: =+AA19+Z19 -> 400000 | AD19: 1220400 | AE19: 387180 | AF19: =+SUM(AC19:AE19) -> 1607580 | AG19: =+AF19+AB19 -> 2007580 | AI19: =VLOOKUP(Q19,[3]Sheet1!B$11:G$1489,6,0) -> E11
A20: 17 | B20: 8XN5253 | C20: 1591CPJ | D20: KIOXIA CORPORATION C/O KIOXIA AMERICA INC | E20: =IF(OR(AI20="E11", AI20="E13", AI20="E15", AI20="G13"), "Import", "Export") -> Import | F20: {=_xlfn.IFS( OR(AI20="E11", AI20="E15"), "Raw materials", OR(AI20="E13", AI20="G13"), "Equipments + Toolings", TRUE, RIGHT(C20, 8) )} -> Raw materials | G20: {=IF(E20="Import", IFERROR( _xlfn.IFS( VLOOKUP(B20,[1]Material!F$5:U$90000,16,0)="LUC","Lucid", VLOOKUP(B20,[1]Material!F$5:U$90000,16,0)="FMC","FORD", OR(VLOOKUP(B20,[1]Material!F$5:U$90000,16,0)="PUR",VLOOKUP(B20,[1]Material!F$5:U$90000,16,0)="HLO"),"PURE", VLOOKUP(B20,[1]Material!F$5:U$90000,16,0)="AIC","AIC", OR(VLOOKUP(B20,[1]Material!F$5:U$90000,16,0)="AGI",VLOOKUP(B20,[1]Material!F$5:U$90000,16,0)="AGIGA"),"AGIGA", OR(LEFT(VLOOKUP(B20,[1]Material!F$5:U$90000,16,0),3)="EF-",VLOOKUP(B20,[1]Material!F$5:U$90000,16,0)="EFI"),"EFI", AND(ISNUMBER(VLOOKUP(B20,[1]Material!F$5:U$90000,16,0)),VLOOKUP(B20,[1]Material!F$5:U$90000,16,0)>=100,VLOOKUP(B20,[1]Material!F$5:U$90000,16,0)<=999,VLOOKUP(B20,[1]Material!F$5:U$90000,16,0)=INT(VLOOKUP(B20,[1]Material!F$5:U$90000,16,0))),"OEM", TRUE,"" ), "không tìm thấy trong file Import" ), VLOOKUP(F20,'[2]Export shipment'!B:Y,24,0) )} -> PURE | H20: =VLOOKUP(B20,[4]Export!I$3627:J$3898,2,0) -> #N/A | I20: CIP | J20: =(V20+X20+AA20)/'Logistics record '!$AD$1 -> 15.116015 | K20: =W20/'Logistics record '!$AD$1 -> 0 | L20: =Y20/'Logistics record '!$AD$1 -> 0 | M20: =AF20/'Logistics record '!$AD$1 -> 60.75051 | N20: {=_xlfn.IFS( OR(UPPER(S20)="AIR", UPPER(S20)="CPN"), "AIR", UPPER(S20)="TC", "LOCAL", TRUE, "SEA" )} -> AIR | O20: =M20+L20+K20+J20 -> 75.866526 | P20: JP | Q20: 108275492360 | R20: 46167 | S20: AIR | T20: 3.4 | V20: 400000 | Z20: =SUM(V20:Y20) -> 400000 | AA20: 0 | AB20: =+AA20+Z20 -> 400000 | AD20: 1220400 | AE20: 387180 | AF20: =+SUM(AC20:AE20) -> 1607580 | AG20: =+AF20+AB20 -> 2007580 | AI20: =VLOOKUP(Q20,[3]Sheet1!B$11:G$1489,6,0) -> E11
... A37: 34 | B37: 8XN5909 | C37: 1591CT4 | D37: KIOXIA CORPORATION C/O KIOXIA AMERICA INC | E37: =IF(OR(AI37="E11", AI37="E13", AI37="E15", AI37="G13"), "Import", "Export") -> Import | F37: {=_xlfn.IFS( OR(AI37="E11", AI37="E15"), "Raw materials", OR(AI37="E13", AI37="G13"), "Equipments + Toolings", TRUE, RIGHT(C37, 8) )} -> Raw materials | G37: {=IF(E37="Import", IFERROR( _xlfn.IFS( VLOOKUP(B37,[1]Material!F$5:U$90000,16,0)="LUC","Lucid", VLOOKUP(B37,[1]Material!F$5:U$90000,16,0)="FMC","FORD", OR(VLOOKUP(B37,[1]Material!F$5:U$90000,16,0)="PUR",VLOOKUP(B37,[1]Material!F$5:U$90000,16,0)="HLO"),"PURE", VLOOKUP(B37,[1]Material!F$5:U$90000,16,0)="AIC","AIC", OR(VLOOKUP(B37,[1]Material!F$5:U$90000,16,0)="AGI",VLOOKUP(B37,[1]Material!F$5:U$90000,16,0)="AGIGA"),"AGIGA", OR(LEFT(VLOOKUP(B37,[1]Material!F$5:U$90000,16,0),3)="EF-",VLOOKUP(B37,[1]Material!F$5:U$90000,16,0)="EFI"),"EFI", AND(ISNUMBER(VLOOKUP(B37,[1]Material!F$5:U$90000,16,0)),VLOOKUP(B37,[1]Material!F$5:U$90000,16,0)>=100,VLOOKUP(B37,[1]Material!F$5:U$90000,16,0)<=999,VLOOKUP(B37,[1]Material!F$5:U$90000,16,0)=INT(VLOOKUP(B37,[1]Material!F$5:U$90000,16,0))),"OEM", TRUE,"" ), "không tìm thấy trong file Import" ), VLOOKUP(F37,'[2]Export shipment'!B:Y,24,0) )} -> PURE | H37: =VLOOKUP(B37,[4]Export!I$3627:J$3898,2,0) -> #N/A | I37: CIP | J37: =(V37+X37+AA37)/'Logistics record '!$AD$1 -> 15.116015 | K37: =W37/'Logistics record '!$AD$1 -> 0 | L37: =Y37/'Logistics record '!$AD$1 -> 0 | M37: =AF37/'Logistics record '!$AD$1 -> 60.75051 | N37: {=_xlfn.IFS( OR(UPPER(S37)="AIR", UPPER(S37)="CPN"), "AIR", UPPER(S37)="TC", "LOCAL", TRUE, "SEA" )} -> AIR | O37: =M37+L37+K37+J37 -> 75.866526 | P37: JP | Q37: 108275788610 | R37: 46167 | S37: AIR | T37: 3.4 | V37: 400000 | Z37: =SUM(V37:Y37) -> 400000 | AA37: 0 | AB37: =+AA37+Z37 -> 400000 | AD37: 1220400 | AE37: 387180 | AF37: =+SUM(AC37:AE37) -> 1607580 | AG37: =+AF37+AB37 -> 2007580 | AI37: =VLOOKUP(Q37,[3]Sheet1!B$11:G$1489,6,0) -> E11
A38: 35 | B38: 8XN5900 | C38: 1591CSV | D38: KIOXIA CORPORATION C/O KIOXIA AMERICA INC | E38: =IF(OR(AI38="E11", AI38="E13", AI38="E15", AI38="G13"), "Import", "Export") -> Import | F38: {=_xlfn.IFS( OR(AI38="E11", AI38="E15"), "Raw materials", OR(AI38="E13", AI38="G13"), "Equipments + Toolings", TRUE, RIGHT(C38, 8) )} -> Raw materials | G38: {=IF(E38="Import", IFERROR( _xlfn.IFS( VLOOKUP(B38,[1]Material!F$5:U$90000,16,0)="LUC","Lucid", VLOOKUP(B38,[1]Material!F$5:U$90000,16,0)="FMC","FORD", OR(VLOOKUP(B38,[1]Material!F$5:U$90000,16,0)="PUR",VLOOKUP(B38,[1]Material!F$5:U$90000,16,0)="HLO"),"PURE", VLOOKUP(B38,[1]Material!F$5:U$90000,16,0)="AIC","AIC", OR(VLOOKUP(B38,[1]Material!F$5:U$90000,16,0)="AGI",VLOOKUP(B38,[1]Material!F$5:U$90000,16,0)="AGIGA"),"AGIGA", OR(LEFT(VLOOKUP(B38,[1]Material!F$5:U$90000,16,0),3)="EF-",VLOOKUP(B38,[1]Material!F$5:U$90000,16,0)="EFI"),"EFI", AND(ISNUMBER(VLOOKUP(B38,[1]Material!F$5:U$90000,16,0)),VLOOKUP(B38,[1]Material!F$5:U$90000,16,0)>=100,VLOOKUP(B38,[1]Material!F$5:U$90000,16,0)<=999,VLOOKUP(B38,[1]Material!F$5:U$90000,16,0)=INT(VLOOKUP(B38,[1]Material!F$5:U$90000,16,0))),"OEM", TRUE,"" ), "không tìm thấy trong file Import" ), VLOOKUP(F38,'[2]Export shipment'!B:Y,24,0) )} -> PURE | I38: DAP | J38: =(V38+X38+AA38)/'Logistics record '!$AD$1 -> 15.116015 | K38: =W38/'Logistics record '!$AD$1 -> 0 | L38: =Y38/'Logistics record '!$AD$1 -> 0 | M38: =AF38/'Logistics record '!$AD$1 -> 0 | N38: {=_xlfn.IFS( OR(UPPER(S38)="AIR", UPPER(S38)="CPN"), "AIR", UPPER(S38)="TC", "LOCAL", TRUE, "SEA" )} -> AIR | O38: =M38+L38+K38+J38 -> 15.116015 | P38: JP | Q38: 108275794910 | R38: 46167 | S38: AIR | T38: 7.3 | V38: 400000 | Z38: =SUM(V38:Y38) -> 400000 | AA38: 0 | AB38: =+AA38+Z38 -> 400000 | AF38: =+SUM(AC38:AE38) -> 0 | AG38: =+AF38+AB38 -> 400000 | AI38: =VLOOKUP(Q38,[3]Sheet1!B$11:G$1489,6,0) -> E11
A39: 36 | B39: 8XN5277 | C39: 15W1S3C | D39: KIOXIA CORPORATION C/O KIOXIA AMERICA INC | E39: =IF(OR(AI39="E11", AI39="E13", AI39="E15", AI39="G13"), "Import", "Export") -> Import | F39: {=_xlfn.IFS( OR(AI39="E11", AI39="E15"), "Raw materials", OR(AI39="E13", AI39="G13"), "Equipments + Toolings", TRUE, RIGHT(C39, 8) )} -> Raw materials | G39: {=IF(E39="Import", IFERROR( _xlfn.IFS( VLOOKUP(B39,[1]Material!F$5:U$90000,16,0)="LUC","Lucid", VLOOKUP(B39,[1]Material!F$5:U$90000,16,0)="FMC","FORD", OR(VLOOKUP(B39,[1]Material!F$5:U$90000,16,0)="PUR",VLOOKUP(B39,[1]Material!F$5:U$90000,16,0)="HLO"),"PURE", VLOOKUP(B39,[1]Material!F$5:U$90000,16,0)="AIC","AIC", OR(VLOOKUP(B39,[1]Material!F$5:U$90000,16,0)="AGI",VLOOKUP(B39,[1]Material!F$5:U$90000,16,0)="AGIGA"),"AGIGA", OR(LEFT(VLOOKUP(B39,[1]Material!F$5:U$90000,16,0),3)="EF-",VLOOKUP(B39,[1]Material!F$5:U$90000,16,0)="EFI"),"EFI", AND(ISNUMBER(VLOOKUP(B39,[1]Material!F$5:U$90000,16,0)),VLOOKUP(B39,[1]Material!F$5:U$90000,16,0)>=100,VLOOKUP(B39,[1]Material!F$5:U$90000,16,0)<=999,VLOOKUP(B39,[1]Material!F$5:U$90000,16,0)=INT(VLOOKUP(B39,[1]Material!F$5:U$90000,16,0))),"OEM", TRUE,"" ), "không tìm thấy trong file Import" ), VLOOKUP(F39,'[2]Export shipment'!B:Y,24,0) )} -> PURE | H39: =VLOOKUP(B39,[4]Export!I$3627:J$3668,2,0) -> #N/A | I39: CIP | J39: =(V39+X39+AA39)/'Logistics record '!$AD$1 -> 15.116015 | K39: =W39/'Logistics record '!$AD$1 -> 0 | L39: =Y39/'Logistics record '!$AD$1 -> 0 | M39: =AF39/'Logistics record '!$AD$1 -> 60.75051 | N39: {=_xlfn.IFS( OR(UPPER(S39)="AIR", UPPER(S39)="CPN"), "AIR", UPPER(S39)="TC", "LOCAL", TRUE, "SEA" )} -> AIR | O39: =M39+L39+K39+J39 -> 75.866526 | P39: JP | Q39: 108275821250 | R39: 46167 | S39: AIR | T39: 6.5 | V39: 400000 | Z39: =SUM(V39:Y39) -> 400000 | AA39: 0 | AB39: =+AA39+Z39 -> 400000 | AD39: 1220400 | AE39: 387180 | AF39: =+SUM(AC39:AE39) -> 1607580 | AG39: =+AF39+AB39 -> 2007580 | AI39: =VLOOKUP(Q39,[3]Sheet1!B$11:G$1489,6,0) -> E11
A40: 37 | B40: 8XN5261 | C40: 1591CPT | D40: KIOXIA CORPORATION C/O KIOXIA AMERICA INC | E40: =IF(OR(AI40="E11", AI40="E13", AI40="E15", AI40="G13"), "Import", "Export") -> Import | F40: {=_xlfn.IFS( OR(AI40="E11", AI40="E15"), "Raw materials", OR(AI40="E13", AI40="G13"), "Equipments + Toolings", TRUE, RIGHT(C40, 8) )} -> Raw materials | G40: {=IF(E40="Import", IFERROR( _xlfn.IFS( VLOOKUP(B40,[1]Material!F$5:U$90000,16,0)="LUC","Lucid", VLOOKUP(B40,[1]Material!F$5:U$90000,16,0)="FMC","FORD", OR(VLOOKUP(B40,[1]Material!F$5:U$90000,16,0)="PUR",VLOOKUP(B40,[1]Material!F$5:U$90000,16,0)="HLO"),"PURE", VLOOKUP(B40,[1]Material!F$5:U$90000,16,0)="AIC","AIC", OR(VLOOKUP(B40,[1]Material!F$5:U$90000,16,0)="AGI",VLOOKUP(B40,[1]Material!F$5:U$90000,16,0)="AGIGA"),"AGIGA", OR(LEFT(VLOOKUP(B40,[1]Material!F$5:U$90000,16,0),3)="EF-",VLOOKUP(B40,[1]Material!F$5:U$90000,16,0)="EFI"),"EFI", AND(ISNUMBER(VLOOKUP(B40,[1]Material!F$5:U$90000,16,0)),VLOOKUP(B40,[1]Material!F$5:U$90000,16,0)>=100,VLOOKUP(B40,[1]Material!F$5:U$90000,16,0)<=999,VLOOKUP(B40,[1]Material!F$5:U$90000,16,0)=INT(VLOOKUP(B40,[1]Material!F$5:U$90000,16,0))),"OEM", TRUE,"" ), "không tìm thấy trong file Import" ), VLOOKUP(F40,'[2]Export shipment'!B:Y,24,0) )} -> PURE | H40: =VLOOKUP(B40,[4]Export!I$3627:J$3668,2,0) -> #N/A | I40: CIP | J40: =(V40+X40+AA40)/'Logistics record '!$AD$1 -> 15.116015 | K40: =W40/'Logistics record '!$AD$1 -> 0 | L40: =Y40/'Logistics record '!$AD$1 -> 0 | M40: =AF40/'Logistics record '!$AD$1 -> 60.75051 | N40: {=_xlfn.IFS( OR(UPPER(S40)="AIR", UPPER(S40)="CPN"), "AIR", UPPER(S40)="TC", "LOCAL", TRUE, "SEA" )} -> AIR | O40: =M40+L40+K40+J40 -> 75.866526 | P40: JP | Q40: 108275861630 | R40: 46167 | S40: AIR | T40: 3.4 | V40: 400000 | Z40: =SUM(V40:Y40) -> 400000 | AA40: 0 | AB40: =+AA40+Z40 -> 400000 | AD40: 1220400 | AE40: 387180 | AF40: =+SUM(AC40:AE40) -> 1607580 | AG40: =+AF40+AB40 -> 2007580 | AI40: =VLOOKUP(Q40,[3]Sheet1!B$11:G$1489,6,0) -> E11
A41: 38 | B41: 8XN5260 | C41: 1591CPS | D41: KIOXIA CORPORATION C/O KIOXIA AMERICA INC | E41: =IF(OR(AI41="E11", AI41="E13", AI41="E15", AI41="G13"), "Import", "Export") -> Import | F41: {=_xlfn.IFS( OR(AI41="E11", AI41="E15"), "Raw materials", OR(AI41="E13", AI41="G13"), "Equipments + Toolings", TRUE, RIGHT(C41, 8) )} -> Raw materials | G41: {=IF(E41="Import", IFERROR( _xlfn.IFS( VLOOKUP(B41,[1]Material!F$5:U$90000,16,0)="LUC","Lucid", VLOOKUP(B41,[1]Material!F$5:U$90000,16,0)="FMC","FORD", OR(VLOOKUP(B41,[1]Material!F$5:U$90000,16,0)="PUR",VLOOKUP(B41,[1]Material!F$5:U$90000,16,0)="HLO"),"PURE", VLOOKUP(B41,[1]Material!F$5:U$90000,16,0)="AIC","AIC", OR(VLOOKUP(B41,[1]Material!F$5:U$90000,16,0)="AGI",VLOOKUP(B41,[1]Material!F$5:U$90000,16,0)="AGIGA"),"AGIGA", OR(LEFT(VLOOKUP(B41,[1]Material!F$5:U$90000,16,0),3)="EF-",VLOOKUP(B41,[1]Material!F$5:U$90000,16,0)="EFI"),"EFI", AND(ISNUMBER(VLOOKUP(B41,[1]Material!F$5:U$90000,16,0)),VLOOKUP(B41,[1]Material!F$5:U$90000,16,0)>=100,VLOOKUP(B41,[1]Material!F$5:U$90000,16,0)<=999,VLOOKUP(B41,[1]Material!F$5:U$90000,16,0)=INT(VLOOKUP(B41,[1]Material!F$5:U$90000,16,0))),"OEM", TRUE,"" ), "không tìm thấy trong file Import" ), VLOOKUP(F41,'[2]Export shipment'!B:Y,24,0) )} -> PURE | H41: =VLOOKUP(B41,[4]Export!I$3627:J$3668,2,0) -> #N/A | I41: CIP | J41: =(V41+X41+AA41)/'Logistics record '!$AD$1 -> 15.116015 | K41: =W41/'Logistics record '!$AD$1 -> 0 | L41: =Y41/'Logistics record '!$AD$1 -> 0 | M41: =AF41/'Logistics record '!$AD$1 -> 60.75051 | N41: {=_xlfn.IFS( OR(UPPER(S41)="AIR", UPPER(S41)="CPN"), "AIR", UPPER(S41)="TC", "LOCAL", TRUE, "SEA" )} -> AIR | O41: =M41+L41+K41+J41 -> 75.866526 | P41: JP | Q41: 108275872130 | R41: 46167 | S41: AIR | T41: 3.4 | V41: 400000 | Z41: =SUM(V41:Y41) -> 400000 | AA41: 0 | AB41: =+AA41+Z41 -> 400000 | AD41: 1220400 | AE41: 387180 | AF41: =+SUM(AC41:AE41) -> 1607580 | AG41: =+AF41+AB41 -> 2007580 | AI41: =VLOOKUP(Q41,[3]Sheet1!B$11:G$1489,6,0) -> E11
A42: 39 | B42: 8XN5901 | C42: 1591CSW | D42: KIOXIA CORPORATION C/O KIOXIA AMERICA INC | E42: =IF(OR(AI42="E11", AI42="E13", AI42="E15", AI42="G13"), "Import", "Export") -> Import | F42: {=_xlfn.IFS( OR(AI42="E11", AI42="E15"), "Raw materials", OR(AI42="E13", AI42="G13"), "Equipments + Toolings", TRUE, RIGHT(C42, 8) )} -> Raw materials | G42: {=IF(E42="Import", IFERROR( _xlfn.IFS( VLOOKUP(B42,[1]Material!F$5:U$90000,16,0)="LUC","Lucid", VLOOKUP(B42,[1]Material!F$5:U$90000,16,0)="FMC","FORD", OR(VLOOKUP(B42,[1]Material!F$5:U$90000,16,0)="PUR",VLOOKUP(B42,[1]Material!F$5:U$90000,16,0)="HLO"),"PURE", VLOOKUP(B42,[1]Material!F$5:U$90000,16,0)="AIC","AIC", OR(VLOOKUP(B42,[1]Material!F$5:U$90000,16,0)="AGI",VLOOKUP(B42,[1]Material!F$5:U$90000,16,0)="AGIGA"),"AGIGA", OR(LEFT(VLOOKUP(B42,[1]Material!F$5:U$90000,16,0),3)="EF-",VLOOKUP(B42,[1]Material!F$5:U$90000,16,0)="EFI"),"EFI", AND(ISNUMBER(VLOOKUP(B42,[1]Material!F$5:U$90000,16,0)),VLOOKUP(B42,[1]Material!F$5:U$90000,16,0)>=100,VLOOKUP(B42,[1]Material!F$5:U$90000,16,0)<=999,VLOOKUP(B42,[1]Material!F$5:U$90000,16,0)=INT(VLOOKUP(B42,[1]Material!F$5:U$90000,16,0))),"OEM", TRUE,"" ), "không tìm thấy trong file Import" ), VLOOKUP(F42,'[2]Export shipment'!B:Y,24,0) )} -> PURE | I42: DAP | J42: =(V42+X42+AA42)/'Logistics record '!$AD$1 -> 15.116015 | K42: =W42/'Logistics record '!$AD$1 -> 0 | L42: =Y42/'Logistics record '!$AD$1 -> 0 | M42: =AF42/'Logistics record '!$AD$1 -> 0 | N42: {=_xlfn.IFS( OR(UPPER(S42)="AIR", UPPER(S42)="CPN"), "AIR", UPPER(S42)="TC", "LOCAL", TRUE, "SEA" )} -> AIR | O42: =M42+L42+K42+J42 -> 15.116015 | P42: JP | Q42: 108275887750 | R42: 46167 | S42: AIR | T42: 9.2 | V42: 400000 | Z42: =SUM(V42:Y42) -> 400000 | AA42: 0 | AB42: =+AA42+Z42 -> 400000 | AF42: =+SUM(AC42:AE42) -> 0 | AG42: =+AF42+AB42 -> 400000 | AI42: =VLOOKUP(Q42,[3]Sheet1!B$11:G$1489,6,0) -> E11
A43: 40 | B43: 8XN5269 | C43: 1591CR1 | D43: KIOXIA CORPORATION C/O KIOXIA AMERICA INC | E43: =IF(OR(AI43="E11", AI43="E13", AI43="E15", AI43="G13"), "Import", "Export") -> Import | F43: {=_xlfn.IFS( OR(AI43="E11", AI43="E15"), "Raw materials", OR(AI43="E13", AI43="G13"), "Equipments + Toolings", TRUE, RIGHT(C43, 8) )} -> Raw materials | G43: {=IF(E43="Import", IFERROR( _xlfn.IFS( VLOOKUP(B43,[1]Material!F$5:U$90000,16,0)="LUC","Lucid", VLOOKUP(B43,[1]Material!F$5:U$90000,16,0)="FMC","FORD", OR(VLOOKUP(B43,[1]Material!F$5:U$90000,16,0)="PUR",VLOOKUP(B43,[1]Material!F$5:U$90000,16,0)="HLO"),"PURE", VLOOKUP(B43,[1]Material!F$5:U$90000,16,0)="AIC","AIC", OR(VLOOKUP(B43,[1]Material!F$5:U$90000,16,0)="AGI",VLOOKUP(B43,[1]Material!F$5:U$90000,16,0)="AGIGA"),"AGIGA", OR(LEFT(VLOOKUP(B43,[1]Material!F$5:U$90000,16,0),3)="EF-",VLOOKUP(B43,[1]Material!F$5:U$90000,16,0)="EFI"),"EFI", AND(ISNUMBER(VLOOKUP(B43,[1]Material!F$5:U$90000,16,0)),VLOOKUP(B43,[1]Material!F$5:U$90000,16,0)>=100,VLOOKUP(B43,[1]Material!F$5:U$90000,16,0)<=999,VLOOKUP(B43,[1]Material!F$5:U$90000,16,0)=INT(VLOOKUP(B43,[1]Material!F$5:U$90000,16,0))),"OEM", TRUE,"" ), "không tìm thấy trong file Import" ), VLOOKUP(F43,'[2]Export shipment'!B:Y,24,0) )} -> PURE | H43: =VLOOKUP(B43,[4]Export!I$3627:J$3668,2,0) -> #N/A | I43: CIP | J43: =(V43+X43+AA43)/'Logistics record '!$AD$1 -> 15.116015 | K43: =W43/'Logistics record '!$AD$1 -> 0 | L43: =Y43/'Logistics record '!$AD$1 -> 0 | M43: =AF43/'Logistics record '!$AD$1 -> 60.75051 | N43: {=_xlfn.IFS( OR(UPPER(S43)="AIR", UPPER(S43)="CPN"), "AIR", UPPER(S43)="TC", "LOCAL", TRUE, "SEA" )} -> AIR | O43: =M43+L43+K43+J43 -> 75.866526 | P43: JP | Q43: 108275898250 | R43: 46167 | S43: AIR | T43: 3.4 | V43: 400000 | Z43: =SUM(V43:Y43) -> 400000 | AA43: 0 | AB43: =+AA43+Z43 -> 400000 | AD43: 1220400 | AE43: 387180 | AF43: =+SUM(AC43:AE43) -> 1607580 | AG43: =+AF43+AB43 -> 2007580 | AI43: =VLOOKUP(Q43,[3]Sheet1!B$11:G$1489,6,0) -> E11
A44: 41 | B44: 8XN5280 | C44: 15W1S3F | D44: KIOXIA CORPORATION C/O KIOXIA AMERICA INC | E44: =IF(OR(AI44="E11", AI44="E13", AI44="E15", AI44="G13"), "Import", "Export") -> Import | F44: {=_xlfn.IFS( OR(AI44="E11", AI44="E15"), "Raw materials", OR(AI44="E13", AI44="G13"), "Equipments + Toolings", TRUE, RIGHT(C44, 8) )} -> Raw materials | G44: {=IF(E44="Import", IFERROR( _xlfn.IFS( VLOOKUP(B44,[1]Material!F$5:U$90000,16,0)="LUC","Lucid", VLOOKUP(B44,[1]Material!F$5:U$90000,16,0)="FMC","FORD", OR(VLOOKUP(B44,[1]Material!F$5:U$90000,16,0)="PUR",VLOOKUP(B44,[1]Material!F$5:U$90000,16,0)="HLO"),"PURE", VLOOKUP(B44,[1]Material!F$5:U$90000,16,0)="AIC","AIC", OR(VLOOKUP(B44,[1]Material!F$5:U$90000,16,0)="AGI",VLOOKUP(B44,[1]Material!F$5:U$90000,16,0)="AGIGA"),"AGIGA", OR(LEFT(VLOOKUP(B44,[1]Material!F$5:U$90000,16,0),3)="EF-",VLOOKUP(B44,[1]Material!F$5:U$90000,16,0)="EFI"),"EFI", AND(ISNUMBER(VLOOKUP(B44,[1]Material!F$5:U$90000,16,0)),VLOOKUP(B44,[1]Material!F$5:U$90000,16,0)>=100,VLOOKUP(B44,[1]Material!F$5:U$90000,16,0)<=999,VLOOKUP(B44,[1]Material!F$5:U$90000,16,0)=INT(VLOOKUP(B44,[1]Material!F$5:U$90000,16,0))),"OEM", TRUE,"" ), "không tìm thấy trong file Import" ), VLOOKUP(F44,'[2]Export shipment'!B:Y,24,0) )} -> PURE | H44: =VLOOKUP(B44,[4]Export!I$3627:J$3668,2,0) -> #N/A | I44: CIP | J44: =(V44+X44+AA44)/'Logistics record '!$AD$1 -> 15.116015 | K44: =W44/'Logistics record '!$AD$1 -> 0 | L44: =Y44/'Logistics record '!$AD$1 -> 0 | M44: =AF44/'Logistics record '!$AD$1 -> 60.75051 | N44: {=_xlfn.IFS( OR(UPPER(S44)="AIR", UPPER(S44)="CPN"), "AIR", UPPER(S44)="TC", "LOCAL", TRUE, "SEA" )} -> AIR | O44: =M44+L44+K44+J44 -> 75.866526 | P44: JP | Q44: 108276113960 | R44: 46167 | S44: AIR | T44: 6.5 | V44: 400000 | Z44: =SUM(V44:Y44) -> 400000 | AA44: 0 | AB44: =+AA44+Z44 -> 400000 | AD44: 1220400 | AE44: 387180 | AF44: =+SUM(AC44:AE44) -> 1607580 | AG44: =+AF44+AB44 -> 2007580 | AI44: =VLOOKUP(Q44,[3]Sheet1!B$11:G$1489,6,0) -> E11
A45: 42 | B45: 8XN5282 | C45: 15W1S3H | D45: KIOXIA CORPORATION C/O KIOXIA AMERICA INC | E45: =IF(OR(AI45="E11", AI45="E13", AI45="E15", AI45="G13"), "Import", "Export") -> Import | F45: {=_xlfn.IFS( OR(AI45="E11", AI45="E15"), "Raw materials", OR(AI45="E13", AI45="G13"), "Equipments + Toolings", TRUE, RIGHT(C45, 8) )} -> Raw materials | G45: {=IF(E45="Import", IFERROR( _xlfn.IFS( VLOOKUP(B45,[1]Material!F$5:U$90000,16,0)="LUC","Lucid", VLOOKUP(B45,[1]Material!F$5:U$90000,16,0)="FMC","FORD", OR(VLOOKUP(B45,[1]Material!F$5:U$90000,16,0)="PUR",VLOOKUP(B45,[1]Material!F$5:U$90000,16,0)="HLO"),"PURE", VLOOKUP(B45,[1]Material!F$5:U$90000,16,0)="AIC","AIC", OR(VLOOKUP(B45,[1]Material!F$5:U$90000,16,0)="AGI",VLOOKUP(B45,[1]Material!F$5:U$90000,16,0)="AGIGA"),"AGIGA", OR(LEFT(VLOOKUP(B45,[1]Material!F$5:U$90000,16,0),3)="EF-",VLOOKUP(B45,[1]Material!F$5:U$90000,16,0)="EFI"),"EFI", AND(ISNUMBER(VLOOKUP(B45,[1]Material!F$5:U$90000,16,0)),VLOOKUP(B45,[1]Material!F$5:U$90000,16,0)>=100,VLOOKUP(B45,[1]Material!F$5:U$90000,16,0)<=999,VLOOKUP(B45,[1]Material!F$5:U$90000,16,0)=INT(VLOOKUP(B45,[1]Material!F$5:U$90000,16,0))),"OEM", TRUE,"" ), "không tìm thấy trong file Import" ), VLOOKUP(F45,'[2]Export shipment'!B:Y,24,0) )} -> PURE | H45: =VLOOKUP(B45,[4]Export!I$3627:J$3668,2,0) -> #N/A | I45: CIP | J45: =(V45+X45+AA45)/'Logistics record '!$AD$1 -> 15.116015 | K45: =W45/'Logistics record '!$AD$1 -> 0 | L45: =Y45/'Logistics record '!$AD$1 -> 0 | M45: =AF45/'Logistics record '!$AD$1 -> 60.75051 | N45: {=_xlfn.IFS( OR(UPPER(S45)="AIR", UPPER(S45)="CPN"), "AIR", UPPER(S45)="TC", "LOCAL", TRUE, "SEA" )} -> AIR | O45: =M45+L45+K45+J45 -> 75.866526 | P45: JP | Q45: 108276114700 | R45: 46167 | S45: AIR | T45: 2.3 | V45: 400000 | Z45: =SUM(V45:Y45) -> 400000 | AA45: 0 | AB45: =+AA45+Z45 -> 400000 | AD45: 1220400 | AE45: 387180 | AF45: =+SUM(AC45:AE45) -> 1607580 | AG45: =+AF45+AB45 -> 2007580 | AI45: =VLOOKUP(Q45,[3]Sheet1!B$11:G$1489,6,0) -> E11
A46: 43 | B46: 8XN5278 | C46: 15W1S3D | D46: KIOXIA CORPORATION C/O KIOXIA AMERICA INC | E46: =IF(OR(AI46="E11", AI46="E13", AI46="E15", AI46="G13"), "Import", "Export") -> Import | F46: {=_xlfn.IFS( OR(AI46="E11", AI46="E15"), "Raw materials", OR(AI46="E13", AI46="G13"), "Equipments + Toolings", TRUE, RIGHT(C46, 8) )} -> Raw materials | G46: {=IF(E46="Import", IFERROR( _xlfn.IFS( VLOOKUP(B46,[1]Material!F$5:U$90000,16,0)="LUC","Lucid", VLOOKUP(B46,[1]Material!F$5:U$90000,16,0)="FMC","FORD", OR(VLOOKUP(B46,[1]Material!F$5:U$90000,16,0)="PUR",VLOOKUP(B46,[1]Material!F$5:U$90000,16,0)="HLO"),"PURE", VLOOKUP(B46,[1]Material!F$5:U$90000,16,0)="AIC","AIC", OR(VLOOKUP(B46,[1]Material!F$5:U$90000,16,0)="AGI",VLOOKUP(B46,[1]Material!F$5:U$90000,16,0)="AGIGA"),"AGIGA", OR(LEFT(VLOOKUP(B46,[1]Material!F$5:U$90000,16,0),3)="EF-",VLOOKUP(B46,[1]Material!F$5:U$90000,16,0)="EFI"),"EFI", AND(ISNUMBER(VLOOKUP(B46,[1]Material!F$5:U$90000,16,0)),VLOOKUP(B46,[1]Material!F$5:U$90000,16,0)>=100,VLOOKUP(B46,[1]Material!F$5:U$90000,16,0)<=999,VLOOKUP(B46,[1]Material!F$5:U$90000,16,0)=INT(VLOOKUP(B46,[1]Material!F$5:U$90000,16,0))),"OEM", TRUE,"" ), "không tìm thấy trong file Import" ), VLOOKUP(F46,'[2]Export shipment'!B:Y,24,0) )} -> PURE | H46: =VLOOKUP(B46,[4]Export!I$3627:J$3668,2,0) -> #N/A | I46: CIP | J46: =(V46+X46+AA46)/'Logistics record '!$AD$1 -> 15.116015 | K46: =W46/'Logistics record '!$AD$1 -> 0 | L46: =Y46/'Logistics record '!$AD$1 -> 0 | M46: =AF46/'Logistics record '!$AD$1 -> 60.75051 | N46: {=_xlfn.IFS( OR(UPPER(S46)="AIR", UPPER(S46)="CPN"), "AIR", UPPER(S46)="TC", "LOCAL", TRUE, "SEA" )} -> AIR | O46: =M46+L46+K46+J46 -> 75.866526 | P46: JP | Q46: 108276136950 | R46: 46167 | S46: AIR | T46: 6.5 | V46: 400000 | Z46: =SUM(V46:Y46) -> 400000 | AA46: 0 | AB46: =+AA46+Z46 -> 400000 | AD46: 1220400 | AE46: 387180 | AF46: =+SUM(AC46:AE46) -> 1607580 | AG46: =+AF46+AB46 -> 2007580 | AI46: =VLOOKUP(Q46,[3]Sheet1!B$11:G$1489,6,0) -> E11
A47: 44 | B47: 8XN5905 | C47: 1591CT0 | D47: KIOXIA CORPORATION C/O KIOXIA AMERICA INC | E47: =IF(OR(AI47="E11", AI47="E13", AI47="E15", AI47="G13"), "Import", "Export") -> Import | F47: {=_xlfn.IFS( OR(AI47="E11", AI47="E15"), "Raw materials", OR(AI47="E13", AI47="G13"), "Equipments + Toolings", TRUE, RIGHT(C47, 8) )} -> Raw materials | G47: {=IF(E47="Import", IFERROR( _xlfn.IFS( VLOOKUP(B47,[1]Material!F$5:U$90000,16,0)="LUC","Lucid", VLOOKUP(B47,[1]Material!F$5:U$90000,16,0)="FMC","FORD", OR(VLOOKUP(B47,[1]Material!F$5:U$90000,16,0)="PUR",VLOOKUP(B47,[1]Material!F$5:U$90000,16,0)="HLO"),"PURE", VLOOKUP(B47,[1]Material!F$5:U$90000,16,0)="AIC","AIC", OR(VLOOKUP(B47,[1]Material!F$5:U$90000,16,0)="AGI",VLOOKUP(B47,[1]Material!F$5:U$90000,16,0)="AGIGA"),"AGIGA", OR(LEFT(VLOOKUP(B47,[1]Material!F$5:U$90000,16,0),3)="EF-",VLOOKUP(B47,[1]Material!F$5:U$90000,16,0)="EFI"),"EFI", AND(ISNUMBER(VLOOKUP(B47,[1]Material!F$5:U$90000,16,0)),VLOOKUP(B47,[1]Material!F$5:U$90000,16,0)>=100,VLOOKUP(B47,[1]Material!F$5:U$90000,16,0)<=999,VLOOKUP(B47,[1]Material!F$5:U$90000,16,0)=INT(VLOOKUP(B47,[1]Material!F$5:U$90000,16,0))),"OEM", TRUE,"" ), "không tìm thấy trong file Import" ), VLOOKUP(F47,'[2]Export shipment'!B:Y,24,0) )} -> PURE | H47: =VLOOKUP(B47,[4]Export!I$3627:J$3668,2,0) -> #N/A | I47: CIP | J47: =(V47+X47+AA47)/'Logistics record '!$AD$1 -> 15.116015 | K47: =W47/'Logistics record '!$AD$1 -> 0 | L47: =Y47/'Logistics record '!$AD$1 -> 0 | M47: =AF47/'Logistics record '!$AD$1 -> 60.75051 | N47: {=_xlfn.IFS( OR(UPPER(S47)="AIR", UPPER(S47)="CPN"), "AIR", UPPER(S47)="TC", "LOCAL", TRUE, "SEA" )} -> AIR | O47: =M47+L47+K47+J47 -> 75.866526 | P47: JP | Q47: 108276159350 | R47: 46167 | S47: AIR | T47: 3.4 | V47: 400000 | Z47: =SUM(V47:Y47) -> 400000 | AA47: 0 | AB47: =+AA47+Z47 -> 400000 | AD47: 1220400 | AE47: 387180 | AF47: =+SUM(AC47:AE47) -> 1607580 | AG47: =+AF47+AB47 -> 2007580 | AI47: =VLOOKUP(Q47,[3]Sheet1!B$11:G$1489,6,0) -> E11
A48: 45 | B48: 8XN5276 | C48: 15W1S3B | D48: KIOXIA CORPORATION C/O KIOXIA AMERICA INC | E48: =IF(OR(AI48="E11", AI48="E13", AI48="E15", AI48="G13"), "Import", "Export") -> Import | F48: {=_xlfn.IFS( OR(AI48="E11", AI48="E15"), "Raw materials", OR(AI48="E13", AI48="G13"), "Equipments + Toolings", TRUE, RIGHT(C48, 8) )} -> Raw materials | G48: {=IF(E48="Import", IFERROR( _xlfn.IFS( VLOOKUP(B48,[1]Material!F$5:U$90000,16,0)="LUC","Lucid", VLOOKUP(B48,[1]Material!F$5:U$90000,16,0)="FMC","FORD", OR(VLOOKUP(B48,[1]Material!F$5:U$90000,16,0)="PUR",VLOOKUP(B48,[1]Material!F$5:U$90000,16,0)="HLO"),"PURE", VLOOKUP(B48,[1]Material!F$5:U$90000,16,0)="AIC","AIC", OR(VLOOKUP(B48,[1]Material!F$5:U$90000,16,0)="AGI",VLOOKUP(B48,[1]Material!F$5:U$90000,16,0)="AGIGA"),"AGIGA", OR(LEFT(VLOOKUP(B48,[1]Material!F$5:U$90000,16,0),3)="EF-",VLOOKUP(B48,[1]Material!F$5:U$90000,16,0)="EFI"),"EFI", AND(ISNUMBER(VLOOKUP(B48,[1]Material!F$5:U$90000,16,0)),VLOOKUP(B48,[1]Material!F$5:U$90000,16,0)>=100,VLOOKUP(B48,[1]Material!F$5:U$90000,16,0)<=999,VLOOKUP(B48,[1]Material!F$5:U$90000,16,0)=INT(VLOOKUP(B48,[1]Material!F$5:U$90000,16,0))),"OEM", TRUE,"" ), "không tìm thấy trong file Import" ), VLOOKUP(F48,'[2]Export shipment'!B:Y,24,0) )} -> PURE | H48: =VLOOKUP(B48,[4]Export!I$3627:J$3668,2,0) -> #N/A | I48: CIP | J48: =(V48+X48+AA48)/'Logistics record '!$AD$1 -> 15.116015 | K48: =W48/'Logistics record '!$AD$1 -> 0 | L48: =Y48/'Logistics record '!$AD$1 -> 0 | M48: =AF48/'Logistics record '!$AD$1 -> 60.75051 | N48: {=_xlfn.IFS( OR(UPPER(S48)="AIR", UPPER(S48)="CPN"), "AIR", UPPER(S48)="TC", "LOCAL", TRUE, "SEA" )} -> AIR | O48: =M48+L48+K48+J48 -> 75.866526 | P48: JP | Q48: 108276175230 | R48: 46167 | S48: AIR | T48: 6.5 | V48: 400000 | Z48: =SUM(V48:Y48) -> 400000 | AA48: 0 | AB48: =+AA48+Z48 -> 400000 | AD48: 1220400 | AE48: 387180 | AF48: =+SUM(AC48:AE48) -> 1607580 | AG48: =+AF48+AB48 -> 2007580 | AI48: =VLOOKUP(Q48,[3]Sheet1!B$11:G$1489,6,0) -> E11
A49: 46 | B49: 8XN5281 | C49: 15W1S3G | D49: KIOXIA CORPORATION C/O KIOXIA AMERICA INC | E49: =IF(OR(AI49="E11", AI49="E13", AI49="E15", AI49="G13"), "Import", "Export") -> Import | F49: {=_xlfn.IFS( OR(AI49="E11", AI49="E15"), "Raw materials", OR(AI49="E13", AI49="G13"), "Equipments + Toolings", TRUE, RIGHT(C49, 8) )} -> Raw materials | G49: {=IF(E49="Import", IFERROR( _xlfn.IFS( VLOOKUP(B49,[1]Material!F$5:U$90000,16,0)="LUC","Lucid", VLOOKUP(B49,[1]Material!F$5:U$90000,16,0)="FMC","FORD", OR(VLOOKUP(B49,[1]Material!F$5:U$90000,16,0)="PUR",VLOOKUP(B49,[1]Material!F$5:U$90000,16,0)="HLO"),"PURE", VLOOKUP(B49,[1]Material!F$5:U$90000,16,0)="AIC","AIC", OR(VLOOKUP(B49,[1]Material!F$5:U$90000,16,0)="AGI",VLOOKUP(B49,[1]Material!F$5:U$90000,16,0)="AGIGA"),"AGIGA", OR(LEFT(VLOOKUP(B49,[1]Material!F$5:U$90000,16,0),3)="EF-",VLOOKUP(B49,[1]Material!F$5:U$90000,16,0)="EFI"),"EFI", AND(ISNUMBER(VLOOKUP(B49,[1]Material!F$5:U$90000,16,0)),VLOOKUP(B49,[1]Material!F$5:U$90000,16,0)>=100,VLOOKUP(B49,[1]Material!F$5:U$90000,16,0)<=999,VLOOKUP(B49,[1]Material!F$5:U$90000,16,0)=INT(VLOOKUP(B49,[1]Material!F$5:U$90000,16,0))),"OEM", TRUE,"" ), "không tìm thấy trong file Import" ), VLOOKUP(F49,'[2]Export shipment'!B:Y,24,0) )} -> PURE | H49: =VLOOKUP(B49,[4]Export!I$3627:J$3668,2,0) -> #N/A | I49: CIP | J49: =(V49+X49+AA49)/'Logistics record '!$AD$1 -> 15.116015 | K49: =W49/'Logistics record '!$AD$1 -> 0 | L49: =Y49/'Logistics record '!$AD$1 -> 0 | M49: =AF49/'Logistics record '!$AD$1 -> 60.75051 | N49: {=_xlfn.IFS( OR(UPPER(S49)="AIR", UPPER(S49)="CPN"), "AIR", UPPER(S49)="TC", "LOCAL", TRUE, "SEA" )} -> AIR | O49: =M49+L49+K49+J49 -> 75.866526 | P49: JP | Q49: 108276176300 | R49: 46167 | S49: AIR | T49: 6.5 | V49: 400000 | Z49: =SUM(V49:Y49) -> 400000 | AA49: 0 | AB49: =+AA49+Z49 -> 400000 | AD49: 1220400 | AE49: 387180 | AF49: =+SUM(AC49:AE49) -> 1607580 | AG49: =+AF49+AB49 -> 2007580 | AI49: =VLOOKUP(Q49,[3]Sheet1!B$11:G$1489,6,0) -> E11
A50: 47 | B50: 8XN5911 | C50: 1591CT6 | D50: KIOXIA CORPORATION C/O KIOXIA AMERICA INC | E50: =IF(OR(AI50="E11", AI50="E13", AI50="E15", AI50="G13"), "Import", "Export") -> Import | F50: {=_xlfn.IFS( OR(AI50="E11", AI50="E15"), "Raw materials", OR(AI50="E13", AI50="G13"), "Equipments + Toolings", TRUE, RIGHT(C50, 8) )} -> Raw materials | G50: {=IF(E50="Import", IFERROR( _xlfn.IFS( VLOOKUP(B50,[1]Material!F$5:U$90000,16,0)="LUC","Lucid", VLOOKUP(B50,[1]Material!F$5:U$90000,16,0)="FMC","FORD", OR(VLOOKUP(B50,[1]Material!F$5:U$90000,16,0)="PUR",VLOOKUP(B50,[1]Material!F$5:U$90000,16,0)="HLO"),"PURE", VLOOKUP(B50,[1]Material!F$5:U$90000,16,0)="AIC","AIC", OR(VLOOKUP(B50,[1]Material!F$5:U$90000,16,0)="AGI",VLOOKUP(B50,[1]Material!F$5:U$90000,16,0)="AGIGA"),"AGIGA", OR(LEFT(VLOOKUP(B50,[1]Material!F$5:U$90000,16,0),3)="EF-",VLOOKUP(B50,[1]Material!F$5:U$90000,16,0)="EFI"),"EFI", AND(ISNUMBER(VLOOKUP(B50,[1]Material!F$5:U$90000,16,0)),VLOOKUP(B50,[1]Material!F$5:U$90000,16,0)>=100,VLOOKUP(B50,[1]Material!F$5:U$90000,16,0)<=999,VLOOKUP(B50,[1]Material!F$5:U$90000,16,0)=INT(VLOOKUP(B50,[1]Material!F$5:U$90000,16,0))),"OEM", TRUE,"" ), "không tìm thấy trong file Import" ), VLOOKUP(F50,'[2]Export shipment'!B:Y,24,0) )} -> PURE | H50: =VLOOKUP(B50,[4]Export!I$3627:J$3668,2,0) -> #N/A | I50: CIP | J50: =(V50+X50+AA50)/'Logistics record '!$AD$1 -> 15.116015 | K50: =W50/'Logistics record '!$AD$1 -> 0 | L50: =Y50/'Logistics record '!$AD$1 -> 0 | M50: =AF50/'Logistics record '!$AD$1 -> 60.75051 | N50: {=_xlfn.IFS( OR(UPPER(S50)="AIR", UPPER(S50)="CPN"), "AIR", UPPER(S50)="TC", "LOCAL", TRUE, "SEA" )} -> AIR | O50: =M50+L50+K50+J50 -> 75.866526 | P50: JP | Q50: 108276180720 | R50: 46167 | S50: AIR | T50: 3.4 | V50: 400000 | Z50: =SUM(V50:Y50) -> 400000 | AA50: 0 | AB50: =+AA50+Z50 -> 400000 | AD50: 1220400 | AE50: 387180 | AF50: =+SUM(AC50:AE50) -> 1607580 | AG50: =+AF50+AB50 -> 2007580 | AI50: =VLOOKUP(Q50,[3]Sheet1!B$11:G$1489,6,0) -> E11
A51: 48 | B51: 8XN5902 | C51: 1591CSX | D51: KIOXIA CORPORATION C/O KIOXIA AMERICA INC | E51: =IF(OR(AI51="E11", AI51="E13", AI51="E15", AI51="G13"), "Import", "Export") -> Import | F51: {=_xlfn.IFS( OR(AI51="E11", AI51="E15"), "Raw materials", OR(AI51="E13", AI51="G13"), "Equipments + Toolings", TRUE, RIGHT(C51, 8) )} -> Raw materials | G51: {=IF(E51="Import", IFERROR( _xlfn.IFS( VLOOKUP(B51,[1]Material!F$5:U$90000,16,0)="LUC","Lucid", VLOOKUP(B51,[1]Material!F$5:U$90000,16,0)="FMC","FORD", OR(VLOOKUP(B51,[1]Material!F$5:U$90000,16,0)="PUR",VLOOKUP(B51,[1]Material!F$5:U$90000,16,0)="HLO"),"PURE", VLOOKUP(B51,[1]Material!F$5:U$90000,16,0)="AIC","AIC", OR(VLOOKUP(B51,[1]Material!F$5:U$90000,16,0)="AGI",VLOOKUP(B51,[1]Material!F$5:U$90000,16,0)="AGIGA"),"AGIGA", OR(LEFT(VLOOKUP(B51,[1]Material!F$5:U$90000,16,0),3)="EF-",VLOOKUP(B51,[1]Material!F$5:U$90000,16,0)="EFI"),"EFI", AND(ISNUMBER(VLOOKUP(B51,[1]Material!F$5:U$90000,16,0)),VLOOKUP(B51,[1]Material!F$5:U$90000,16,0)>=100,VLOOKUP(B51,[1]Material!F$5:U$90000,16,0)<=999,VLOOKUP(B51,[1]Material!F$5:U$90000,16,0)=INT(VLOOKUP(B51,[1]Material!F$5:U$90000,16,0))),"OEM", TRUE,"" ), "không tìm thấy trong file Import" ), VLOOKUP(F51,'[2]Export shipment'!B:Y,24,0) )} -> PURE | H51: =VLOOKUP(B51,[4]Export!I$3627:J$3668,2,0) -> #N/A | I51: CIP | J51: =(V51+X51+AA51)/'Logistics record '!$AD$1 -> 15.116015 | K51: =W51/'Logistics record '!$AD$1 -> 22.674023 | L51: =Y51/'Logistics record '!$AD$1 -> 0 | M51: =AF51/'Logistics record '!$AD$1 -> 60.75051 | N51: {=_xlfn.IFS( OR(UPPER(S51)="AIR", UPPER(S51)="CPN"), "AIR", UPPER(S51)="TC", "LOCAL", TRUE, "SEA" )} -> AIR | O51: =M51+L51+K51+J51 -> 98.540549 | P51: JP | Q51: 108276189930 | R51: 46167 | S51: AIR | T51: 11.8 | V51: 400000 | W51: 600000 | Z51: =SUM(V51:Y51) -> 1000000 | AA51: 0 | AB51: =+AA51+Z51 -> 1000000 | AD51: 1220400 | AE51: 387180 | AF51: =+SUM(AC51:AE51) -> 1607580 | AG51: =+AF51+AB51 -> 2607580 | AI51: =VLOOKUP(Q51,[3]Sheet1!B$11:G$1489,6,0) -> E11
A52: 49 | B52: 8XN5903 | C52: 1591CSY | D52: KIOXIA CORPORATION C/O KIOXIA AMERICA INC | E52: =IF(OR(AI52="E11", AI52="E13", AI52="E15", AI52="G13"), "Import", "Export") -> Import | F52: {=_xlfn.IFS( OR(AI52="E11", AI52="E15"), "Raw materials", OR(AI52="E13", AI52="G13"), "Equipments + Toolings", TRUE, RIGHT(C52, 8) )} -> Raw materials | G52: {=IF(E52="Import", IFERROR( _xlfn.IFS( VLOOKUP(B52,[1]Material!F$5:U$90000,16,0)="LUC","Lucid", VLOOKUP(B52,[1]Material!F$5:U$90000,16,0)="FMC","FORD", OR(VLOOKUP(B52,[1]Material!F$5:U$90000,16,0)="PUR",VLOOKUP(B52,[1]Material!F$5:U$90000,16,0)="HLO"),"PURE", VLOOKUP(B52,[1]Material!F$5:U$90000,16,0)="AIC","AIC", OR(VLOOKUP(B52,[1]Material!F$5:U$90000,16,0)="AGI",VLOOKUP(B52,[1]Material!F$5:U$90000,16,0)="AGIGA"),"AGIGA", OR(LEFT(VLOOKUP(B52,[1]Material!F$5:U$90000,16,0),3)="EF-",VLOOKUP(B52,[1]Material!F$5:U$90000,16,0)="EFI"),"EFI", AND(ISNUMBER(VLOOKUP(B52,[1]Material!F$5:U$90000,16,0)),VLOOKUP(B52,[1]Material!F$5:U$90000,16,0)>=100,VLOOKUP(B52,[1]Material!F$5:U$90000,16,0)<=999,VLOOKUP(B52,[1]Material!F$5:U$90000,16,0)=INT(VLOOKUP(B52,[1]Material!F$5:U$90000,16,0))),"OEM", TRUE,"" ), "không tìm thấy trong file Import" ), VLOOKUP(F52,'[2]Export shipment'!B:Y,24,0) )} -> PURE | H52: =VLOOKUP(B52,[4]Export!I$3627:J$3668,2,0) -> #N/A | I52: CIP | J52: =(V52+X52+AA52)/'Logistics record '!$AD$1 -> 15.116015 | K52: =W52/'Logistics record '!$AD$1 -> 0 | L52: =Y52/'Logistics record '!$AD$1 -> 0 | M52: =AF52/'Logistics record '!$AD$1 -> 60.75051 | N52: {=_xlfn.IFS( OR(UPPER(S52)="AIR", UPPER(S52)="CPN"), "AIR", UPPER(S52)="TC", "LOCAL", TRUE, "SEA" )} -> AIR | O52: =M52+L52+K52+J52 -> 75.866526 | P52: JP | Q52: 108276197040 | R52: 46167 | S52: AIR | T52: 3.4 | V52: 400000 | Z52: =SUM(V52:Y52) -> 400000 | AA52: 0 | AB52: =+AA52+Z52 -> 400000 | AD52: 1220400 | AE52: 387180 | AF52: =+SUM(AC52:AE52) -> 1607580 | AG52: =+AF52+AB52 -> 2007580 | AI52: =VLOOKUP(Q52,[3]Sheet1!B$11:G$1489,6,0) -> E11
A53: 50 | B53: 707296342982 | C53: 21153393 | D53: ARROW COMPONENTS MEXICO SA De CV | E53: =IF(OR(AI53="E11", AI53="E13", AI53="E15", AI53="G13"), "Import", "Export") -> Import | F53: {=_xlfn.IFS( OR(AI53="E11", AI53="E15"), "Raw materials", OR(AI53="E13", AI53="G13"), "Equipments + Toolings", TRUE, RIGHT(C53, 8) )} -> Raw materials | G53: {=IF(E53="Import", IFERROR( _xlfn.IFS( VLOOKUP(B53,[1]Material!F$5:U$90000,16,0)="LUC","Lucid", VLOOKUP(B53,[1]Material!F$5:U$90000,16,0)="FMC","FORD", OR(VLOOKUP(B53,[1]Material!F$5:U$90000,16,0)="PUR",VLOOKUP(B53,[1]Material!F$5:U$90000,16,0)="HLO"),"PURE", VLOOKUP(B53,[1]Material!F$5:U$90000,16,0)="AIC","AIC", OR(VLOOKUP(B53,[1]Material!F$5:U$90000,16,0)="AGI",VLOOKUP(B53,[1]Material!F$5:U$90000,16,0)="AGIGA"),"AGIGA", OR(LEFT(VLOOKUP(B53,[1]Material!F$5:U$90000,16,0),3)="EF-",VLOOKUP(B53,[1]Material!F$5:U$90000,16,0)="EFI"),"EFI", AND(ISNUMBER(VLOOKUP(B53,[1]Material!F$5:U$90000,16,0)),VLOOKUP(B53,[1]Material!F$5:U$90000,16,0)>=100,VLOOKUP(B53,[1]Material!F$5:U$90000,16,0)<=999,VLOOKUP(B53,[1]Material!F$5:U$90000,16,0)=INT(VLOOKUP(B53,[1]Material!F$5:U$90000,16,0))),"OEM", TRUE,"" ), "không tìm thấy trong file Import" ), VLOOKUP(F53,'[2]Export shipment'!B:Y,24,0) )} -> PURE | J53: =(V53+X53+AA53)/'Logistics record '!$AD$1 -> 15.116015 | K53: =W53/'Logistics record '!$AD$1 -> 0 | L53: =Y53/'Logistics record '!$AD$1 -> 0 | M53: =AF53/'Logistics record '!$AD$1 -> 0 | N53: {=_xlfn.IFS( OR(UPPER(S53)="AIR", UPPER(S53)="CPN"), "AIR", UPPER(S53)="TC", "LOCAL", TRUE, "SEA" )} -> AIR | O53: =M53+L53+K53+J53 -> 15.116015 | P53: MX | Q53: 108277141340 | R53: 46168 | S53: CPN | T53: 0.5 | V53: 400000 | Z53: =SUM(V53:Y53) -> 400000 | AA53: 0 | AB53: =+AA53+Z53 -> 400000 | AF53: =+SUM(AC53:AE53) -> 0 | AG53: =+AF53+AB53 -> 400000 | AI53: =VLOOKUP(Q53,[3]Sheet1!B$11:G$1489,6,0) -> E11
A54: 51 | B54: 872115753797 | C54: 2026CYM | D54: CYMMETRIK SHENZHEN PRINTING CO., LTD | E54: =IF(OR(AI54="E11", AI54="E13", AI54="E15", AI54="G13"), "Import", "Export") -> Import | F54: {=_xlfn.IFS( OR(AI54="E11", AI54="E15"), "Raw materials", OR(AI54="E13", AI54="G13"), "Equipments + Toolings", TRUE, RIGHT(C54, 8) )} -> Raw materials | G54: {=IF(E54="Import", IFERROR( _xlfn.IFS( VLOOKUP(B54,[1]Material!F$5:U$90000,16,0)="LUC","Lucid", VLOOKUP(B54,[1]Material!F$5:U$90000,16,0)="FMC","FORD", OR(VLOOKUP(B54,[1]Material!F$5:U$90000,16,0)="PUR",VLOOKUP(B54,[1]Material!F$5:U$90000,16,0)="HLO"),"PURE", VLOOKUP(B54,[1]Material!F$5:U$90000,16,0)="AIC","AIC", OR(VLOOKUP(B54,[1]Material!F$5:U$90000,16,0)="AGI",VLOOKUP(B54,[1]Material!F$5:U$90000,16,0)="AGIGA"),"AGIGA", OR(LEFT(VLOOKUP(B54,[1]Material!F$5:U$90000,16,0),3)="EF-",VLOOKUP(B54,[1]Material!F$5:U$90000,16,0)="EFI"),"EFI", AND(ISNUMBER(VLOOKUP(B54,[1]Material!F$5:U$90000,16,0)),VLOOKUP(B54,[1]Material!F$5:U$90000,16,0)>=100,VLOOKUP(B54,[1]Material!F$5:U$90000,16,0)<=999,VLOOKUP(B54,[1]Material!F$5:U$90000,16,0)=INT(VLOOKUP(B54,[1]Material!F$5:U$90000,16,0))),"OEM", TRUE,"" ), "không tìm thấy trong file Import" ), VLOOKUP(F54,'[2]Export shipment'!B:Y,24,0) )} -> PURE | J54: =(V54+X54+AA54)/'Logistics record '!$AD$1 -> 15.116015 | K54: =W54/'Logistics record '!$AD$1 -> 0 | L54: =Y54/'Logistics record '!$AD$1 -> 0 | M54: =AF54/'Logistics record '!$AD$1 -> 0 | N54: {=_xlfn.IFS( OR(UPPER(S54)="AIR", UPPER(S54)="CPN"), "AIR", UPPER(S54)="TC", "LOCAL", TRUE, "SEA" )} -> AIR | O54: =M54+L54+K54+J54 -> 15.116015 | P54: CN | Q54: 108277159320 | R54: 46168 | S54: CPN | T54: 0.9 | V54: 400000 | Z54: =SUM(V54:Y54) -> 400000 | AA54: 0 | AB54: =+AA54+Z54 -> 400000 | AF54: =+SUM(AC54:AE54) -> 0 | AG54: =+AF54+AB54 -> 400000 | AI54: =VLOOKUP(Q54,[3]Sheet1!B$11:G$1489,6,0) -> E11
A55: 52 | B55: 492830230119 | C55: 030261952 | D55: ARROW ELECTRONICS, INC. | E55: =IF(OR(AI55="E11", AI55="E13", AI55="E15", AI55="G13"), "Import", "Export") -> Import | F55: {=_xlfn.IFS( OR(AI55="E11", AI55="E15"), "Raw materials", OR(AI55="E13", AI55="G13"), "Equipments + Toolings", TRUE, RIGHT(C55, 8) )} -> Raw materials | G55: {=IF(E55="Import", IFERROR( _xlfn.IFS( VLOOKUP(B55,[1]Material!F$5:U$90000,16,0)="LUC","Lucid", VLOOKUP(B55,[1]Material!F$5:U$90000,16,0)="FMC","FORD", OR(VLOOKUP(B55,[1]Material!F$5:U$90000,16,0)="PUR",VLOOKUP(B55,[1]Material!F$5:U$90000,16,0)="HLO"),"PURE", VLOOKUP(B55,[1]Material!F$5:U$90000,16,0)="AIC","AIC", OR(VLOOKUP(B55,[1]Material!F$5:U$90000,16,0)="AGI",VLOOKUP(B55,[1]Material!F$5:U$90000,16,0)="AGIGA"),"AGIGA", OR(LEFT(VLOOKUP(B55,[1]Material!F$5:U$90000,16,0),3)="EF-",VLOOKUP(B55,[1]Material!F$5:U$90000,16,0)="EFI"),"EFI", AND(ISNUMBER(VLOOKUP(B55,[1]Material!F$5:U$90000,16,0)),VLOOKUP(B55,[1]Material!F$5:U$90000,16,0)>=100,VLOOKUP(B55,[1]Material!F$5:U$90000,16,0)<=999,VLOOKUP(B55,[1]Material!F$5:U$90000,16,0)=INT(VLOOKUP(B55,[1]Material!F$5:U$90000,16,0))),"OEM", TRUE,"" ), "không tìm thấy trong file Import" ), VLOOKUP(F55,'[2]Export shipment'!B:Y,24,0) )} -> FORD | J55: =(V55+X55+AA55)/'Logistics record '!$AD$1 -> 15.116015 | K55: =W55/'Logistics record '!$AD$1 -> 0 | L55: =Y55/'Logistics record '!$AD$1 -> 0 | M55: =AF55/'Logistics record '!$AD$1 -> 0 | N55: {=_xlfn.IFS( OR(UPPER(S55)="AIR", UPPER(S55)="CPN"), "AIR", UPPER(S55)="TC", "LOCAL", TRUE, "SEA" )} -> AIR | O55: =M55+L55+K55+J55 -> 15.116015 | P55: US | Q55: 108277197450 | R55: 46168 | S55: CPN | T55: 5.9 | V55: 400000 | Z55: =SUM(V55:Y55) -> 400000 | AA55: 0 | AB55: =+AA55+Z55 -> 400000 | AF55: =+SUM(AC55:AE55) -> 0 | AG55: =+AF55+AB55 -> 400000 | AI55: =VLOOKUP(Q55,[3]Sheet1!B$11:G$1489,6,0) -> E11
A56: 53 | B56: 500292657094 | C56: 21131210 | D56: ARROW COMPONENTS MEXICO SA De CV | E56: =IF(OR(AI56="E11", AI56="E13", AI56="E15", AI56="G13"), "Import", "Export") -> Import | F56: {=_xlfn.IFS( OR(AI56="E11", AI56="E15"), "Raw materials", OR(AI56="E13", AI56="G13"), "Equipments + Toolings", TRUE, RIGHT(C56, 8) )} -> Raw materials | G56: {=IF(E56="Import", IFERROR( _xlfn.IFS( VLOOKUP(B56,[1]Material!F$5:U$90000,16,0)="LUC","Lucid", VLOOKUP(B56,[1]Material!F$5:U$90000,16,0)="FMC","FORD", OR(VLOOKUP(B56,[1]Material!F$5:U$90000,16,0)="PUR",VLOOKUP(B56,[1]Material!F$5:U$90000,16,0)="HLO"),"PURE", VLOOKUP(B56,[1]Material!F$5:U$90000,16,0)="AIC","AIC", OR(VLOOKUP(B56,[1]Material!F$5:U$90000,16,0)="AGI",VLOOKUP(B56,[1]Material!F$5:U$90000,16,0)="AGIGA"),"AGIGA", OR(LEFT(VLOOKUP(B56,[1]Material!F$5:U$90000,16,0),3)="EF-",VLOOKUP(B56,[1]Material!F$5:U$90000,16,0)="EFI"),"EFI", AND(ISNUMBER(VLOOKUP(B56,[1]Material!F$5:U$90000,16,0)),VLOOKUP(B56,[1]Material!F$5:U$90000,16,0)>=100,VLOOKUP(B56,[1]Material!F$5:U$90000,16,0)<=999,VLOOKUP(B56,[1]Material!F$5:U$90000,16,0)=INT(VLOOKUP(B56,[1]Material!F$5:U$90000,16,0))),"OEM", TRUE,"" ), "không tìm thấy trong file Import" ), VLOOKUP(F56,'[2]Export shipment'!B:Y,24,0) )} -> EFI | J56: =(V56+X56+AA56)/'Logistics record '!$AD$1 -> 15.116015 | K56: =W56/'Logistics record '!$AD$1 -> 0 | L56: =Y56/'Logistics record '!$AD$1 -> 0 | M56: =AF56/'Logistics record '!$AD$1 -> 0 | N56: {=_xlfn.IFS( OR(UPPER(S56)="AIR", UPPER(S56)="CPN"), "AIR", UPPER(S56)="TC", "LOCAL", TRUE, "SEA" )} -> AIR | O56: =M56+L56+K56+J56 -> 15.116015 | P56: MX | Q56: 108277316230 | R56: 46168 | S56: CPN | T56: 1.8 | V56: 400000 | Z56: =SUM(V56:Y56) -> 400000 | AA56: 0 | AB56: =+AA56+Z56 -> 400000 | AF56: =+SUM(AC56:AE56) -> 0 | AG56: =+AF56+AB56 -> 400000 | AI56: =VLOOKUP(Q56,[3]Sheet1!B$11:G$1489,6,0) -> E11
A57: 54 | B57: 500292656878 | C57: 21152780 | D57: ARROW COMPONENTS MEXICO SA De CV | E57: =IF(OR(AI57="E11", AI57="E13", AI57="E15", AI57="G13"), "Import", "Export") -> Import | F57: {=_xlfn.IFS( OR(AI57="E11", AI57="E15"), "Raw materials", OR(AI57="E13", AI57="G13"), "Equipments + Toolings", TRUE, RIGHT(C57, 8) )} -> Raw materials | G57: {=IF(E57="Import", IFERROR( _xlfn.IFS( VLOOKUP(B57,[1]Material!F$5:U$90000,16,0)="LUC","Lucid", VLOOKUP(B57,[1]Material!F$5:U$90000,16,0)="FMC","FORD", OR(VLOOKUP(B57,[1]Material!F$5:U$90000,16,0)="PUR",VLOOKUP(B57,[1]Material!F$5:U$90000,16,0)="HLO"),"PURE", VLOOKUP(B57,[1]Material!F$5:U$90000,16,0)="AIC","AIC", OR(VLOOKUP(B57,[1]Material!F$5:U$90000,16,0)="AGI",VLOOKUP(B57,[1]Material!F$5:U$90000,16,0)="AGIGA"),"AGIGA", OR(LEFT(VLOOKUP(B57,[1]Material!F$5:U$90000,16,0),3)="EF-",VLOOKUP(B57,[1]Material!F$5:U$90000,16,0)="EFI"),"EFI", AND(ISNUMBER(VLOOKUP(B57,[1]Material!F$5:U$90000,16,0)),VLOOKUP(B57,[1]Material!F$5:U$90000,16,0)>=100,VLOOKUP(B57,[1]Material!F$5:U$90000,16,0)<=999,VLOOKUP(B57,[1]Material!F$5:U$90000,16,0)=INT(VLOOKUP(B57,[1]Material!F$5:U$90000,16,0))),"OEM", TRUE,"" ), "không tìm thấy trong file Import" ), VLOOKUP(F57,'[2]Export shipment'!B:Y,24,0) )} -> EFI | J57: =(V57+X57+AA57)/'Logistics record '!$AD$1 -> 15.116015 | K57: =W57/'Logistics record '!$AD$1 -> 0 | L57: =Y57/'Logistics record '!$AD$1 -> 0 | M57: =AF57/'Logistics record '!$AD$1 -> 0 | N57: {=_xlfn.IFS( OR(UPPER(S57)="AIR", UPPER(S57)="CPN"), "AIR", UPPER(S57)="TC", "LOCAL", TRUE, "SEA" )} -> AIR | O57: =M57+L57+K57+J57 -> 15.116015 | P57: MX | Q57: 108277360110 | R57: 46168 | S57: CPN | T57: 0.5 | V57: 400000 | Z57: =SUM(V57:Y57) -> 400000 | AA57: 0 | AB57: =+AA57+Z57 -> 400000 | AF57: =+SUM(AC57:AE57) -> 0 | AG57: =+AF57+AB57 -> 400000 | AI57: =VLOOKUP(Q57,[3]Sheet1!B$11:G$1489,6,0) -> E11
A58: 55 | B58: 500292661362 | C58: 21181118 | D58: ARROW COMPONENTS MEXICO SA De CV | E58: =IF(OR(AI58="E11", AI58="E13", AI58="E15", AI58="G13"), "Import", "Export") -> Import | F58: {=_xlfn.IFS( OR(AI58="E11", AI58="E15"), "Raw materials", OR(AI58="E13", AI58="G13"), "Equipments + Toolings", TRUE, RIGHT(C58, 8) )} -> Raw materials | G58: {=IF(E58="Import", IFERROR( _xlfn.IFS( VLOOKUP(B58,[1]Material!F$5:U$90000,16,0)="LUC","Lucid", VLOOKUP(B58,[1]Material!F$5:U$90000,16,0)="FMC","FORD", OR(VLOOKUP(B58,[1]Material!F$5:U$90000,16,0)="PUR",VLOOKUP(B58,[1]Material!F$5:U$90000,16,0)="HLO"),"PURE", VLOOKUP(B58,[1]Material!F$5:U$90000,16,0)="AIC","AIC", OR(VLOOKUP(B58,[1]Material!F$5:U$90000,16,0)="AGI",VLOOKUP(B58,[1]Material!F$5:U$90000,16,0)="AGIGA"),"AGIGA", OR(LEFT(VLOOKUP(B58,[1]Material!F$5:U$90000,16,0),3)="EF-",VLOOKUP(B58,[1]Material!F$5:U$90000,16,0)="EFI"),"EFI", AND(ISNUMBER(VLOOKUP(B58,[1]Material!F$5:U$90000,16,0)),VLOOKUP(B58,[1]Material!F$5:U$90000,16,0)>=100,VLOOKUP(B58,[1]Material!F$5:U$90000,16,0)<=999,VLOOKUP(B58,[1]Material!F$5:U$90000,16,0)=INT(VLOOKUP(B58,[1]Material!F$5:U$90000,16,0))),"OEM", TRUE,"" ), "không tìm thấy trong file Import" ), VLOOKUP(F58,'[2]Export shipment'!B:Y,24,0) )} -> PURE | J58: =(V58+X58+AA58)/'Logistics record '!$AD$1 -> 15.116015 | K58: =W58/'Logistics record '!$AD$1 -> 0 | L58: =Y58/'Logistics record '!$AD$1 -> 0 | M58: =AF58/'Logistics record '!$AD$1 -> 0 | N58: {=_xlfn.IFS( OR(UPPER(S58)="AIR", UPPER(S58)="CPN"), "AIR", UPPER(S58)="TC", "LOCAL", TRUE, "SEA" )} -> AIR | O58: =M58+L58+K58+J58 -> 15.116015 | P58: MX | Q58: 108277380260 | R58: 46168 | S58: CPN | T58: 0.5 | V58: 400000 | Z58: =SUM(V58:Y58) -> 400000 | AA58: 0 | AB58: =+AA58+Z58 -> 400000 | AF58: =+SUM(AC58:AE58) -> 0 | AG58: =+AF58+AB58 -> 400000 | AI58: =VLOOKUP(Q58,[3]Sheet1!B$11:G$1489,6,0) -> E11
A59: 56 | B59: 526750324069 | C59: 126188103 | D59: DIGI-KEY ELECTRONICS | E59: =IF(OR(AI59="E11", AI59="E13", AI59="E15", AI59="G13"), "Import", "Export") -> Import | F59: {=_xlfn.IFS( OR(AI59="E11", AI59="E15"), "Raw materials", OR(AI59="E13", AI59="G13"), "Equipments + Toolings", TRUE, RIGHT(C59, 8) )} -> Raw materials | G59: {=IF(E59="Import", IFERROR( _xlfn.IFS( VLOOKUP(B59,[1]Material!F$5:U$90000,16,0)="LUC","Lucid", VLOOKUP(B59,[1]Material!F$5:U$90000,16,0)="FMC","FORD", OR(VLOOKUP(B59,[1]Material!F$5:U$90000,16,0)="PUR",VLOOKUP(B59,[1]Material!F$5:U$90000,16,0)="HLO"),"PURE", VLOOKUP(B59,[1]Material!F$5:U$90000,16,0)="AIC","AIC", OR(VLOOKUP(B59,[1]Material!F$5:U$90000,16,0)="AGI",VLOOKUP(B59,[1]Material!F$5:U$90000,16,0)="AGIGA"),"AGIGA", OR(LEFT(VLOOKUP(B59,[1]Material!F$5:U$90000,16,0),3)="EF-",VLOOKUP(B59,[1]Material!F$5:U$90000,16,0)="EFI"),"EFI", AND(ISNUMBER(VLOOKUP(B59,[1]Material!F$5:U$90000,16,0)),VLOOKUP(B59,[1]Material!F$5:U$90000,16,0)>=100,VLOOKUP(B59,[1]Material!F$5:U$90000,16,0)<=999,VLOOKUP(B59,[1]Material!F$5:U$90000,16,0)=INT(VLOOKUP(B59,[1]Material!F$5:U$90000,16,0))),"OEM", TRUE,"" ), "không tìm thấy trong file Import" ), VLOOKUP(F59,'[2]Export shipment'!B:Y,24,0) )} -> EFI | J59: =(V59+X59+AA59)/'Logistics record '!$AD$1 -> 15.116015 | K59: =W59/'Logistics record '!$AD$1 -> 0 | L59: =Y59/'Logistics record '!$AD$1 -> 0 | M59: =AF59/'Logistics record '!$AD$1 -> 0 | N59: {=_xlfn.IFS( OR(UPPER(S59)="AIR", UPPER(S59)="CPN"), "AIR", UPPER(S59)="TC", "LOCAL", TRUE, "SEA" )} -> AIR | O59: =M59+L59+K59+J59 -> 15.116015 | P59: US | Q59: 108278127640 | R59: 46168 | S59: CPN | T59: 0.2 | V59: 400000 | Z59: =SUM(V59:Y59) -> 400000 | AA59: 0 | AB59: =+AA59+Z59 -> 400000 | AF59: =+SUM(AC59:AE59) -> 0 | AG59: =+AF59+AB59 -> 400000 | AI59: =VLOOKUP(Q59,[3]Sheet1!B$11:G$1489,6,0) -> E11
A60: 57 | B60: 500292660572 | C60: 21164804 | D60: ARROW COMPONENTS MEXICO SA De CV | E60: =IF(OR(AI60="E11", AI60="E13", AI60="E15", AI60="G13"), "Import", "Export") -> Import | F60: {=_xlfn.IFS( OR(AI60="E11", AI60="E15"), "Raw materials", OR(AI60="E13", AI60="G13"), "Equipments + Toolings", TRUE, RIGHT(C60, 8) )} -> Raw materials | G60: {=IF(E60="Import", IFERROR( _xlfn.IFS( VLOOKUP(B60,[1]Material!F$5:U$90000,16,0)="LUC","Lucid", VLOOKUP(B60,[1]Material!F$5:U$90000,16,0)="FMC","FORD", OR(VLOOKUP(B60,[1]Material!F$5:U$90000,16,0)="PUR",VLOOKUP(B60,[1]Material!F$5:U$90000,16,0)="HLO"),"PURE", VLOOKUP(B60,[1]Material!F$5:U$90000,16,0)="AIC","AIC", OR(VLOOKUP(B60,[1]Material!F$5:U$90000,16,0)="AGI",VLOOKUP(B60,[1]Material!F$5:U$90000,16,0)="AGIGA"),"AGIGA", OR(LEFT(VLOOKUP(B60,[1]Material!F$5:U$90000,16,0),3)="EF-",VLOOKUP(B60,[1]Material!F$5:U$90000,16,0)="EFI"),"EFI", AND(ISNUMBER(VLOOKUP(B60,[1]Material!F$5:U$90000,16,0)),VLOOKUP(B60,[1]Material!F$5:U$90000,16,0)>=100,VLOOKUP(B60,[1]Material!F$5:U$90000,16,0)<=999,VLOOKUP(B60,[1]Material!F$5:U$90000,16,0)=INT(VLOOKUP(B60,[1]Material!F$5:U$90000,16,0))),"OEM", TRUE,"" ), "không tìm thấy trong file Import" ), VLOOKUP(F60,'[2]Export shipment'!B:Y,24,0) )} -> PURE | J60: =(V60+X60+AA60)/'Logistics record '!$AD$1 -> 15.116015 | K60: =W60/'Logistics record '!$AD$1 -> 0 | L60: =Y60/'Logistics record '!$AD$1 -> 0 | M60: =AF60/'Logistics record '!$AD$1 -> 0 | N60: {=_xlfn.IFS( OR(UPPER(S60)="AIR", UPPER(S60)="CPN"), "AIR", UPPER(S60)="TC", "LOCAL", TRUE, "SEA" )} -> AIR | O60: =M60+L60+K60+J60 -> 15.116015 | P60: MX | Q60: 108278214920 | R60: 46168 | S60: CPN | T60: 0.6 | V60: 400000 | Z60: =SUM(V60:Y60) -> 400000 | AA60: 0 | AB60: =+AA60+Z60 -> 400000 | AF60: =+SUM(AC60:AE60) -> 0 | AG60: =+AF60+AB60 -> 400000 | AI60: =VLOOKUP(Q60,[3]Sheet1!B$11:G$1489,6,0) -> E11
A61: 58 | B61: 381501224770 | C61: 334229 | D61: DHL SUPPLY CHAIN MGMT PHILS INC ON BEHALF OF ANALOG DEVICES INT | E61: =IF(OR(AI61="E11", AI61="E13", AI61="E15", AI61="G13"), "Import", "Export") -> Import | F61: {=_xlfn.IFS( OR(AI61="E11", AI61="E15"), "Raw materials", OR(AI61="E13", AI61="G13"), "Equipments + Toolings", TRUE, RIGHT(C61, 8) )} -> Raw materials | G61: {=IF(E61="Import", IFERROR( _xlfn.IFS( VLOOKUP(B61,[1]Material!F$5:U$90000,16,0)="LUC","Lucid", VLOOKUP(B61,[1]Material!F$5:U$90000,16,0)="FMC","FORD", OR(VLOOKUP(B61,[1]Material!F$5:U$90000,16,0)="PUR",VLOOKUP(B61,[1]Material!F$5:U$90000,16,0)="HLO"),"PURE", VLOOKUP(B61,[1]Material!F$5:U$90000,16,0)="AIC","AIC", OR(VLOOKUP(B61,[1]Material!F$5:U$90000,16,0)="AGI",VLOOKUP(B61,[1]Material!F$5:U$90000,16,0)="AGIGA"),"AGIGA", OR(LEFT(VLOOKUP(B61,[1]Material!F$5:U$90000,16,0),3)="EF-",VLOOKUP(B61,[1]Material!F$5:U$90000,16,0)="EFI"),"EFI", AND(ISNUMBER(VLOOKUP(B61,[1]Material!F$5:U$90000,16,0)),VLOOKUP(B61,[1]Material!F$5:U$90000,16,0)>=100,VLOOKUP(B61,[1]Material!F$5:U$90000,16,0)<=999,VLOOKUP(B61,[1]Material!F$5:U$90000,16,0)=INT(VLOOKUP(B61,[1]Material!F$5:U$90000,16,0))),"OEM", TRUE,"" ), "không tìm thấy trong file Import" ), VLOOKUP(F61,'[2]Export shipment'!B:Y,24,0) )} -> PURE | J61: =(V61+X61+AA61)/'Logistics record '!$AD$1 -> 15.116015 | K61: =W61/'Logistics record '!$AD$1 -> 0 | L61: =Y61/'Logistics record '!$AD$1 -> 0 | M61: =AF61/'Logistics record '!$AD$1 -> 0 | N61: {=_xlfn.IFS( OR(UPPER(S61)="AIR", UPPER(S61)="CPN"), "AIR", UPPER(S61)="TC", "LOCAL", TRUE, "SEA" )} -> AIR | O61: =M61+L61+K61+J61 -> 15.116015 | P61: PH | Q61: 108278448830 | R61: 46168 | S61: CPN | T61: 2.2 | V61: 400000 | Z61: =SUM(V61:Y61) -> 400000 | AA61: 0 | AB61: =+AA61+Z61 -> 400000 | AF61: =+SUM(AC61:AE61) -> 0 | AG61: =+AF61+AB61 -> 400000 | AI61: =VLOOKUP(Q61,[3]Sheet1!B$11:G$1489,6,0) -> E11
